Workbook

Sheet Guide
B1: APD Project Tracker
B2: A single-file, OneDrive/SharePoint-hosted version of the APD Project Management Dashboard (without the AI features).
B4: Getting started
B5: 1. Add a project | C5: Go to Projects and type the project name in the first empty row (column A). Everything else on that row is optional; grey columns calculate themselves.
B6: 2. Log records | C6: On any register sheet, pick the Project from the dropdown in column A and fill in the row. Dropdowns, date and number checks are built in.
B7: 3. View results | C7: Dashboard shows the portfolio, alerts and upcoming work. Project Summary (pick a project in C3) is a printable one-page report. Gantt draws the selected project's milestones. Charts shows the trends.
B8: 4. Example rows | C8: This is the blank copy: every sheet is empty and ready for your data.
B10: Colour key
B11: Blue text | C11: Input cells - type here.
B12: Grey cells / grey headers | C12: Formulas - do not overwrite (Project Health, budgets, buckets, flags, ranks).
B13: Yellow | C13: Selector cells (Project Summary C3, Search B3).
B14: Green / Amber / Red | C14: Health ratings. Schedule and Budget: green below 95%, amber 95-115%, red above 115% (same rules as the web app). Risk: red if any open Critical risk, amber if any High.
B16: How the numbers work (same rules as the web tool)
B17: Effective budget | C17: Latest Approved Budget if entered, otherwise Original Budget plus approved Variations.
B18: Forecast at completion | C18: For each project and month, an Actual replaces that month's Forecast - they are never added together. Enter one line per project, month and type.
B19: Revised completion | C19: Target Completion plus days from approved EOT Claims (Days Granted, or Days Claimed if none recorded).
B20: Overdue project | C20: Target Completion has passed and the status is not Project Completion, Defects Liability, Complete or Cancelled.
B21: Risk score | C21: Likelihood (1-5) x Consequence (1-5): 16+ Critical, 10-15 High, 5-9 Medium, below 5 Low.
B23: Limits (fixed row capacity - extend by copying the last formula row down)
B24: Projects | C24: 100
B25: Tasks | C25: 1,000
B26: Cash Flow | C26: 2,000
B27: Every other register | C27: 500 rows each
B28: Dashboard portfolio table | C28: Shows the first 30 projects; the Projects sheet always shows all.
B30: Macros (optional - see the VBA folder)
B31: What they add | C31: Global search across every sheet, an automatic Activity Log (who changed what, when), recurring tasks (marking a recurring task Done creates the next one), one-click PDF of the Project Summary, a dated backup copy, and an Outlook email digest of overdue / expiring items.
B32: Without macros | C32: Everything above that is a formula still works - dashboard, health, alerts, summary, Gantt, charts, dropdowns. Use Ctrl+F (Within: Workbook) for search.
B34: Keeping the data in your company's OneDrive / SharePoint
B35: Where to save | C35: Save this file in a OneDrive for Business or SharePoint document library your IT department approves. The data then lives in the company tenant under its retention, backup and access policies.
B36: Access control | C36: Use the library's sharing settings: Edit for the project team, View for read-only stakeholders. Excel Version History restores earlier versions.
B37: Co-authoring | C37: Several people can edit the same .xlsx at once in Excel desktop or the browser. Avoid sorting a register while others are editing it.
B38: What is not in a spreadsheet | C38: Per-user logins and per-project permissions, file attachments, site photo upload/map, scheduled emails and the AI assistant. Link to files in SharePoint (link columns on Documents, Meeting Minutes and Site Visits) instead.
B40: Sheet index
B41: Dashboard | C41: Portfolio table, alerts, today & upcoming, top risks.
B42: Project Summary | C42: One-page report for the selected project.
B43: Gantt | C43: Weekly bar chart of the selected project's milestones.
B44: Charts | C44: Status, budget vs forecast, S-curve, risk bands.
B45: Search | C45: Cross-sheet search (needs the macros).
B46: Projects | C46: One row per project. Grey columns are formulas - do not type in them.
B47: Tasks | C47: Register - one row per record.
B48: Actions | C48: Register - one row per record.
B49: Risks | C49: Register - one row per record.
B50: RFIs | C50: Register - one row per record.
B51: Defects | C51: Register - one row per record.
B52: Variations | C52: Register - one row per record.
... B78: Calc | C78: Chart working figures.

Sheet Dashboard
A1: APD Project Management Dashboard | F1: As at | G1: =TODAY() -> 46306
A2: Every figure here is a live formula over the register sheets.
A4: Total Projects | C4: In Construction | E4: Overdue Projects | G4: Total Approved Budget
A5: =COUNTA(Projects!$A$2:$A$101) -> 0 | C5: =COUNTIF(Projects!$D$2:$D$101,"Construction") -> 0 | E5: =COUNTIF(Projects!$X$2:$X$101,"Overdue") -> 0 | G5: =SUM(Projects!$R$2:$R$101) -> 0
A7: Portfolio (first 30 projects - full list on the Projects sheet)
A8: Project | B8: Status | C8: Project Manager | D8: Revised Completion | E8: Effective Budget | F8: Forecast at Completion | G8: Budget Variance | H8: Schedule | I8: Budget | J8: Risk | K8: Overall | L8: Open Tasks | M8: Open Actions | N8: Open RFIs | O8: Open Defects
A9: =IF(INDEX(Projects!$A$2:$A$101,ROWS(A$9:A9))="","",INDEX(Projects!$A$2:$A$101,ROWS(A$9:A9))) | B9: =IF($A9="","",IFERROR(IF(INDEX(Projects!$D$2:$D$101,MATCH($A9,Projects!$A$2:$A$101,0))="","",INDEX(Projects!$D$2:$D$101,MATCH($A9,Projects!$A$2:$A$101,0))),"")) | C9: =IF($A9="","",IFERROR(IF(INDEX(Projects!$F$2:$F$101,MATCH($A9,Projects!$A$2:$A$101,0))="","",INDEX(Projects!$F$2:$F$101,MATCH($A9,Projects!$A$2:$A$101,0))),"")) | D9: =IF($A9="","",IFERROR(IF(INDEX(Projects!$W$2:$W$101,MATCH($A9,Projects!$A$2:$A$101,0))="","",INDEX(Projects!$W$2:$W$101,MATCH($A9,Projects!$A$2:$A$101,0))),"")) | E9: =IF($A9="","",IFERROR(IF(INDEX(Projects!$R$2:$R$101,MATCH($A9,Projects!$A$2:$A$101,0))="","",INDEX(Projects!$R$2:$R$101,MATCH($A9,Projects!$A$2:$A$101,0))),"")) | F9: =IF($A9="","",IFERROR(IF(INDEX(Projects!$T$2:$T$101,MATCH($A9,Projects!$A$2:$A$101,0))="","",INDEX(Projects!$T$2:$T$101,MATCH($A9,Projects!$A$2:$A$101,0))),"")) | G9: =IF($A9="","",IFERROR(IF(INDEX(Projects!$U$2:$U$101,MATCH($A9,Projects!$A$2:$A$101,0))="","",INDEX(Projects!$U$2:$U$101,MATCH($A9,Projects!$A$2:$A$101,0))),"")) | H9: =IF($A9="","",IFERROR(IF(INDEX(Projects!$Z$2:$Z$101,MATCH($A9,Projects!$A$2:$A$101,0))="","",INDEX(Projects!$Z$2:$Z$101,MATCH($A9,Projects!$A$2:$A$101,0))),"")) | I9: =IF($A9="","",IFERROR(IF(INDEX(Projects!$AB$2:$AB$101,MATCH($A9,Projects!$A$2:$A$101,0))="","",INDEX(Projects!$AB$2:$AB$101,MATCH($A9,Projects!$A$2:$A$101,0))),"")) | J9: =IF($A9="","",IFERROR(IF(INDEX(Projects!$AE$2:$AE$101,MATCH($A9,Projects!$A$2:$A$101,0))="","",INDEX(Projects!$AE$2:$AE$101,MATCH($A9,Projects!$A$2:$A$101,0))),"")) | K9: =IF($A9="","",IFERROR(IF(INDEX(Projects!$AF$2:$AF$101,MATCH($A9,Projects!$A$2:$A$101,0))="","",INDEX(Projects!$AF$2:$AF$101,MATCH($A9,Projects!$A$2:$A$101,0))),"")) | L9: =IF($A9="","",IFERROR(IF(INDEX(Projects!$AG$2:$AG$101,MATCH($A9,Projects!$A$2:$A$101,0))="","",INDEX(Projects!$AG$2:$AG$101,MATCH($A9,Projects!$A$2:$A$101,0))),"")) | M9: =IF($A9="","",IFERROR(IF(INDEX(Projects!$AH$2:$AH$101,MATCH($A9,Projects!$A$2:$A$101,0))="","",INDEX(Projects!$AH$2:$AH$101,MATCH($A9,Projects!$A$2:$A$101,0))),"")) | N9: =IF($A9="","",IFERROR(IF(INDEX(Projects!$AI$2:$AI$101,MATCH($A9,Projects!$A$2:$A$101,0))="","",INDEX(Projects!$AI$2:$AI$101,MATCH($A9,Projects!$A$2:$A$101,0))),"")) | O9: =IF($A9="","",IFERROR(IF(INDEX(Projects!$AJ$2:$AJ$101,MATCH($A9,Projects!$A$2:$A$101,0))="","",INDEX(Projects!$AJ$2:$AJ$101,MATCH($A9,Projects!$A$2:$A$101,0))),""))
A10: =IF(INDEX(Projects!$A$2:$A$101,ROWS(A$9:A10))="","",INDEX(Projects!$A$2:$A$101,ROWS(A$9:A10))) | B10: =IF($A10="","",IFERROR(IF(INDEX(Projects!$D$2:$D$101,MATCH($A10,Projects!$A$2:$A$101,0))="","",INDEX(Projects!$D$2:$D$101,MATCH($A10,Projects!$A$2:$A$101,0))),"")) | C10: =IF($A10="","",IFERROR(IF(INDEX(Projects!$F$2:$F$101,MATCH($A10,Projects!$A$2:$A$101,0))="","",INDEX(Projects!$F$2:$F$101,MATCH($A10,Projects!$A$2:$A$101,0))),"")) | D10: =IF($A10="","",IFERROR(IF(INDEX(Projects!$W$2:$W$101,MATCH($A10,Projects!$A$2:$A$101,0))="","",INDEX(Projects!$W$2:$W$101,MATCH($A10,Projects!$A$2:$A$101,0))),"")) | E10: =IF($A10="","",IFERROR(IF(INDEX(Projects!$R$2:$R$101,MATCH($A10,Projects!$A$2:$A$101,0))="","",INDEX(Projects!$R$2:$R$101,MATCH($A10,Projects!$A$2:$A$101,0))),"")) | F10: =IF($A10="","",IFERROR(IF(INDEX(Projects!$T$2:$T$101,MATCH($A10,Projects!$A$2:$A$101,0))="","",INDEX(Projects!$T$2:$T$101,MATCH($A10,Projects!$A$2:$A$101,0))),"")) | G10: =IF($A10="","",IFERROR(IF(INDEX(Projects!$U$2:$U$101,MATCH($A10,Projects!$A$2:$A$101,0))="","",INDEX(Projects!$U$2:$U$101,MATCH($A10,Projects!$A$2:$A$101,0))),"")) | H10: =IF($A10="","",IFERROR(IF(INDEX(Projects!$Z$2:$Z$101,MATCH($A10,Projects!$A$2:$A$101,0))="","",INDEX(Projects!$Z$2:$Z$101,MATCH($A10,Projects!$A$2:$A$101,0))),"")) | I10: =IF($A10="","",IFERROR(IF(INDEX(Projects!$AB$2:$AB$101,MATCH($A10,Projects!$A$2:$A$101,0))="","",INDEX(Projects!$AB$2:$AB$101,MATCH($A10,Projects!$A$2:$A$101,0))),"")) | J10: =IF($A10="","",IFERROR(IF(INDEX(Projects!$AE$2:$AE$101,MATCH($A10,Projects!$A$2:$A$101,0))="","",INDEX(Projects!$AE$2:$AE$101,MATCH($A10,Projects!$A$2:$A$101,0))),"")) | K10: =IF($A10="","",IFERROR(IF(INDEX(Projects!$AF$2:$AF$101,MATCH($A10,Projects!$A$2:$A$101,0))="","",INDEX(Projects!$AF$2:$AF$101,MATCH($A10,Projects!$A$2:$A$101,0))),"")) | L10: =IF($A10="","",IFERROR(IF(INDEX(Projects!$AG$2:$AG$101,MATCH($A10,Projects!$A$2:$A$101,0))="","",INDEX(Projects!$AG$2:$AG$101,MATCH($A10,Projects!$A$2:$A$101,0))),"")) | M10: =IF($A10="","",IFERROR(IF(INDEX(Projects!$AH$2:$AH$101,MATCH($A10,Projects!$A$2:$A$101,0))="","",INDEX(Projects!$AH$2:$AH$101,MATCH($A10,Projects!$A$2:$A$101,0))),"")) | N10: =IF($A10="","",IFERROR(IF(INDEX(Projects!$AI$2:$AI$101,MATCH($A10,Projects!$A$2:$A$101,0))="","",INDEX(Projects!$AI$2:$AI$101,MATCH($A10,Projects!$A$2:$A$101,0))),"")) | O10: =IF($A10="","",IFERROR(IF(INDEX(Projects!$AJ$2:$AJ$101,MATCH($A10,Projects!$A$2:$A$101,0))="","",INDEX(Projects!$AJ$2:$AJ$101,MATCH($A10,Projects!$A$2:$A$101,0))),""))
A11: =IF(INDEX(Projects!$A$2:$A$101,ROWS(A$9:A11))="","",INDEX(Projects!$A$2:$A$101,ROWS(A$9:A11))) | B11: =IF($A11="","",IFERROR(IF(INDEX(Projects!$D$2:$D$101,MATCH($A11,Projects!$A$2:$A$101,0))="","",INDEX(Projects!$D$2:$D$101,MATCH($A11,Projects!$A$2:$A$101,0))),"")) | C11: =IF($A11="","",IFERROR(IF(INDEX(Projects!$F$2:$F$101,MATCH($A11,Projects!$A$2:$A$101,0))="","",INDEX(Projects!$F$2:$F$101,MATCH($A11,Projects!$A$2:$A$101,0))),"")) | D11: =IF($A11="","",IFERROR(IF(INDEX(Projects!$W$2:$W$101,MATCH($A11,Projects!$A$2:$A$101,0))="","",INDEX(Projects!$W$2:$W$101,MATCH($A11,Projects!$A$2:$A$101,0))),"")) | E11: =IF($A11="","",IFERROR(IF(INDEX(Projects!$R$2:$R$101,MATCH($A11,Projects!$A$2:$A$101,0))="","",INDEX(Projects!$R$2:$R$101,MATCH($A11,Projects!$A$2:$A$101,0))),"")) | F11: =IF($A11="","",IFERROR(IF(INDEX(Projects!$T$2:$T$101,MATCH($A11,Projects!$A$2:$A$101,0))="","",INDEX(Projects!$T$2:$T$101,MATCH($A11,Projects!$A$2:$A$101,0))),"")) | G11: =IF($A11="","",IFERROR(IF(INDEX(Projects!$U$2:$U$101,MATCH($A11,Projects!$A$2:$A$101,0))="","",INDEX(Projects!$U$2:$U$101,MATCH($A11,Projects!$A$2:$A$101,0))),"")) | H11: =IF($A11="","",IFERROR(IF(INDEX(Projects!$Z$2:$Z$101,MATCH($A11,Projects!$A$2:$A$101,0))="","",INDEX(Projects!$Z$2:$Z$101,MATCH($A11,Projects!$A$2:$A$101,0))),"")) | I11: =IF($A11="","",IFERROR(IF(INDEX(Projects!$AB$2:$AB$101,MATCH($A11,Projects!$A$2:$A$101,0))="","",INDEX(Projects!$AB$2:$AB$101,MATCH($A11,Projects!$A$2:$A$101,0))),"")) | J11: =IF($A11="","",IFERROR(IF(INDEX(Projects!$AE$2:$AE$101,MATCH($A11,Projects!$A$2:$A$101,0))="","",INDEX(Projects!$AE$2:$AE$101,MATCH($A11,Projects!$A$2:$A$101,0))),"")) | K11: =IF($A11="","",IFERROR(IF(INDEX(Projects!$AF$2:$AF$101,MATCH($A11,Projects!$A$2:$A$101,0))="","",INDEX(Projects!$AF$2:$AF$101,MATCH($A11,Projects!$A$2:$A$101,0))),"")) | L11: =IF($A11="","",IFERROR(IF(INDEX(Projects!$AG$2:$AG$101,MATCH($A11,Projects!$A$2:$A$101,0))="","",INDEX(Projects!$AG$2:$AG$101,MATCH($A11,Projects!$A$2:$A$101,0))),"")) | M11: =IF($A11="","",IFERROR(IF(INDEX(Projects!$AH$2:$AH$101,MATCH($A11,Projects!$A$2:$A$101,0))="","",INDEX(Projects!$AH$2:$AH$101,MATCH($A11,Projects!$A$2:$A$101,0))),"")) | N11: =IF($A11="","",IFERROR(IF(INDEX(Projects!$AI$2:$AI$101,MATCH($A11,Projects!$A$2:$A$101,0))="","",INDEX(Projects!$AI$2:$AI$101,MATCH($A11,Projects!$A$2:$A$101,0))),"")) | O11: =IF($A11="","",IFERROR(IF(INDEX(Projects!$AJ$2:$AJ$101,MATCH($A11,Projects!$A$2:$A$101,0))="","",INDEX(Projects!$AJ$2:$AJ$101,MATCH($A11,Projects!$A$2:$A$101,0))),""))
A12: =IF(INDEX(Projects!$A$2:$A$101,ROWS(A$9:A12))="","",INDEX(Projects!$A$2:$A$101,ROWS(A$9:A12))) | B12: =IF($A12="","",IFERROR(IF(INDEX(Projects!$D$2:$D$101,MATCH($A12,Projects!$A$2:$A$101,0))="","",INDEX(Projects!$D$2:$D$101,MATCH($A12,Projects!$A$2:$A$101,0))),"")) | C12: =IF($A12="","",IFERROR(IF(INDEX(Projects!$F$2:$F$101,MATCH($A12,Projects!$A$2:$A$101,0))="","",INDEX(Projects!$F$2:$F$101,MATCH($A12,Projects!$A$2:$A$101,0))),"")) | D12: =IF($A12="","",IFERROR(IF(INDEX(Projects!$W$2:$W$101,MATCH($A12,Projects!$A$2:$A$101,0))="","",INDEX(Projects!$W$2:$W$101,MATCH($A12,Projects!$A$2:$A$101,0))),"")) | E12: =IF($A12="","",IFERROR(IF(INDEX(Projects!$R$2:$R$101,MATCH($A12,Projects!$A$2:$A$101,0))="","",INDEX(Projects!$R$2:$R$101,MATCH($A12,Projects!$A$2:$A$101,0))),"")) | F12: =IF($A12="","",IFERROR(IF(INDEX(Projects!$T$2:$T$101,MATCH($A12,Projects!$A$2:$A$101,0))="","",INDEX(Projects!$T$2:$T$101,MATCH($A12,Projects!$A$2:$A$101,0))),"")) | G12: =IF($A12="","",IFERROR(IF(INDEX(Projects!$U$2:$U$101,MATCH($A12,Projects!$A$2:$A$101,0))="","",INDEX(Projects!$U$2:$U$101,MATCH($A12,Projects!$A$2:$A$101,0))),"")) | H12: =IF($A12="","",IFERROR(IF(INDEX(Projects!$Z$2:$Z$101,MATCH($A12,Projects!$A$2:$A$101,0))="","",INDEX(Projects!$Z$2:$Z$101,MATCH($A12,Projects!$A$2:$A$101,0))),"")) | I12: =IF($A12="","",IFERROR(IF(INDEX(Projects!$AB$2:$AB$101,MATCH($A12,Projects!$A$2:$A$101,0))="","",INDEX(Projects!$AB$2:$AB$101,MATCH($A12,Projects!$A$2:$A$101,0))),"")) | J12: =IF($A12="","",IFERROR(IF(INDEX(Projects!$AE$2:$AE$101,MATCH($A12,Projects!$A$2:$A$101,0))="","",INDEX(Projects!$AE$2:$AE$101,MATCH($A12,Projects!$A$2:$A$101,0))),"")) | K12: =IF($A12="","",IFERROR(IF(INDEX(Projects!$AF$2:$AF$101,MATCH($A12,Projects!$A$2:$A$101,0))="","",INDEX(Projects!$AF$2:$AF$101,MATCH($A12,Projects!$A$2:$A$101,0))),"")) | L12: =IF($A12="","",IFERROR(IF(INDEX(Projects!$AG$2:$AG$101,MATCH($A12,Projects!$A$2:$A$101,0))="","",INDEX(Projects!$AG$2:$AG$101,MATCH($A12,Projects!$A$2:$A$101,0))),"")) | M12: =IF($A12="","",IFERROR(IF(INDEX(Projects!$AH$2:$AH$101,MATCH($A12,Projects!$A$2:$A$101,0))="","",INDEX(Projects!$AH$2:$AH$101,MATCH($A12,Projects!$A$2:$A$101,0))),"")) | N12: =IF($A12="","",IFERROR(IF(INDEX(Projects!$AI$2:$AI$101,MATCH($A12,Projects!$A$2:$A$101,0))="","",INDEX(Projects!$AI$2:$AI$101,MATCH($A12,Projects!$A$2:$A$101,0))),"")) | O12: =IF($A12="","",IFERROR(IF(INDEX(Projects!$AJ$2:$AJ$101,MATCH($A12,Projects!$A$2:$A$101,0))="","",INDEX(Projects!$AJ$2:$AJ$101,MATCH($A12,Projects!$A$2:$A$101,0))),""))
A13: =IF(INDEX(Projects!$A$2:$A$101,ROWS(A$9:A13))="","",INDEX(Projects!$A$2:$A$101,ROWS(A$9:A13))) | B13: =IF($A13="","",IFERROR(IF(INDEX(Projects!$D$2:$D$101,MATCH($A13,Projects!$A$2:$A$101,0))="","",INDEX(Projects!$D$2:$D$101,MATCH($A13,Projects!$A$2:$A$101,0))),"")) | C13: =IF($A13="","",IFERROR(IF(INDEX(Projects!$F$2:$F$101,MATCH($A13,Projects!$A$2:$A$101,0))="","",INDEX(Projects!$F$2:$F$101,MATCH($A13,Projects!$A$2:$A$101,0))),"")) | D13: =IF($A13="","",IFERROR(IF(INDEX(Projects!$W$2:$W$101,MATCH($A13,Projects!$A$2:$A$101,0))="","",INDEX(Projects!$W$2:$W$101,MATCH($A13,Projects!$A$2:$A$101,0))),"")) | E13: =IF($A13="","",IFERROR(IF(INDEX(Projects!$R$2:$R$101,MATCH($A13,Projects!$A$2:$A$101,0))="","",INDEX(Projects!$R$2:$R$101,MATCH($A13,Projects!$A$2:$A$101,0))),"")) | F13: =IF($A13="","",IFERROR(IF(INDEX(Projects!$T$2:$T$101,MATCH($A13,Projects!$A$2:$A$101,0))="","",INDEX(Projects!$T$2:$T$101,MATCH($A13,Projects!$A$2:$A$101,0))),"")) | G13: =IF($A13="","",IFERROR(IF(INDEX(Projects!$U$2:$U$101,MATCH($A13,Projects!$A$2:$A$101,0))="","",INDEX(Projects!$U$2:$U$101,MATCH($A13,Projects!$A$2:$A$101,0))),"")) | H13: =IF($A13="","",IFERROR(IF(INDEX(Projects!$Z$2:$Z$101,MATCH($A13,Projects!$A$2:$A$101,0))="","",INDEX(Projects!$Z$2:$Z$101,MATCH($A13,Projects!$A$2:$A$101,0))),"")) | I13: =IF($A13="","",IFERROR(IF(INDEX(Projects!$AB$2:$AB$101,MATCH($A13,Projects!$A$2:$A$101,0))="","",INDEX(Projects!$AB$2:$AB$101,MATCH($A13,Projects!$A$2:$A$101,0))),"")) | J13: =IF($A13="","",IFERROR(IF(INDEX(Projects!$AE$2:$AE$101,MATCH($A13,Projects!$A$2:$A$101,0))="","",INDEX(Projects!$AE$2:$AE$101,MATCH($A13,Projects!$A$2:$A$101,0))),"")) | K13: =IF($A13="","",IFERROR(IF(INDEX(Projects!$AF$2:$AF$101,MATCH($A13,Projects!$A$2:$A$101,0))="","",INDEX(Projects!$AF$2:$AF$101,MATCH($A13,Projects!$A$2:$A$101,0))),"")) | L13: =IF($A13="","",IFERROR(IF(INDEX(Projects!$AG$2:$AG$101,MATCH($A13,Projects!$A$2:$A$101,0))="","",INDEX(Projects!$AG$2:$AG$101,MATCH($A13,Projects!$A$2:$A$101,0))),"")) | M13: =IF($A13="","",IFERROR(IF(INDEX(Projects!$AH$2:$AH$101,MATCH($A13,Projects!$A$2:$A$101,0))="","",INDEX(Projects!$AH$2:$AH$101,MATCH($A13,Projects!$A$2:$A$101,0))),"")) | N13: =IF($A13="","",IFERROR(IF(INDEX(Projects!$AI$2:$AI$101,MATCH($A13,Projects!$A$2:$A$101,0))="","",INDEX(Projects!$AI$2:$AI$101,MATCH($A13,Projects!$A$2:$A$101,0))),"")) | O13: =IF($A13="","",IFERROR(IF(INDEX(Projects!$AJ$2:$AJ$101,MATCH($A13,Projects!$A$2:$A$101,0))="","",INDEX(Projects!$AJ$2:$AJ$101,MATCH($A13,Projects!$A$2:$A$101,0))),""))
A14: =IF(INDEX(Projects!$A$2:$A$101,ROWS(A$9:A14))="","",INDEX(Projects!$A$2:$A$101,ROWS(A$9:A14))) | B14: =IF($A14="","",IFERROR(IF(INDEX(Projects!$D$2:$D$101,MATCH($A14,Projects!$A$2:$A$101,0))="","",INDEX(Projects!$D$2:$D$101,MATCH($A14,Projects!$A$2:$A$101,0))),"")) | C14: =IF($A14="","",IFERROR(IF(INDEX(Projects!$F$2:$F$101,MATCH($A14,Projects!$A$2:$A$101,0))="","",INDEX(Projects!$F$2:$F$101,MATCH($A14,Projects!$A$2:$A$101,0))),"")) | D14: =IF($A14="","",IFERROR(IF(INDEX(Projects!$W$2:$W$101,MATCH($A14,Projects!$A$2:$A$101,0))="","",INDEX(Projects!$W$2:$W$101,MATCH($A14,Projects!$A$2:$A$101,0))),"")) | E14: =IF($A14="","",IFERROR(IF(INDEX(Projects!$R$2:$R$101,MATCH($A14,Projects!$A$2:$A$101,0))="","",INDEX(Projects!$R$2:$R$101,MATCH($A14,Projects!$A$2:$A$101,0))),"")) | F14: =IF($A14="","",IFERROR(IF(INDEX(Projects!$T$2:$T$101,MATCH($A14,Projects!$A$2:$A$101,0))="","",INDEX(Projects!$T$2:$T$101,MATCH($A14,Projects!$A$2:$A$101,0))),"")) | G14: =IF($A14="","",IFERROR(IF(INDEX(Projects!$U$2:$U$101,MATCH($A14,Projects!$A$2:$A$101,0))="","",INDEX(Projects!$U$2:$U$101,MATCH($A14,Projects!$A$2:$A$101,0))),"")) | H14: =IF($A14="","",IFERROR(IF(INDEX(Projects!$Z$2:$Z$101,MATCH($A14,Projects!$A$2:$A$101,0))="","",INDEX(Projects!$Z$2:$Z$101,MATCH($A14,Projects!$A$2:$A$101,0))),"")) | I14: =IF($A14="","",IFERROR(IF(INDEX(Projects!$AB$2:$AB$101,MATCH($A14,Projects!$A$2:$A$101,0))="","",INDEX(Projects!$AB$2:$AB$101,MATCH($A14,Projects!$A$2:$A$101,0))),"")) | J14: =IF($A14="","",IFERROR(IF(INDEX(Projects!$AE$2:$AE$101,MATCH($A14,Projects!$A$2:$A$101,0))="","",INDEX(Projects!$AE$2:$AE$101,MATCH($A14,Projects!$A$2:$A$101,0))),"")) | K14: =IF($A14="","",IFERROR(IF(INDEX(Projects!$AF$2:$AF$101,MATCH($A14,Projects!$A$2:$A$101,0))="","",INDEX(Projects!$AF$2:$AF$101,MATCH($A14,Projects!$A$2:$A$101,0))),"")) | L14: =IF($A14="","",IFERROR(IF(INDEX(Projects!$AG$2:$AG$101,MATCH($A14,Projects!$A$2:$A$101,0))="","",INDEX(Projects!$AG$2:$AG$101,MATCH($A14,Projects!$A$2:$A$101,0))),"")) | M14: =IF($A14="","",IFERROR(IF(INDEX(Projects!$AH$2:$AH$101,MATCH($A14,Projects!$A$2:$A$101,0))="","",INDEX(Projects!$AH$2:$AH$101,MATCH($A14,Projects!$A$2:$A$101,0))),"")) | N14: =IF($A14="","",IFERROR(IF(INDEX(Projects!$AI$2:$AI$101,MATCH($A14,Projects!$A$2:$A$101,0))="","",INDEX(Projects!$AI$2:$AI$101,MATCH($A14,Projects!$A$2:$A$101,0))),"")) | O14: =IF($A14="","",IFERROR(IF(INDEX(Projects!$AJ$2:$AJ$101,MATCH($A14,Projects!$A$2:$A$101,0))="","",INDEX(Projects!$AJ$2:$AJ$101,MATCH($A14,Projects!$A$2:$A$101,0))),""))
A15: =IF(INDEX(Projects!$A$2:$A$101,ROWS(A$9:A15))="","",INDEX(Projects!$A$2:$A$101,ROWS(A$9:A15))) | B15: =IF($A15="","",IFERROR(IF(INDEX(Projects!$D$2:$D$101,MATCH($A15,Projects!$A$2:$A$101,0))="","",INDEX(Projects!$D$2:$D$101,MATCH($A15,Projects!$A$2:$A$101,0))),"")) | C15: =IF($A15="","",IFERROR(IF(INDEX(Projects!$F$2:$F$101,MATCH($A15,Projects!$A$2:$A$101,0))="","",INDEX(Projects!$F$2:$F$101,MATCH($A15,Projects!$A$2:$A$101,0))),"")) | D15: =IF($A15="","",IFERROR(IF(INDEX(Projects!$W$2:$W$101,MATCH($A15,Projects!$A$2:$A$101,0))="","",INDEX(Projects!$W$2:$W$101,MATCH($A15,Projects!$A$2:$A$101,0))),"")) | E15: =IF($A15="","",IFERROR(IF(INDEX(Projects!$R$2:$R$101,MATCH($A15,Projects!$A$2:$A$101,0))="","",INDEX(Projects!$R$2:$R$101,MATCH($A15,Projects!$A$2:$A$101,0))),"")) | F15: =IF($A15="","",IFERROR(IF(INDEX(Projects!$T$2:$T$101,MATCH($A15,Projects!$A$2:$A$101,0))="","",INDEX(Projects!$T$2:$T$101,MATCH($A15,Projects!$A$2:$A$101,0))),"")) | G15: =IF($A15="","",IFERROR(IF(INDEX(Projects!$U$2:$U$101,MATCH($A15,Projects!$A$2:$A$101,0))="","",INDEX(Projects!$U$2:$U$101,MATCH($A15,Projects!$A$2:$A$101,0))),"")) | H15: =IF($A15="","",IFERROR(IF(INDEX(Projects!$Z$2:$Z$101,MATCH($A15,Projects!$A$2:$A$101,0))="","",INDEX(Projects!$Z$2:$Z$101,MATCH($A15,Projects!$A$2:$A$101,0))),"")) | I15: =IF($A15="","",IFERROR(IF(INDEX(Projects!$AB$2:$AB$101,MATCH($A15,Projects!$A$2:$A$101,0))="","",INDEX(Projects!$AB$2:$AB$101,MATCH($A15,Projects!$A$2:$A$101,0))),"")) | J15: =IF($A15="","",IFERROR(IF(INDEX(Projects!$AE$2:$AE$101,MATCH($A15,Projects!$A$2:$A$101,0))="","",INDEX(Projects!$AE$2:$AE$101,MATCH($A15,Projects!$A$2:$A$101,0))),"")) | K15: =IF($A15="","",IFERROR(IF(INDEX(Projects!$AF$2:$AF$101,MATCH($A15,Projects!$A$2:$A$101,0))="","",INDEX(Projects!$AF$2:$AF$101,MATCH($A15,Projects!$A$2:$A$101,0))),"")) | L15: =IF($A15="","",IFERROR(IF(INDEX(Projects!$AG$2:$AG$101,MATCH($A15,Projects!$A$2:$A$101,0))="","",INDEX(Projects!$AG$2:$AG$101,MATCH($A15,Projects!$A$2:$A$101,0))),"")) | M15: =IF($A15="","",IFERROR(IF(INDEX(Projects!$AH$2:$AH$101,MATCH($A15,Projects!$A$2:$A$101,0))="","",INDEX(Projects!$AH$2:$AH$101,MATCH($A15,Projects!$A$2:$A$101,0))),"")) | N15: =IF($A15="","",IFERROR(IF(INDEX(Projects!$AI$2:$AI$101,MATCH($A15,Projects!$A$2:$A$101,0))="","",INDEX(Projects!$AI$2:$AI$101,MATCH($A15,Projects!$A$2:$A$101,0))),"")) | O15: =IF($A15="","",IFERROR(IF(INDEX(Projects!$AJ$2:$AJ$101,MATCH($A15,Projects!$A$2:$A$101,0))="","",INDEX(Projects!$AJ$2:$AJ$101,MATCH($A15,Projects!$A$2:$A$101,0))),""))
A16: =IF(INDEX(Projects!$A$2:$A$101,ROWS(A$9:A16))="","",INDEX(Projects!$A$2:$A$101,ROWS(A$9:A16))) | B16: =IF($A16="","",IFERROR(IF(INDEX(Projects!$D$2:$D$101,MATCH($A16,Projects!$A$2:$A$101,0))="","",INDEX(Projects!$D$2:$D$101,MATCH($A16,Projects!$A$2:$A$101,0))),"")) | C16: =IF($A16="","",IFERROR(IF(INDEX(Projects!$F$2:$F$101,MATCH($A16,Projects!$A$2:$A$101,0))="","",INDEX(Projects!$F$2:$F$101,MATCH($A16,Projects!$A$2:$A$101,0))),"")) | D16: =IF($A16="","",IFERROR(IF(INDEX(Projects!$W$2:$W$101,MATCH($A16,Projects!$A$2:$A$101,0))="","",INDEX(Projects!$W$2:$W$101,MATCH($A16,Projects!$A$2:$A$101,0))),"")) | E16: =IF($A16="","",IFERROR(IF(INDEX(Projects!$R$2:$R$101,MATCH($A16,Projects!$A$2:$A$101,0))="","",INDEX(Projects!$R$2:$R$101,MATCH($A16,Projects!$A$2:$A$101,0))),"")) | F16: =IF($A16="","",IFERROR(IF(INDEX(Projects!$T$2:$T$101,MATCH($A16,Projects!$A$2:$A$101,0))="","",INDEX(Projects!$T$2:$T$101,MATCH($A16,Projects!$A$2:$A$101,0))),"")) | G16: =IF($A16="","",IFERROR(IF(INDEX(Projects!$U$2:$U$101,MATCH($A16,Projects!$A$2:$A$101,0))="","",INDEX(Projects!$U$2:$U$101,MATCH($A16,Projects!$A$2:$A$101,0))),"")) | H16: =IF($A16="","",IFERROR(IF(INDEX(Projects!$Z$2:$Z$101,MATCH($A16,Projects!$A$2:$A$101,0))="","",INDEX(Projects!$Z$2:$Z$101,MATCH($A16,Projects!$A$2:$A$101,0))),"")) | I16: =IF($A16="","",IFERROR(IF(INDEX(Projects!$AB$2:$AB$101,MATCH($A16,Projects!$A$2:$A$101,0))="","",INDEX(Projects!$AB$2:$AB$101,MATCH($A16,Projects!$A$2:$A$101,0))),"")) | J16: =IF($A16="","",IFERROR(IF(INDEX(Projects!$AE$2:$AE$101,MATCH($A16,Projects!$A$2:$A$101,0))="","",INDEX(Projects!$AE$2:$AE$101,MATCH($A16,Projects!$A$2:$A$101,0))),"")) | K16: =IF($A16="","",IFERROR(IF(INDEX(Projects!$AF$2:$AF$101,MATCH($A16,Projects!$A$2:$A$101,0))="","",INDEX(Projects!$AF$2:$AF$101,MATCH($A16,Projects!$A$2:$A$101,0))),"")) | L16: =IF($A16="","",IFERROR(IF(INDEX(Projects!$AG$2:$AG$101,MATCH($A16,Projects!$A$2:$A$101,0))="","",INDEX(Projects!$AG$2:$AG$101,MATCH($A16,Projects!$A$2:$A$101,0))),"")) | M16: =IF($A16="","",IFERROR(IF(INDEX(Projects!$AH$2:$AH$101,MATCH($A16,Projects!$A$2:$A$101,0))="","",INDEX(Projects!$AH$2:$AH$101,MATCH($A16,Projects!$A$2:$A$101,0))),"")) | N16: =IF($A16="","",IFERROR(IF(INDEX(Projects!$AI$2:$AI$101,MATCH($A16,Projects!$A$2:$A$101,0))="","",INDEX(Projects!$AI$2:$AI$101,MATCH($A16,Projects!$A$2:$A$101,0))),"")) | O16: =IF($A16="","",IFERROR(IF(INDEX(Projects!$AJ$2:$AJ$101,MATCH($A16,Projects!$A$2:$A$101,0))="","",INDEX(Projects!$AJ$2:$AJ$101,MATCH($A16,Projects!$A$2:$A$101,0))),""))
A17: =IF(INDEX(Projects!$A$2:$A$101,ROWS(A$9:A17))="","",INDEX(Projects!$A$2:$A$101,ROWS(A$9:A17))) | B17: =IF($A17="","",IFERROR(IF(INDEX(Projects!$D$2:$D$101,MATCH($A17,Projects!$A$2:$A$101,0))="","",INDEX(Projects!$D$2:$D$101,MATCH($A17,Projects!$A$2:$A$101,0))),"")) | C17: =IF($A17="","",IFERROR(IF(INDEX(Projects!$F$2:$F$101,MATCH($A17,Projects!$A$2:$A$101,0))="","",INDEX(Projects!$F$2:$F$101,MATCH($A17,Projects!$A$2:$A$101,0))),"")) | D17: =IF($A17="","",IFERROR(IF(INDEX(Projects!$W$2:$W$101,MATCH($A17,Projects!$A$2:$A$101,0))="","",INDEX(Projects!$W$2:$W$101,MATCH($A17,Projects!$A$2:$A$101,0))),"")) | E17: =IF($A17="","",IFERROR(IF(INDEX(Projects!$R$2:$R$101,MATCH($A17,Projects!$A$2:$A$101,0))="","",INDEX(Projects!$R$2:$R$101,MATCH($A17,Projects!$A$2:$A$101,0))),"")) | F17: =IF($A17="","",IFERROR(IF(INDEX(Projects!$T$2:$T$101,MATCH($A17,Projects!$A$2:$A$101,0))="","",INDEX(Projects!$T$2:$T$101,MATCH($A17,Projects!$A$2:$A$101,0))),"")) | G17: =IF($A17="","",IFERROR(IF(INDEX(Projects!$U$2:$U$101,MATCH($A17,Projects!$A$2:$A$101,0))="","",INDEX(Projects!$U$2:$U$101,MATCH($A17,Projects!$A$2:$A$101,0))),"")) | H17: =IF($A17="","",IFERROR(IF(INDEX(Projects!$Z$2:$Z$101,MATCH($A17,Projects!$A$2:$A$101,0))="","",INDEX(Projects!$Z$2:$Z$101,MATCH($A17,Projects!$A$2:$A$101,0))),"")) | I17: =IF($A17="","",IFERROR(IF(INDEX(Projects!$AB$2:$AB$101,MATCH($A17,Projects!$A$2:$A$101,0))="","",INDEX(Projects!$AB$2:$AB$101,MATCH($A17,Projects!$A$2:$A$101,0))),"")) | J17: =IF($A17="","",IFERROR(IF(INDEX(Projects!$AE$2:$AE$101,MATCH($A17,Projects!$A$2:$A$101,0))="","",INDEX(Projects!$AE$2:$AE$101,MATCH($A17,Projects!$A$2:$A$101,0))),"")) | K17: =IF($A17="","",IFERROR(IF(INDEX(Projects!$AF$2:$AF$101,MATCH($A17,Projects!$A$2:$A$101,0))="","",INDEX(Projects!$AF$2:$AF$101,MATCH($A17,Projects!$A$2:$A$101,0))),"")) | L17: =IF($A17="","",IFERROR(IF(INDEX(Projects!$AG$2:$AG$101,MATCH($A17,Projects!$A$2:$A$101,0))="","",INDEX(Projects!$AG$2:$AG$101,MATCH($A17,Projects!$A$2:$A$101,0))),"")) | M17: =IF($A17="","",IFERROR(IF(INDEX(Projects!$AH$2:$AH$101,MATCH($A17,Projects!$A$2:$A$101,0))="","",INDEX(Projects!$AH$2:$AH$101,MATCH($A17,Projects!$A$2:$A$101,0))),"")) | N17: =IF($A17="","",IFERROR(IF(INDEX(Projects!$AI$2:$AI$101,MATCH($A17,Projects!$A$2:$A$101,0))="","",INDEX(Projects!$AI$2:$AI$101,MATCH($A17,Projects!$A$2:$A$101,0))),"")) | O17: =IF($A17="","",IFERROR(IF(INDEX(Projects!$AJ$2:$AJ$101,MATCH($A17,Projects!$A$2:$A$101,0))="","",INDEX(Projects!$AJ$2:$AJ$101,MATCH($A17,Projects!$A$2:$A$101,0))),""))
A18: =IF(INDEX(Projects!$A$2:$A$101,ROWS(A$9:A18))="","",INDEX(Projects!$A$2:$A$101,ROWS(A$9:A18))) | B18: =IF($A18="","",IFERROR(IF(INDEX(Projects!$D$2:$D$101,MATCH($A18,Projects!$A$2:$A$101,0))="","",INDEX(Projects!$D$2:$D$101,MATCH($A18,Projects!$A$2:$A$101,0))),"")) | C18: =IF($A18="","",IFERROR(IF(INDEX(Projects!$F$2:$F$101,MATCH($A18,Projects!$A$2:$A$101,0))="","",INDEX(Projects!$F$2:$F$101,MATCH($A18,Projects!$A$2:$A$101,0))),"")) | D18: =IF($A18="","",IFERROR(IF(INDEX(Projects!$W$2:$W$101,MATCH($A18,Projects!$A$2:$A$101,0))="","",INDEX(Projects!$W$2:$W$101,MATCH($A18,Projects!$A$2:$A$101,0))),"")) | E18: =IF($A18="","",IFERROR(IF(INDEX(Projects!$R$2:$R$101,MATCH($A18,Projects!$A$2:$A$101,0))="","",INDEX(Projects!$R$2:$R$101,MATCH($A18,Projects!$A$2:$A$101,0))),"")) | F18: =IF($A18="","",IFERROR(IF(INDEX(Projects!$T$2:$T$101,MATCH($A18,Projects!$A$2:$A$101,0))="","",INDEX(Projects!$T$2:$T$101,MATCH($A18,Projects!$A$2:$A$101,0))),"")) | G18: =IF($A18="","",IFERROR(IF(INDEX(Projects!$U$2:$U$101,MATCH($A18,Projects!$A$2:$A$101,0))="","",INDEX(Projects!$U$2:$U$101,MATCH($A18,Projects!$A$2:$A$101,0))),"")) | H18: =IF($A18="","",IFERROR(IF(INDEX(Projects!$Z$2:$Z$101,MATCH($A18,Projects!$A$2:$A$101,0))="","",INDEX(Projects!$Z$2:$Z$101,MATCH($A18,Projects!$A$2:$A$101,0))),"")) | I18: =IF($A18="","",IFERROR(IF(INDEX(Projects!$AB$2:$AB$101,MATCH($A18,Projects!$A$2:$A$101,0))="","",INDEX(Projects!$AB$2:$AB$101,MATCH($A18,Projects!$A$2:$A$101,0))),"")) | J18: =IF($A18="","",IFERROR(IF(INDEX(Projects!$AE$2:$AE$101,MATCH($A18,Projects!$A$2:$A$101,0))="","",INDEX(Projects!$AE$2:$AE$101,MATCH($A18,Projects!$A$2:$A$101,0))),"")) | K18: =IF($A18="","",IFERROR(IF(INDEX(Projects!$AF$2:$AF$101,MATCH($A18,Projects!$A$2:$A$101,0))="","",INDEX(Projects!$AF$2:$AF$101,MATCH($A18,Projects!$A$2:$A$101,0))),"")) | L18: =IF($A18="","",IFERROR(IF(INDEX(Projects!$AG$2:$AG$101,MATCH($A18,Projects!$A$2:$A$101,0))="","",INDEX(Projects!$AG$2:$AG$101,MATCH($A18,Projects!$A$2:$A$101,0))),"")) | M18: =IF($A18="","",IFERROR(IF(INDEX(Projects!$AH$2:$AH$101,MATCH($A18,Projects!$A$2:$A$101,0))="","",INDEX(Projects!$AH$2:$AH$101,MATCH($A18,Projects!$A$2:$A$101,0))),"")) | N18: =IF($A18="","",IFERROR(IF(INDEX(Projects!$AI$2:$AI$101,MATCH($A18,Projects!$A$2:$A$101,0))="","",INDEX(Projects!$AI$2:$AI$101,MATCH($A18,Projects!$A$2:$A$101,0))),"")) | O18: =IF($A18="","",IFERROR(IF(INDEX(Projects!$AJ$2:$AJ$101,MATCH($A18,Projects!$A$2:$A$101,0))="","",INDEX(Projects!$AJ$2:$AJ$101,MATCH($A18,Projects!$A$2:$A$101,0))),""))
A19: =IF(INDEX(Projects!$A$2:$A$101,ROWS(A$9:A19))="","",INDEX(Projects!$A$2:$A$101,ROWS(A$9:A19))) | B19: =IF($A19="","",IFERROR(IF(INDEX(Projects!$D$2:$D$101,MATCH($A19,Projects!$A$2:$A$101,0))="","",INDEX(Projects!$D$2:$D$101,MATCH($A19,Projects!$A$2:$A$101,0))),"")) | C19: =IF($A19="","",IFERROR(IF(INDEX(Projects!$F$2:$F$101,MATCH($A19,Projects!$A$2:$A$101,0))="","",INDEX(Projects!$F$2:$F$101,MATCH($A19,Projects!$A$2:$A$101,0))),"")) | D19: =IF($A19="","",IFERROR(IF(INDEX(Projects!$W$2:$W$101,MATCH($A19,Projects!$A$2:$A$101,0))="","",INDEX(Projects!$W$2:$W$101,MATCH($A19,Projects!$A$2:$A$101,0))),"")) | E19: =IF($A19="","",IFERROR(IF(INDEX(Projects!$R$2:$R$101,MATCH($A19,Projects!$A$2:$A$101,0))="","",INDEX(Projects!$R$2:$R$101,MATCH($A19,Projects!$A$2:$A$101,0))),"")) | F19: =IF($A19="","",IFERROR(IF(INDEX(Projects!$T$2:$T$101,MATCH($A19,Projects!$A$2:$A$101,0))="","",INDEX(Projects!$T$2:$T$101,MATCH($A19,Projects!$A$2:$A$101,0))),"")) | G19: =IF($A19="","",IFERROR(IF(INDEX(Projects!$U$2:$U$101,MATCH($A19,Projects!$A$2:$A$101,0))="","",INDEX(Projects!$U$2:$U$101,MATCH($A19,Projects!$A$2:$A$101,0))),"")) | H19: =IF($A19="","",IFERROR(IF(INDEX(Projects!$Z$2:$Z$101,MATCH($A19,Projects!$A$2:$A$101,0))="","",INDEX(Projects!$Z$2:$Z$101,MATCH($A19,Projects!$A$2:$A$101,0))),"")) | I19: =IF($A19="","",IFERROR(IF(INDEX(Projects!$AB$2:$AB$101,MATCH($A19,Projects!$A$2:$A$101,0))="","",INDEX(Projects!$AB$2:$AB$101,MATCH($A19,Projects!$A$2:$A$101,0))),"")) | J19: =IF($A19="","",IFERROR(IF(INDEX(Projects!$AE$2:$AE$101,MATCH($A19,Projects!$A$2:$A$101,0))="","",INDEX(Projects!$AE$2:$AE$101,MATCH($A19,Projects!$A$2:$A$101,0))),"")) | K19: =IF($A19="","",IFERROR(IF(INDEX(Projects!$AF$2:$AF$101,MATCH($A19,Projects!$A$2:$A$101,0))="","",INDEX(Projects!$AF$2:$AF$101,MATCH($A19,Projects!$A$2:$A$101,0))),"")) | L19: =IF($A19="","",IFERROR(IF(INDEX(Projects!$AG$2:$AG$101,MATCH($A19,Projects!$A$2:$A$101,0))="","",INDEX(Projects!$AG$2:$AG$101,MATCH($A19,Projects!$A$2:$A$101,0))),"")) | M19: =IF($A19="","",IFERROR(IF(INDEX(Projects!$AH$2:$AH$101,MATCH($A19,Projects!$A$2:$A$101,0))="","",INDEX(Projects!$AH$2:$AH$101,MATCH($A19,Projects!$A$2:$A$101,0))),"")) | N19: =IF($A19="","",IFERROR(IF(INDEX(Projects!$AI$2:$AI$101,MATCH($A19,Projects!$A$2:$A$101,0))="","",INDEX(Projects!$AI$2:$AI$101,MATCH($A19,Projects!$A$2:$A$101,0))),"")) | O19: =IF($A19="","",IFERROR(IF(INDEX(Projects!$AJ$2:$AJ$101,MATCH($A19,Projects!$A$2:$A$101,0))="","",INDEX(Projects!$AJ$2:$AJ$101,MATCH($A19,Projects!$A$2:$A$101,0))),""))
A20: =IF(INDEX(Projects!$A$2:$A$101,ROWS(A$9:A20))="","",INDEX(Projects!$A$2:$A$101,ROWS(A$9:A20))) | B20: =IF($A20="","",IFERROR(IF(INDEX(Projects!$D$2:$D$101,MATCH($A20,Projects!$A$2:$A$101,0))="","",INDEX(Projects!$D$2:$D$101,MATCH($A20,Projects!$A$2:$A$101,0))),"")) | C20: =IF($A20="","",IFERROR(IF(INDEX(Projects!$F$2:$F$101,MATCH($A20,Projects!$A$2:$A$101,0))="","",INDEX(Projects!$F$2:$F$101,MATCH($A20,Projects!$A$2:$A$101,0))),"")) | D20: =IF($A20="","",IFERROR(IF(INDEX(Projects!$W$2:$W$101,MATCH($A20,Projects!$A$2:$A$101,0))="","",INDEX(Projects!$W$2:$W$101,MATCH($A20,Projects!$A$2:$A$101,0))),"")) | E20: =IF($A20="","",IFERROR(IF(INDEX(Projects!$R$2:$R$101,MATCH($A20,Projects!$A$2:$A$101,0))="","",INDEX(Projects!$R$2:$R$101,MATCH($A20,Projects!$A$2:$A$101,0))),"")) | F20: =IF($A20="","",IFERROR(IF(INDEX(Projects!$T$2:$T$101,MATCH($A20,Projects!$A$2:$A$101,0))="","",INDEX(Projects!$T$2:$T$101,MATCH($A20,Projects!$A$2:$A$101,0))),"")) | G20: =IF($A20="","",IFERROR(IF(INDEX(Projects!$U$2:$U$101,MATCH($A20,Projects!$A$2:$A$101,0))="","",INDEX(Projects!$U$2:$U$101,MATCH($A20,Projects!$A$2:$A$101,0))),"")) | H20: =IF($A20="","",IFERROR(IF(INDEX(Projects!$Z$2:$Z$101,MATCH($A20,Projects!$A$2:$A$101,0))="","",INDEX(Projects!$Z$2:$Z$101,MATCH($A20,Projects!$A$2:$A$101,0))),"")) | I20: =IF($A20="","",IFERROR(IF(INDEX(Projects!$AB$2:$AB$101,MATCH($A20,Projects!$A$2:$A$101,0))="","",INDEX(Projects!$AB$2:$AB$101,MATCH($A20,Projects!$A$2:$A$101,0))),"")) | J20: =IF($A20="","",IFERROR(IF(INDEX(Projects!$AE$2:$AE$101,MATCH($A20,Projects!$A$2:$A$101,0))="","",INDEX(Projects!$AE$2:$AE$101,MATCH($A20,Projects!$A$2:$A$101,0))),"")) | K20: =IF($A20="","",IFERROR(IF(INDEX(Projects!$AF$2:$AF$101,MATCH($A20,Projects!$A$2:$A$101,0))="","",INDEX(Projects!$AF$2:$AF$101,MATCH($A20,Projects!$A$2:$A$101,0))),"")) | L20: =IF($A20="","",IFERROR(IF(INDEX(Projects!$AG$2:$AG$101,MATCH($A20,Projects!$A$2:$A$101,0))="","",INDEX(Projects!$AG$2:$AG$101,MATCH($A20,Projects!$A$2:$A$101,0))),"")) | M20: =IF($A20="","",IFERROR(IF(INDEX(Projects!$AH$2:$AH$101,MATCH($A20,Projects!$A$2:$A$101,0))="","",INDEX(Projects!$AH$2:$AH$101,MATCH($A20,Projects!$A$2:$A$101,0))),"")) | N20: =IF($A20="","",IFERROR(IF(INDEX(Projects!$AI$2:$AI$101,MATCH($A20,Projects!$A$2:$A$101,0))="","",INDEX(Projects!$AI$2:$AI$101,MATCH($A20,Projects!$A$2:$A$101,0))),"")) | O20: =IF($A20="","",IFERROR(IF(INDEX(Projects!$AJ$2:$AJ$101,MATCH($A20,Projects!$A$2:$A$101,0))="","",INDEX(Projects!$AJ$2:$AJ$101,MATCH($A20,Projects!$A$2:$A$101,0))),""))
... A38: =IF(INDEX(Projects!$A$2:$A$101,ROWS(A$9:A38))="","",INDEX(Projects!$A$2:$A$101,ROWS(A$9:A38))) | B38: =IF($A38="","",IFERROR(IF(INDEX(Projects!$D$2:$D$101,MATCH($A38,Projects!$A$2:$A$101,0))="","",INDEX(Projects!$D$2:$D$101,MATCH($A38,Projects!$A$2:$A$101,0))),"")) | C38: =IF($A38="","",IFERROR(IF(INDEX(Projects!$F$2:$F$101,MATCH($A38,Projects!$A$2:$A$101,0))="","",INDEX(Projects!$F$2:$F$101,MATCH($A38,Projects!$A$2:$A$101,0))),"")) | D38: =IF($A38="","",IFERROR(IF(INDEX(Projects!$W$2:$W$101,MATCH($A38,Projects!$A$2:$A$101,0))="","",INDEX(Projects!$W$2:$W$101,MATCH($A38,Projects!$A$2:$A$101,0))),"")) | E38: =IF($A38="","",IFERROR(IF(INDEX(Projects!$R$2:$R$101,MATCH($A38,Projects!$A$2:$A$101,0))="","",INDEX(Projects!$R$2:$R$101,MATCH($A38,Projects!$A$2:$A$101,0))),"")) | F38: =IF($A38="","",IFERROR(IF(INDEX(Projects!$T$2:$T$101,MATCH($A38,Projects!$A$2:$A$101,0))="","",INDEX(Projects!$T$2:$T$101,MATCH($A38,Projects!$A$2:$A$101,0))),"")) | G38: =IF($A38="","",IFERROR(IF(INDEX(Projects!$U$2:$U$101,MATCH($A38,Projects!$A$2:$A$101,0))="","",INDEX(Projects!$U$2:$U$101,MATCH($A38,Projects!$A$2:$A$101,0))),"")) | H38: =IF($A38="","",IFERROR(IF(INDEX(Projects!$Z$2:$Z$101,MATCH($A38,Projects!$A$2:$A$101,0))="","",INDEX(Projects!$Z$2:$Z$101,MATCH($A38,Projects!$A$2:$A$101,0))),"")) | I38: =IF($A38="","",IFERROR(IF(INDEX(Projects!$AB$2:$AB$101,MATCH($A38,Projects!$A$2:$A$101,0))="","",INDEX(Projects!$AB$2:$AB$101,MATCH($A38,Projects!$A$2:$A$101,0))),"")) | J38: =IF($A38="","",IFERROR(IF(INDEX(Projects!$AE$2:$AE$101,MATCH($A38,Projects!$A$2:$A$101,0))="","",INDEX(Projects!$AE$2:$AE$101,MATCH($A38,Projects!$A$2:$A$101,0))),"")) | K38: =IF($A38="","",IFERROR(IF(INDEX(Projects!$AF$2:$AF$101,MATCH($A38,Projects!$A$2:$A$101,0))="","",INDEX(Projects!$AF$2:$AF$101,MATCH($A38,Projects!$A$2:$A$101,0))),"")) | L38: =IF($A38="","",IFERROR(IF(INDEX(Projects!$AG$2:$AG$101,MATCH($A38,Projects!$A$2:$A$101,0))="","",INDEX(Projects!$AG$2:$AG$101,MATCH($A38,Projects!$A$2:$A$101,0))),"")) | M38: =IF($A38="","",IFERROR(IF(INDEX(Projects!$AH$2:$AH$101,MATCH($A38,Projects!$A$2:$A$101,0))="","",INDEX(Projects!$AH$2:$AH$101,MATCH($A38,Projects!$A$2:$A$101,0))),"")) | N38: =IF($A38="","",IFERROR(IF(INDEX(Projects!$AI$2:$AI$101,MATCH($A38,Projects!$A$2:$A$101,0))="","",INDEX(Projects!$AI$2:$AI$101,MATCH($A38,Projects!$A$2:$A$101,0))),"")) | O38: =IF($A38="","",IFERROR(IF(INDEX(Projects!$AJ$2:$AJ$101,MATCH($A38,Projects!$A$2:$A$101,0))="","",INDEX(Projects!$AJ$2:$AJ$101,MATCH($A38,Projects!$A$2:$A$101,0))),""))
A41: Alerts | E41: Today & Upcoming
A42: Alert | B42: Count | E42: Due | F42: Tasks | G42: Actions | H42: Total
A43: Projects past target completion | B43: =COUNTIF(Projects!$X$2:$X$101,"Overdue") -> 0 | E43: Overdue | F43: =COUNTIF(Tasks!$H$2:$H$1001,E43) -> 0 | G43: =COUNTIF(Actions!$M$2:$M$501,E43) -> 0 | H43: =F43+G43 -> 0
A44: Projects with Red overall health | B44: =COUNTIF(Projects!$AF$2:$AF$101,"Red") -> 0 | E44: Due Today | F44: =COUNTIF(Tasks!$H$2:$H$1001,E44) -> 0 | G44: =COUNTIF(Actions!$M$2:$M$501,E44) -> 0 | H44: =F44+G44 -> 0
A45: Overdue tasks | B45: =COUNTIF(Tasks!$H$2:$H$1001,"Overdue") -> 0 | E45: Due This Week | F45: =COUNTIF(Tasks!$H$2:$H$1001,E45) -> 0 | G45: =COUNTIF(Actions!$M$2:$M$501,E45) -> 0 | H45: =F45+G45 -> 0
A46: Overdue actions / decisions | B46: =COUNTIF(Actions!$M$2:$M$501,"Overdue") -> 0 | E46: Later | F46: =COUNTIF(Tasks!$H$2:$H$1001,E46) -> 0 | G46: =COUNTIF(Actions!$M$2:$M$501,E46) -> 0 | H46: =F46+G46 -> 0
A47: Overdue RFIs | B47: =COUNTIF(RFIs!$L$2:$L$501,"Overdue") -> 0 | E47: No Due Date | F47: =COUNTIF(Tasks!$H$2:$H$1001,E47) -> 0 | G47: =COUNTIF(Actions!$M$2:$M$501,E47) -> 0 | H47: =F47+G47 -> 0
A48: RFIs due within 7 days | B48: =COUNTIF(RFIs!$L$2:$L$501,"Due Soon") -> 0
A49: Overdue defects | B49: =COUNTIF(Defects!$M$2:$M$501,"Overdue") -> 0
A50: Overdue correspondence responses | B50: =COUNTIF(Correspondence!$L$2:$L$501,"Overdue") -> 0
A51: Overdue risk actions | B51: =COUNTIF(Risks!$R$2:$R$501,"Overdue") -> 0
A52: Overdue commissioning / handover items | B52: =COUNTIF(Checklist!$J$2:$J$501,"Overdue") -> 0
A53: Permits expired or expiring (60 days) | B53: =COUNTIF(Permits!$K$2:$K$501,"Expired")+COUNTIF(Permits!$K$2:$K$501,"Expiring Soon") -> 0
A54: Insurance / warranties expired or expiring | B54: =COUNTIF('Insurance Warranties'!$J$2:$J$501,"Expired")+COUNTIF('Insurance Warranties'!$J$2:$J$501,"Expiring Soon") -> 0
A55: Subcontractor insurance expired or expiring | B55: =COUNTIF(Subcontractors!$L$2:$L$501,"Expired")+COUNTIF(Subcontractors!$L$2:$L$501,"Expiring Soon") -> 0
A56: Training records expired or expiring | B56: =COUNTIF('Training Records'!$I$2:$I$501,"Expired")+COUNTIF('Training Records'!$I$2:$I$501,"Expiring Soon") -> 0
A57: Environmental exceedances | B57: =COUNTIF('Env Monitoring'!$K$2:$K$501,"Exceedance") -> 0
A58: Open High / Critical SQE issues | B58: =COUNTIFS('SQE Issues'!$C$2:$C$501,"High",'SQE Issues'!$H$2:$H$501,"<>Closed")+COUNTIFS('SQE Issues'!$C$2:$C$501,"Critical",'SQE Issues'!$H$2:$H$501,"<>Closed") -> 0
A59: Payment claims awaiting certification | B59: =COUNTIF('Payment Claims'!$G$2:$G$501,"Submitted") -> 0
A62: Upcoming tasks (next 15 open, soonest first) | F62: Upcoming actions & decisions (next 15 open)
A63: Task | B63: Project | C63: Due | D63: Bucket | F63: Action | G63: Project | H63: Owner | I63: Due | J63: Bucket
A64: =IFERROR(IF(INDEX(Tasks!$B$2:$B$1001,MATCH(SMALL(Tasks!$I$2:$I$1001,ROWS(A$64:A64)),Tasks!$I$2:$I$1001,0))="","",INDEX(Tasks!$B$2:$B$1001,MATCH(SMALL(Tasks!$I$2:$I$1001,ROWS(A$64:A64)),Tasks!$I$2:$I$1001,0))),"") | B64: =IFERROR(IF(INDEX(Tasks!$A$2:$A$1001,MATCH(SMALL(Tasks!$I$2:$I$1001,ROWS(A$64:A64)),Tasks!$I$2:$I$1001,0))="","",INDEX(Tasks!$A$2:$A$1001,MATCH(SMALL(Tasks!$I$2:$I$1001,ROWS(A$64:A64)),Tasks!$I$2:$I$1001,0))),"") | C64: =IFERROR(IF(INDEX(Tasks!$E$2:$E$1001,MATCH(SMALL(Tasks!$I$2:$I$1001,ROWS(A$64:A64)),Tasks!$I$2:$I$1001,0))="","",INDEX(Tasks!$E$2:$E$1001,MATCH(SMALL(Tasks!$I$2:$I$1001,ROWS(A$64:A64)),Tasks!$I$2:$I$1001,0))),"") | D64: =IFERROR(IF(INDEX(Tasks!$H$2:$H$1001,MATCH(SMALL(Tasks!$I$2:$I$1001,ROWS(A$64:A64)),Tasks!$I$2:$I$1001,0))="","",INDEX(Tasks!$H$2:$H$1001,MATCH(SMALL(Tasks!$I$2:$I$1001,ROWS(A$64:A64)),Tasks!$I$2:$I$1001,0))),"") | F64: =IFERROR(IF(INDEX(Actions!$C$2:$C$501,MATCH(SMALL(Actions!$N$2:$N$501,ROWS(F$64:F64)),Actions!$N$2:$N$501,0))="","",INDEX(Actions!$C$2:$C$501,MATCH(SMALL(Actions!$N$2:$N$501,ROWS(F$64:F64)),Actions!$N$2:$N$501,0))),"") | G64: =IFERROR(IF(INDEX(Actions!$A$2:$A$501,MATCH(SMALL(Actions!$N$2:$N$501,ROWS(F$64:F64)),Actions!$N$2:$N$501,0))="","",INDEX(Actions!$A$2:$A$501,MATCH(SMALL(Actions!$N$2:$N$501,ROWS(F$64:F64)),Actions!$N$2:$N$501,0))),"") | H64: =IFERROR(IF(INDEX(Actions!$F$2:$F$501,MATCH(SMALL(Actions!$N$2:$N$501,ROWS(F$64:F64)),Actions!$N$2:$N$501,0))="","",INDEX(Actions!$F$2:$F$501,MATCH(SMALL(Actions!$N$2:$N$501,ROWS(F$64:F64)),Actions!$N$2:$N$501,0))),"") | I64: =IFERROR(IF(INDEX(Actions!$G$2:$G$501,MATCH(SMALL(Actions!$N$2:$N$501,ROWS(F$64:F64)),Actions!$N$2:$N$501,0))="","",INDEX(Actions!$G$2:$G$501,MATCH(SMALL(Actions!$N$2:$N$501,ROWS(F$64:F64)),Actions!$N$2:$N$501,0))),"") | J64: =IFERROR(IF(INDEX(Actions!$M$2:$M$501,MATCH(SMALL(Actions!$N$2:$N$501,ROWS(F$64:F64)),Actions!$N$2:$N$501,0))="","",INDEX(Actions!$M$2:$M$501,MATCH(SMALL(Actions!$N$2:$N$501,ROWS(F$64:F64)),Actions!$N$2:$N$501,0))),"")
A65: =IFERROR(IF(INDEX(Tasks!$B$2:$B$1001,MATCH(SMALL(Tasks!$I$2:$I$1001,ROWS(A$64:A65)),Tasks!$I$2:$I$1001,0))="","",INDEX(Tasks!$B$2:$B$1001,MATCH(SMALL(Tasks!$I$2:$I$1001,ROWS(A$64:A65)),Tasks!$I$2:$I$1001,0))),"") | B65: =IFERROR(IF(INDEX(Tasks!$A$2:$A$1001,MATCH(SMALL(Tasks!$I$2:$I$1001,ROWS(A$64:A65)),Tasks!$I$2:$I$1001,0))="","",INDEX(Tasks!$A$2:$A$1001,MATCH(SMALL(Tasks!$I$2:$I$1001,ROWS(A$64:A65)),Tasks!$I$2:$I$1001,0))),"") | C65: =IFERROR(IF(INDEX(Tasks!$E$2:$E$1001,MATCH(SMALL(Tasks!$I$2:$I$1001,ROWS(A$64:A65)),Tasks!$I$2:$I$1001,0))="","",INDEX(Tasks!$E$2:$E$1001,MATCH(SMALL(Tasks!$I$2:$I$1001,ROWS(A$64:A65)),Tasks!$I$2:$I$1001,0))),"") | D65: =IFERROR(IF(INDEX(Tasks!$H$2:$H$1001,MATCH(SMALL(Tasks!$I$2:$I$1001,ROWS(A$64:A65)),Tasks!$I$2:$I$1001,0))="","",INDEX(Tasks!$H$2:$H$1001,MATCH(SMALL(Tasks!$I$2:$I$1001,ROWS(A$64:A65)),Tasks!$I$2:$I$1001,0))),"") | F65: =IFERROR(IF(INDEX(Actions!$C$2:$C$501,MATCH(SMALL(Actions!$N$2:$N$501,ROWS(F$64:F65)),Actions!$N$2:$N$501,0))="","",INDEX(Actions!$C$2:$C$501,MATCH(SMALL(Actions!$N$2:$N$501,ROWS(F$64:F65)),Actions!$N$2:$N$501,0))),"") | G65: =IFERROR(IF(INDEX(Actions!$A$2:$A$501,MATCH(SMALL(Actions!$N$2:$N$501,ROWS(F$64:F65)),Actions!$N$2:$N$501,0))="","",INDEX(Actions!$A$2:$A$501,MATCH(SMALL(Actions!$N$2:$N$501,ROWS(F$64:F65)),Actions!$N$2:$N$501,0))),"") | H65: =IFERROR(IF(INDEX(Actions!$F$2:$F$501,MATCH(SMALL(Actions!$N$2:$N$501,ROWS(F$64:F65)),Actions!$N$2:$N$501,0))="","",INDEX(Actions!$F$2:$F$501,MATCH(SMALL(Actions!$N$2:$N$501,ROWS(F$64:F65)),Actions!$N$2:$N$501,0))),"") | I65: =IFERROR(IF(INDEX(Actions!$G$2:$G$501,MATCH(SMALL(Actions!$N$2:$N$501,ROWS(F$64:F65)),Actions!$N$2:$N$501,0))="","",INDEX(Actions!$G$2:$G$501,MATCH(SMALL(Actions!$N$2:$N$501,ROWS(F$64:F65)),Actions!$N$2:$N$501,0))),"") | J65: =IFERROR(IF(INDEX(Actions!$M$2:$M$501,MATCH(SMALL(Actions!$N$2:$N$501,ROWS(F$64:F65)),Actions!$N$2:$N$501,0))="","",INDEX(Actions!$M$2:$M$501,MATCH(SMALL(Actions!$N$2:$N$501,ROWS(F$64:F65)),Actions!$N$2:$N$501,0))),"")
A66: =IFERROR(IF(INDEX(Tasks!$B$2:$B$1001,MATCH(SMALL(Tasks!$I$2:$I$1001,ROWS(A$64:A66)),Tasks!$I$2:$I$1001,0))="","",INDEX(Tasks!$B$2:$B$1001,MATCH(SMALL(Tasks!$I$2:$I$1001,ROWS(A$64:A66)),Tasks!$I$2:$I$1001,0))),"") | B66: =IFERROR(IF(INDEX(Tasks!$A$2:$A$1001,MATCH(SMALL(Tasks!$I$2:$I$1001,ROWS(A$64:A66)),Tasks!$I$2:$I$1001,0))="","",INDEX(Tasks!$A$2:$A$1001,MATCH(SMALL(Tasks!$I$2:$I$1001,ROWS(A$64:A66)),Tasks!$I$2:$I$1001,0))),"") | C66: =IFERROR(IF(INDEX(Tasks!$E$2:$E$1001,MATCH(SMALL(Tasks!$I$2:$I$1001,ROWS(A$64:A66)),Tasks!$I$2:$I$1001,0))="","",INDEX(Tasks!$E$2:$E$1001,MATCH(SMALL(Tasks!$I$2:$I$1001,ROWS(A$64:A66)),Tasks!$I$2:$I$1001,0))),"") | D66: =IFERROR(IF(INDEX(Tasks!$H$2:$H$1001,MATCH(SMALL(Tasks!$I$2:$I$1001,ROWS(A$64:A66)),Tasks!$I$2:$I$1001,0))="","",INDEX(Tasks!$H$2:$H$1001,MATCH(SMALL(Tasks!$I$2:$I$1001,ROWS(A$64:A66)),Tasks!$I$2:$I$1001,0))),"") | F66: =IFERROR(IF(INDEX(Actions!$C$2:$C$501,MATCH(SMALL(Actions!$N$2:$N$501,ROWS(F$64:F66)),Actions!$N$2:$N$501,0))="","",INDEX(Actions!$C$2:$C$501,MATCH(SMALL(Actions!$N$2:$N$501,ROWS(F$64:F66)),Actions!$N$2:$N$501,0))),"") | G66: =IFERROR(IF(INDEX(Actions!$A$2:$A$501,MATCH(SMALL(Actions!$N$2:$N$501,ROWS(F$64:F66)),Actions!$N$2:$N$501,0))="","",INDEX(Actions!$A$2:$A$501,MATCH(SMALL(Actions!$N$2:$N$501,ROWS(F$64:F66)),Actions!$N$2:$N$501,0))),"") | H66: =IFERROR(IF(INDEX(Actions!$F$2:$F$501,MATCH(SMALL(Actions!$N$2:$N$501,ROWS(F$64:F66)),Actions!$N$2:$N$501,0))="","",INDEX(Actions!$F$2:$F$501,MATCH(SMALL(Actions!$N$2:$N$501,ROWS(F$64:F66)),Actions!$N$2:$N$501,0))),"") | I66: =IFERROR(IF(INDEX(Actions!$G$2:$G$501,MATCH(SMALL(Actions!$N$2:$N$501,ROWS(F$64:F66)),Actions!$N$2:$N$501,0))="","",INDEX(Actions!$G$2:$G$501,MATCH(SMALL(Actions!$N$2:$N$501,ROWS(F$64:F66)),Actions!$N$2:$N$501,0))),"") | J66: =IFERROR(IF(INDEX(Actions!$M$2:$M$501,MATCH(SMALL(Actions!$N$2:$N$501,ROWS(F$64:F66)),Actions!$N$2:$N$501,0))="","",INDEX(Actions!$M$2:$M$501,MATCH(SMALL(Actions!$N$2:$N$501,ROWS(F$64:F66)),Actions!$N$2:$N$501,0))),"")
A67: =IFERROR(IF(INDEX(Tasks!$B$2:$B$1001,MATCH(SMALL(Tasks!$I$2:$I$1001,ROWS(A$64:A67)),Tasks!$I$2:$I$1001,0))="","",INDEX(Tasks!$B$2:$B$1001,MATCH(SMALL(Tasks!$I$2:$I$1001,ROWS(A$64:A67)),Tasks!$I$2:$I$1001,0))),"") | B67: =IFERROR(IF(INDEX(Tasks!$A$2:$A$1001,MATCH(SMALL(Tasks!$I$2:$I$1001,ROWS(A$64:A67)),Tasks!$I$2:$I$1001,0))="","",INDEX(Tasks!$A$2:$A$1001,MATCH(SMALL(Tasks!$I$2:$I$1001,ROWS(A$64:A67)),Tasks!$I$2:$I$1001,0))),"") | C67: =IFERROR(IF(INDEX(Tasks!$E$2:$E$1001,MATCH(SMALL(Tasks!$I$2:$I$1001,ROWS(A$64:A67)),Tasks!$I$2:$I$1001,0))="","",INDEX(Tasks!$E$2:$E$1001,MATCH(SMALL(Tasks!$I$2:$I$1001,ROWS(A$64:A67)),Tasks!$I$2:$I$1001,0))),"") | D67: =IFERROR(IF(INDEX(Tasks!$H$2:$H$1001,MATCH(SMALL(Tasks!$I$2:$I$1001,ROWS(A$64:A67)),Tasks!$I$2:$I$1001,0))="","",INDEX(Tasks!$H$2:$H$1001,MATCH(SMALL(Tasks!$I$2:$I$1001,ROWS(A$64:A67)),Tasks!$I$2:$I$1001,0))),"") | F67: =IFERROR(IF(INDEX(Actions!$C$2:$C$501,MATCH(SMALL(Actions!$N$2:$N$501,ROWS(F$64:F67)),Actions!$N$2:$N$501,0))="","",INDEX(Actions!$C$2:$C$501,MATCH(SMALL(Actions!$N$2:$N$501,ROWS(F$64:F67)),Actions!$N$2:$N$501,0))),"") | G67: =IFERROR(IF(INDEX(Actions!$A$2:$A$501,MATCH(SMALL(Actions!$N$2:$N$501,ROWS(F$64:F67)),Actions!$N$2:$N$501,0))="","",INDEX(Actions!$A$2:$A$501,MATCH(SMALL(Actions!$N$2:$N$501,ROWS(F$64:F67)),Actions!$N$2:$N$501,0))),"") | H67: =IFERROR(IF(INDEX(Actions!$F$2:$F$501,MATCH(SMALL(Actions!$N$2:$N$501,ROWS(F$64:F67)),Actions!$N$2:$N$501,0))="","",INDEX(Actions!$F$2:$F$501,MATCH(SMALL(Actions!$N$2:$N$501,ROWS(F$64:F67)),Actions!$N$2:$N$501,0))),"") | I67: =IFERROR(IF(INDEX(Actions!$G$2:$G$501,MATCH(SMALL(Actions!$N$2:$N$501,ROWS(F$64:F67)),Actions!$N$2:$N$501,0))="","",INDEX(Actions!$G$2:$G$501,MATCH(SMALL(Actions!$N$2:$N$501,ROWS(F$64:F67)),Actions!$N$2:$N$501,0))),"") | J67: =IFERROR(IF(INDEX(Actions!$M$2:$M$501,MATCH(SMALL(Actions!$N$2:$N$501,ROWS(F$64:F67)),Actions!$N$2:$N$501,0))="","",INDEX(Actions!$M$2:$M$501,MATCH(SMALL(Actions!$N$2:$N$501,ROWS(F$64:F67)),Actions!$N$2:$N$501,0))),"")
A68: =IFERROR(IF(INDEX(Tasks!$B$2:$B$1001,MATCH(SMALL(Tasks!$I$2:$I$1001,ROWS(A$64:A68)),Tasks!$I$2:$I$1001,0))="","",INDEX(Tasks!$B$2:$B$1001,MATCH(SMALL(Tasks!$I$2:$I$1001,ROWS(A$64:A68)),Tasks!$I$2:$I$1001,0))),"") | B68: =IFERROR(IF(INDEX(Tasks!$A$2:$A$1001,MATCH(SMALL(Tasks!$I$2:$I$1001,ROWS(A$64:A68)),Tasks!$I$2:$I$1001,0))="","",INDEX(Tasks!$A$2:$A$1001,MATCH(SMALL(Tasks!$I$2:$I$1001,ROWS(A$64:A68)),Tasks!$I$2:$I$1001,0))),"") | C68: =IFERROR(IF(INDEX(Tasks!$E$2:$E$1001,MATCH(SMALL(Tasks!$I$2:$I$1001,ROWS(A$64:A68)),Tasks!$I$2:$I$1001,0))="","",INDEX(Tasks!$E$2:$E$1001,MATCH(SMALL(Tasks!$I$2:$I$1001,ROWS(A$64:A68)),Tasks!$I$2:$I$1001,0))),"") | D68: =IFERROR(IF(INDEX(Tasks!$H$2:$H$1001,MATCH(SMALL(Tasks!$I$2:$I$1001,ROWS(A$64:A68)),Tasks!$I$2:$I$1001,0))="","",INDEX(Tasks!$H$2:$H$1001,MATCH(SMALL(Tasks!$I$2:$I$1001,ROWS(A$64:A68)),Tasks!$I$2:$I$1001,0))),"") | F68: =IFERROR(IF(INDEX(Actions!$C$2:$C$501,MATCH(SMALL(Actions!$N$2:$N$501,ROWS(F$64:F68)),Actions!$N$2:$N$501,0))="","",INDEX(Actions!$C$2:$C$501,MATCH(SMALL(Actions!$N$2:$N$501,ROWS(F$64:F68)),Actions!$N$2:$N$501,0))),"") | G68: =IFERROR(IF(INDEX(Actions!$A$2:$A$501,MATCH(SMALL(Actions!$N$2:$N$501,ROWS(F$64:F68)),Actions!$N$2:$N$501,0))="","",INDEX(Actions!$A$2:$A$501,MATCH(SMALL(Actions!$N$2:$N$501,ROWS(F$64:F68)),Actions!$N$2:$N$501,0))),"") | H68: =IFERROR(IF(INDEX(Actions!$F$2:$F$501,MATCH(SMALL(Actions!$N$2:$N$501,ROWS(F$64:F68)),Actions!$N$2:$N$501,0))="","",INDEX(Actions!$F$2:$F$501,MATCH(SMALL(Actions!$N$2:$N$501,ROWS(F$64:F68)),Actions!$N$2:$N$501,0))),"") | I68: =IFERROR(IF(INDEX(Actions!$G$2:$G$501,MATCH(SMALL(Actions!$N$2:$N$501,ROWS(F$64:F68)),Actions!$N$2:$N$501,0))="","",INDEX(Actions!$G$2:$G$501,MATCH(SMALL(Actions!$N$2:$N$501,ROWS(F$64:F68)),Actions!$N$2:$N$501,0))),"") | J68: =IFERROR(IF(INDEX(Actions!$M$2:$M$501,MATCH(SMALL(Actions!$N$2:$N$501,ROWS(F$64:F68)),Actions!$N$2:$N$501,0))="","",INDEX(Actions!$M$2:$M$501,MATCH(SMALL(Actions!$N$2:$N$501,ROWS(F$64:F68)),Actions!$N$2:$N$501,0))),"")
A69: =IFERROR(IF(INDEX(Tasks!$B$2:$B$1001,MATCH(SMALL(Tasks!$I$2:$I$1001,ROWS(A$64:A69)),Tasks!$I$2:$I$1001,0))="","",INDEX(Tasks!$B$2:$B$1001,MATCH(SMALL(Tasks!$I$2:$I$1001,ROWS(A$64:A69)),Tasks!$I$2:$I$1001,0))),"") | B69: =IFERROR(IF(INDEX(Tasks!$A$2:$A$1001,MATCH(SMALL(Tasks!$I$2:$I$1001,ROWS(A$64:A69)),Tasks!$I$2:$I$1001,0))="","",INDEX(Tasks!$A$2:$A$1001,MATCH(SMALL(Tasks!$I$2:$I$1001,ROWS(A$64:A69)),Tasks!$I$2:$I$1001,0))),"") | C69: =IFERROR(IF(INDEX(Tasks!$E$2:$E$1001,MATCH(SMALL(Tasks!$I$2:$I$1001,ROWS(A$64:A69)),Tasks!$I$2:$I$1001,0))="","",INDEX(Tasks!$E$2:$E$1001,MATCH(SMALL(Tasks!$I$2:$I$1001,ROWS(A$64:A69)),Tasks!$I$2:$I$1001,0))),"") | D69: =IFERROR(IF(INDEX(Tasks!$H$2:$H$1001,MATCH(SMALL(Tasks!$I$2:$I$1001,ROWS(A$64:A69)),Tasks!$I$2:$I$1001,0))="","",INDEX(Tasks!$H$2:$H$1001,MATCH(SMALL(Tasks!$I$2:$I$1001,ROWS(A$64:A69)),Tasks!$I$2:$I$1001,0))),"") | F69: =IFERROR(IF(INDEX(Actions!$C$2:$C$501,MATCH(SMALL(Actions!$N$2:$N$501,ROWS(F$64:F69)),Actions!$N$2:$N$501,0))="","",INDEX(Actions!$C$2:$C$501,MATCH(SMALL(Actions!$N$2:$N$501,ROWS(F$64:F69)),Actions!$N$2:$N$501,0))),"") | G69: =IFERROR(IF(INDEX(Actions!$A$2:$A$501,MATCH(SMALL(Actions!$N$2:$N$501,ROWS(F$64:F69)),Actions!$N$2:$N$501,0))="","",INDEX(Actions!$A$2:$A$501,MATCH(SMALL(Actions!$N$2:$N$501,ROWS(F$64:F69)),Actions!$N$2:$N$501,0))),"") | H69: =IFERROR(IF(INDEX(Actions!$F$2:$F$501,MATCH(SMALL(Actions!$N$2:$N$501,ROWS(F$64:F69)),Actions!$N$2:$N$501,0))="","",INDEX(Actions!$F$2:$F$501,MATCH(SMALL(Actions!$N$2:$N$501,ROWS(F$64:F69)),Actions!$N$2:$N$501,0))),"") | I69: =IFERROR(IF(INDEX(Actions!$G$2:$G$501,MATCH(SMALL(Actions!$N$2:$N$501,ROWS(F$64:F69)),Actions!$N$2:$N$501,0))="","",INDEX(Actions!$G$2:$G$501,MATCH(SMALL(Actions!$N$2:$N$501,ROWS(F$64:F69)),Actions!$N$2:$N$501,0))),"") | J69: =IFERROR(IF(INDEX(Actions!$M$2:$M$501,MATCH(SMALL(Actions!$N$2:$N$501,ROWS(F$64:F69)),Actions!$N$2:$N$501,0))="","",INDEX(Actions!$M$2:$M$501,MATCH(SMALL(Actions!$N$2:$N$501,ROWS(F$64:F69)),Actions!$N$2:$N$501,0))),"")
A70: =IFERROR(IF(INDEX(Tasks!$B$2:$B$1001,MATCH(SMALL(Tasks!$I$2:$I$1001,ROWS(A$64:A70)),Tasks!$I$2:$I$1001,0))="","",INDEX(Tasks!$B$2:$B$1001,MATCH(SMALL(Tasks!$I$2:$I$1001,ROWS(A$64:A70)),Tasks!$I$2:$I$1001,0))),"") | B70: =IFERROR(IF(INDEX(Tasks!$A$2:$A$1001,MATCH(SMALL(Tasks!$I$2:$I$1001,ROWS(A$64:A70)),Tasks!$I$2:$I$1001,0))="","",INDEX(Tasks!$A$2:$A$1001,MATCH(SMALL(Tasks!$I$2:$I$1001,ROWS(A$64:A70)),Tasks!$I$2:$I$1001,0))),"") | C70: =IFERROR(IF(INDEX(Tasks!$E$2:$E$1001,MATCH(SMALL(Tasks!$I$2:$I$1001,ROWS(A$64:A70)),Tasks!$I$2:$I$1001,0))="","",INDEX(Tasks!$E$2:$E$1001,MATCH(SMALL(Tasks!$I$2:$I$1001,ROWS(A$64:A70)),Tasks!$I$2:$I$1001,0))),"") | D70: =IFERROR(IF(INDEX(Tasks!$H$2:$H$1001,MATCH(SMALL(Tasks!$I$2:$I$1001,ROWS(A$64:A70)),Tasks!$I$2:$I$1001,0))="","",INDEX(Tasks!$H$2:$H$1001,MATCH(SMALL(Tasks!$I$2:$I$1001,ROWS(A$64:A70)),Tasks!$I$2:$I$1001,0))),"") | F70: =IFERROR(IF(INDEX(Actions!$C$2:$C$501,MATCH(SMALL(Actions!$N$2:$N$501,ROWS(F$64:F70)),Actions!$N$2:$N$501,0))="","",INDEX(Actions!$C$2:$C$501,MATCH(SMALL(Actions!$N$2:$N$501,ROWS(F$64:F70)),Actions!$N$2:$N$501,0))),"") | G70: =IFERROR(IF(INDEX(Actions!$A$2:$A$501,MATCH(SMALL(Actions!$N$2:$N$501,ROWS(F$64:F70)),Actions!$N$2:$N$501,0))="","",INDEX(Actions!$A$2:$A$501,MATCH(SMALL(Actions!$N$2:$N$501,ROWS(F$64:F70)),Actions!$N$2:$N$501,0))),"") | H70: =IFERROR(IF(INDEX(Actions!$F$2:$F$501,MATCH(SMALL(Actions!$N$2:$N$501,ROWS(F$64:F70)),Actions!$N$2:$N$501,0))="","",INDEX(Actions!$F$2:$F$501,MATCH(SMALL(Actions!$N$2:$N$501,ROWS(F$64:F70)),Actions!$N$2:$N$501,0))),"") | I70: =IFERROR(IF(INDEX(Actions!$G$2:$G$501,MATCH(SMALL(Actions!$N$2:$N$501,ROWS(F$64:F70)),Actions!$N$2:$N$501,0))="","",INDEX(Actions!$G$2:$G$501,MATCH(SMALL(Actions!$N$2:$N$501,ROWS(F$64:F70)),Actions!$N$2:$N$501,0))),"") | J70: =IFERROR(IF(INDEX(Actions!$M$2:$M$501,MATCH(SMALL(Actions!$N$2:$N$501,ROWS(F$64:F70)),Actions!$N$2:$N$501,0))="","",INDEX(Actions!$M$2:$M$501,MATCH(SMALL(Actions!$N$2:$N$501,ROWS(F$64:F70)),Actions!$N$2:$N$501,0))),"")
A71: =IFERROR(IF(INDEX(Tasks!$B$2:$B$1001,MATCH(SMALL(Tasks!$I$2:$I$1001,ROWS(A$64:A71)),Tasks!$I$2:$I$1001,0))="","",INDEX(Tasks!$B$2:$B$1001,MATCH(SMALL(Tasks!$I$2:$I$1001,ROWS(A$64:A71)),Tasks!$I$2:$I$1001,0))),"") | B71: =IFERROR(IF(INDEX(Tasks!$A$2:$A$1001,MATCH(SMALL(Tasks!$I$2:$I$1001,ROWS(A$64:A71)),Tasks!$I$2:$I$1001,0))="","",INDEX(Tasks!$A$2:$A$1001,MATCH(SMALL(Tasks!$I$2:$I$1001,ROWS(A$64:A71)),Tasks!$I$2:$I$1001,0))),"") | C71: =IFERROR(IF(INDEX(Tasks!$E$2:$E$1001,MATCH(SMALL(Tasks!$I$2:$I$1001,ROWS(A$64:A71)),Tasks!$I$2:$I$1001,0))="","",INDEX(Tasks!$E$2:$E$1001,MATCH(SMALL(Tasks!$I$2:$I$1001,ROWS(A$64:A71)),Tasks!$I$2:$I$1001,0))),"") | D71: =IFERROR(IF(INDEX(Tasks!$H$2:$H$1001,MATCH(SMALL(Tasks!$I$2:$I$1001,ROWS(A$64:A71)),Tasks!$I$2:$I$1001,0))="","",INDEX(Tasks!$H$2:$H$1001,MATCH(SMALL(Tasks!$I$2:$I$1001,ROWS(A$64:A71)),Tasks!$I$2:$I$1001,0))),"") | F71: =IFERROR(IF(INDEX(Actions!$C$2:$C$501,MATCH(SMALL(Actions!$N$2:$N$501,ROWS(F$64:F71)),Actions!$N$2:$N$501,0))="","",INDEX(Actions!$C$2:$C$501,MATCH(SMALL(Actions!$N$2:$N$501,ROWS(F$64:F71)),Actions!$N$2:$N$501,0))),"") | G71: =IFERROR(IF(INDEX(Actions!$A$2:$A$501,MATCH(SMALL(Actions!$N$2:$N$501,ROWS(F$64:F71)),Actions!$N$2:$N$501,0))="","",INDEX(Actions!$A$2:$A$501,MATCH(SMALL(Actions!$N$2:$N$501,ROWS(F$64:F71)),Actions!$N$2:$N$501,0))),"") | H71: =IFERROR(IF(INDEX(Actions!$F$2:$F$501,MATCH(SMALL(Actions!$N$2:$N$501,ROWS(F$64:F71)),Actions!$N$2:$N$501,0))="","",INDEX(Actions!$F$2:$F$501,MATCH(SMALL(Actions!$N$2:$N$501,ROWS(F$64:F71)),Actions!$N$2:$N$501,0))),"") | I71: =IFERROR(IF(INDEX(Actions!$G$2:$G$501,MATCH(SMALL(Actions!$N$2:$N$501,ROWS(F$64:F71)),Actions!$N$2:$N$501,0))="","",INDEX(Actions!$G$2:$G$501,MATCH(SMALL(Actions!$N$2:$N$501,ROWS(F$64:F71)),Actions!$N$2:$N$501,0))),"") | J71: =IFERROR(IF(INDEX(Actions!$M$2:$M$501,MATCH(SMALL(Actions!$N$2:$N$501,ROWS(F$64:F71)),Actions!$N$2:$N$501,0))="","",INDEX(Actions!$M$2:$M$501,MATCH(SMALL(Actions!$N$2:$N$501,ROWS(F$64:F71)),Actions!$N$2:$N$501,0))),"")
A72: =IFERROR(IF(INDEX(Tasks!$B$2:$B$1001,MATCH(SMALL(Tasks!$I$2:$I$1001,ROWS(A$64:A72)),Tasks!$I$2:$I$1001,0))="","",INDEX(Tasks!$B$2:$B$1001,MATCH(SMALL(Tasks!$I$2:$I$1001,ROWS(A$64:A72)),Tasks!$I$2:$I$1001,0))),"") | B72: =IFERROR(IF(INDEX(Tasks!$A$2:$A$1001,MATCH(SMALL(Tasks!$I$2:$I$1001,ROWS(A$64:A72)),Tasks!$I$2:$I$1001,0))="","",INDEX(Tasks!$A$2:$A$1001,MATCH(SMALL(Tasks!$I$2:$I$1001,ROWS(A$64:A72)),Tasks!$I$2:$I$1001,0))),"") | C72: =IFERROR(IF(INDEX(Tasks!$E$2:$E$1001,MATCH(SMALL(Tasks!$I$2:$I$1001,ROWS(A$64:A72)),Tasks!$I$2:$I$1001,0))="","",INDEX(Tasks!$E$2:$E$1001,MATCH(SMALL(Tasks!$I$2:$I$1001,ROWS(A$64:A72)),Tasks!$I$2:$I$1001,0))),"") | D72: =IFERROR(IF(INDEX(Tasks!$H$2:$H$1001,MATCH(SMALL(Tasks!$I$2:$I$1001,ROWS(A$64:A72)),Tasks!$I$2:$I$1001,0))="","",INDEX(Tasks!$H$2:$H$1001,MATCH(SMALL(Tasks!$I$2:$I$1001,ROWS(A$64:A72)),Tasks!$I$2:$I$1001,0))),"") | F72: =IFERROR(IF(INDEX(Actions!$C$2:$C$501,MATCH(SMALL(Actions!$N$2:$N$501,ROWS(F$64:F72)),Actions!$N$2:$N$501,0))="","",INDEX(Actions!$C$2:$C$501,MATCH(SMALL(Actions!$N$2:$N$501,ROWS(F$64:F72)),Actions!$N$2:$N$501,0))),"") | G72: =IFERROR(IF(INDEX(Actions!$A$2:$A$501,MATCH(SMALL(Actions!$N$2:$N$501,ROWS(F$64:F72)),Actions!$N$2:$N$501,0))="","",INDEX(Actions!$A$2:$A$501,MATCH(SMALL(Actions!$N$2:$N$501,ROWS(F$64:F72)),Actions!$N$2:$N$501,0))),"") | H72: =IFERROR(IF(INDEX(Actions!$F$2:$F$501,MATCH(SMALL(Actions!$N$2:$N$501,ROWS(F$64:F72)),Actions!$N$2:$N$501,0))="","",INDEX(Actions!$F$2:$F$501,MATCH(SMALL(Actions!$N$2:$N$501,ROWS(F$64:F72)),Actions!$N$2:$N$501,0))),"") | I72: =IFERROR(IF(INDEX(Actions!$G$2:$G$501,MATCH(SMALL(Actions!$N$2:$N$501,ROWS(F$64:F72)),Actions!$N$2:$N$501,0))="","",INDEX(Actions!$G$2:$G$501,MATCH(SMALL(Actions!$N$2:$N$501,ROWS(F$64:F72)),Actions!$N$2:$N$501,0))),"") | J72: =IFERROR(IF(INDEX(Actions!$M$2:$M$501,MATCH(SMALL(Actions!$N$2:$N$501,ROWS(F$64:F72)),Actions!$N$2:$N$501,0))="","",INDEX(Actions!$M$2:$M$501,MATCH(SMALL(Actions!$N$2:$N$501,ROWS(F$64:F72)),Actions!$N$2:$N$501,0))),"")
A73: =IFERROR(IF(INDEX(Tasks!$B$2:$B$1001,MATCH(SMALL(Tasks!$I$2:$I$1001,ROWS(A$64:A73)),Tasks!$I$2:$I$1001,0))="","",INDEX(Tasks!$B$2:$B$1001,MATCH(SMALL(Tasks!$I$2:$I$1001,ROWS(A$64:A73)),Tasks!$I$2:$I$1001,0))),"") | B73: =IFERROR(IF(INDEX(Tasks!$A$2:$A$1001,MATCH(SMALL(Tasks!$I$2:$I$1001,ROWS(A$64:A73)),Tasks!$I$2:$I$1001,0))="","",INDEX(Tasks!$A$2:$A$1001,MATCH(SMALL(Tasks!$I$2:$I$1001,ROWS(A$64:A73)),Tasks!$I$2:$I$1001,0))),"") | C73: =IFERROR(IF(INDEX(Tasks!$E$2:$E$1001,MATCH(SMALL(Tasks!$I$2:$I$1001,ROWS(A$64:A73)),Tasks!$I$2:$I$1001,0))="","",INDEX(Tasks!$E$2:$E$1001,MATCH(SMALL(Tasks!$I$2:$I$1001,ROWS(A$64:A73)),Tasks!$I$2:$I$1001,0))),"") | D73: =IFERROR(IF(INDEX(Tasks!$H$2:$H$1001,MATCH(SMALL(Tasks!$I$2:$I$1001,ROWS(A$64:A73)),Tasks!$I$2:$I$1001,0))="","",INDEX(Tasks!$H$2:$H$1001,MATCH(SMALL(Tasks!$I$2:$I$1001,ROWS(A$64:A73)),Tasks!$I$2:$I$1001,0))),"") | F73: =IFERROR(IF(INDEX(Actions!$C$2:$C$501,MATCH(SMALL(Actions!$N$2:$N$501,ROWS(F$64:F73)),Actions!$N$2:$N$501,0))="","",INDEX(Actions!$C$2:$C$501,MATCH(SMALL(Actions!$N$2:$N$501,ROWS(F$64:F73)),Actions!$N$2:$N$501,0))),"") | G73: =IFERROR(IF(INDEX(Actions!$A$2:$A$501,MATCH(SMALL(Actions!$N$2:$N$501,ROWS(F$64:F73)),Actions!$N$2:$N$501,0))="","",INDEX(Actions!$A$2:$A$501,MATCH(SMALL(Actions!$N$2:$N$501,ROWS(F$64:F73)),Actions!$N$2:$N$501,0))),"") | H73: =IFERROR(IF(INDEX(Actions!$F$2:$F$501,MATCH(SMALL(Actions!$N$2:$N$501,ROWS(F$64:F73)),Actions!$N$2:$N$501,0))="","",INDEX(Actions!$F$2:$F$501,MATCH(SMALL(Actions!$N$2:$N$501,ROWS(F$64:F73)),Actions!$N$2:$N$501,0))),"") | I73: =IFERROR(IF(INDEX(Actions!$G$2:$G$501,MATCH(SMALL(Actions!$N$2:$N$501,ROWS(F$64:F73)),Actions!$N$2:$N$501,0))="","",INDEX(Actions!$G$2:$G$501,MATCH(SMALL(Actions!$N$2:$N$501,ROWS(F$64:F73)),Actions!$N$2:$N$501,0))),"") | J73: =IFERROR(IF(INDEX(Actions!$M$2:$M$501,MATCH(SMALL(Actions!$N$2:$N$501,ROWS(F$64:F73)),Actions!$N$2:$N$501,0))="","",INDEX(Actions!$M$2:$M$501,MATCH(SMALL(Actions!$N$2:$N$501,ROWS(F$64:F73)),Actions!$N$2:$N$501,0))),"")
A74: =IFERROR(IF(INDEX(Tasks!$B$2:$B$1001,MATCH(SMALL(Tasks!$I$2:$I$1001,ROWS(A$64:A74)),Tasks!$I$2:$I$1001,0))="","",INDEX(Tasks!$B$2:$B$1001,MATCH(SMALL(Tasks!$I$2:$I$1001,ROWS(A$64:A74)),Tasks!$I$2:$I$1001,0))),"") | B74: =IFERROR(IF(INDEX(Tasks!$A$2:$A$1001,MATCH(SMALL(Tasks!$I$2:$I$1001,ROWS(A$64:A74)),Tasks!$I$2:$I$1001,0))="","",INDEX(Tasks!$A$2:$A$1001,MATCH(SMALL(Tasks!$I$2:$I$1001,ROWS(A$64:A74)),Tasks!$I$2:$I$1001,0))),"") | C74: =IFERROR(IF(INDEX(Tasks!$E$2:$E$1001,MATCH(SMALL(Tasks!$I$2:$I$1001,ROWS(A$64:A74)),Tasks!$I$2:$I$1001,0))="","",INDEX(Tasks!$E$2:$E$1001,MATCH(SMALL(Tasks!$I$2:$I$1001,ROWS(A$64:A74)),Tasks!$I$2:$I$1001,0))),"") | D74: =IFERROR(IF(INDEX(Tasks!$H$2:$H$1001,MATCH(SMALL(Tasks!$I$2:$I$1001,ROWS(A$64:A74)),Tasks!$I$2:$I$1001,0))="","",INDEX(Tasks!$H$2:$H$1001,MATCH(SMALL(Tasks!$I$2:$I$1001,ROWS(A$64:A74)),Tasks!$I$2:$I$1001,0))),"") | F74: =IFERROR(IF(INDEX(Actions!$C$2:$C$501,MATCH(SMALL(Actions!$N$2:$N$501,ROWS(F$64:F74)),Actions!$N$2:$N$501,0))="","",INDEX(Actions!$C$2:$C$501,MATCH(SMALL(Actions!$N$2:$N$501,ROWS(F$64:F74)),Actions!$N$2:$N$501,0))),"") | G74: =IFERROR(IF(INDEX(Actions!$A$2:$A$501,MATCH(SMALL(Actions!$N$2:$N$501,ROWS(F$64:F74)),Actions!$N$2:$N$501,0))="","",INDEX(Actions!$A$2:$A$501,MATCH(SMALL(Actions!$N$2:$N$501,ROWS(F$64:F74)),Actions!$N$2:$N$501,0))),"") | H74: =IFERROR(IF(INDEX(Actions!$F$2:$F$501,MATCH(SMALL(Actions!$N$2:$N$501,ROWS(F$64:F74)),Actions!$N$2:$N$501,0))="","",INDEX(Actions!$F$2:$F$501,MATCH(SMALL(Actions!$N$2:$N$501,ROWS(F$64:F74)),Actions!$N$2:$N$501,0))),"") | I74: =IFERROR(IF(INDEX(Actions!$G$2:$G$501,MATCH(SMALL(Actions!$N$2:$N$501,ROWS(F$64:F74)),Actions!$N$2:$N$501,0))="","",INDEX(Actions!$G$2:$G$501,MATCH(SMALL(Actions!$N$2:$N$501,ROWS(F$64:F74)),Actions!$N$2:$N$501,0))),"") | J74: =IFERROR(IF(INDEX(Actions!$M$2:$M$501,MATCH(SMALL(Actions!$N$2:$N$501,ROWS(F$64:F74)),Actions!$N$2:$N$501,0))="","",INDEX(Actions!$M$2:$M$501,MATCH(SMALL(Actions!$N$2:$N$501,ROWS(F$64:F74)),Actions!$N$2:$N$501,0))),"")
A75: =IFERROR(IF(INDEX(Tasks!$B$2:$B$1001,MATCH(SMALL(Tasks!$I$2:$I$1001,ROWS(A$64:A75)),Tasks!$I$2:$I$1001,0))="","",INDEX(Tasks!$B$2:$B$1001,MATCH(SMALL(Tasks!$I$2:$I$1001,ROWS(A$64:A75)),Tasks!$I$2:$I$1001,0))),"") | B75: =IFERROR(IF(INDEX(Tasks!$A$2:$A$1001,MATCH(SMALL(Tasks!$I$2:$I$1001,ROWS(A$64:A75)),Tasks!$I$2:$I$1001,0))="","",INDEX(Tasks!$A$2:$A$1001,MATCH(SMALL(Tasks!$I$2:$I$1001,ROWS(A$64:A75)),Tasks!$I$2:$I$1001,0))),"") | C75: =IFERROR(IF(INDEX(Tasks!$E$2:$E$1001,MATCH(SMALL(Tasks!$I$2:$I$1001,ROWS(A$64:A75)),Tasks!$I$2:$I$1001,0))="","",INDEX(Tasks!$E$2:$E$1001,MATCH(SMALL(Tasks!$I$2:$I$1001,ROWS(A$64:A75)),Tasks!$I$2:$I$1001,0))),"") | D75: =IFERROR(IF(INDEX(Tasks!$H$2:$H$1001,MATCH(SMALL(Tasks!$I$2:$I$1001,ROWS(A$64:A75)),Tasks!$I$2:$I$1001,0))="","",INDEX(Tasks!$H$2:$H$1001,MATCH(SMALL(Tasks!$I$2:$I$1001,ROWS(A$64:A75)),Tasks!$I$2:$I$1001,0))),"") | F75: =IFERROR(IF(INDEX(Actions!$C$2:$C$501,MATCH(SMALL(Actions!$N$2:$N$501,ROWS(F$64:F75)),Actions!$N$2:$N$501,0))="","",INDEX(Actions!$C$2:$C$501,MATCH(SMALL(Actions!$N$2:$N$501,ROWS(F$64:F75)),Actions!$N$2:$N$501,0))),"") | G75: =IFERROR(IF(INDEX(Actions!$A$2:$A$501,MATCH(SMALL(Actions!$N$2:$N$501,ROWS(F$64:F75)),Actions!$N$2:$N$501,0))="","",INDEX(Actions!$A$2:$A$501,MATCH(SMALL(Actions!$N$2:$N$501,ROWS(F$64:F75)),Actions!$N$2:$N$501,0))),"") | H75: =IFERROR(IF(INDEX(Actions!$F$2:$F$501,MATCH(SMALL(Actions!$N$2:$N$501,ROWS(F$64:F75)),Actions!$N$2:$N$501,0))="","",INDEX(Actions!$F$2:$F$501,MATCH(SMALL(Actions!$N$2:$N$501,ROWS(F$64:F75)),Actions!$N$2:$N$501,0))),"") | I75: =IFERROR(IF(INDEX(Actions!$G$2:$G$501,MATCH(SMALL(Actions!$N$2:$N$501,ROWS(F$64:F75)),Actions!$N$2:$N$501,0))="","",INDEX(Actions!$G$2:$G$501,MATCH(SMALL(Actions!$N$2:$N$501,ROWS(F$64:F75)),Actions!$N$2:$N$501,0))),"") | J75: =IFERROR(IF(INDEX(Actions!$M$2:$M$501,MATCH(SMALL(Actions!$N$2:$N$501,ROWS(F$64:F75)),Actions!$N$2:$N$501,0))="","",INDEX(Actions!$M$2:$M$501,MATCH(SMALL(Actions!$N$2:$N$501,ROWS(F$64:F75)),Actions!$N$2:$N$501,0))),"")
... A78: =IFERROR(IF(INDEX(Tasks!$B$2:$B$1001,MATCH(SMALL(Tasks!$I$2:$I$1001,ROWS(A$64:A78)),Tasks!$I$2:$I$1001,0))="","",INDEX(Tasks!$B$2:$B$1001,MATCH(SMALL(Tasks!$I$2:$I$1001,ROWS(A$64:A78)),Tasks!$I$2:$I$1001,0))),"") | B78: =IFERROR(IF(INDEX(Tasks!$A$2:$A$1001,MATCH(SMALL(Tasks!$I$2:$I$1001,ROWS(A$64:A78)),Tasks!$I$2:$I$1001,0))="","",INDEX(Tasks!$A$2:$A$1001,MATCH(SMALL(Tasks!$I$2:$I$1001,ROWS(A$64:A78)),Tasks!$I$2:$I$1001,0))),"") | C78: =IFERROR(IF(INDEX(Tasks!$E$2:$E$1001,MATCH(SMALL(Tasks!$I$2:$I$1001,ROWS(A$64:A78)),Tasks!$I$2:$I$1001,0))="","",INDEX(Tasks!$E$2:$E$1001,MATCH(SMALL(Tasks!$I$2:$I$1001,ROWS(A$64:A78)),Tasks!$I$2:$I$1001,0))),"") | D78: =IFERROR(IF(INDEX(Tasks!$H$2:$H$1001,MATCH(SMALL(Tasks!$I$2:$I$1001,ROWS(A$64:A78)),Tasks!$I$2:$I$1001,0))="","",INDEX(Tasks!$H$2:$H$1001,MATCH(SMALL(Tasks!$I$2:$I$1001,ROWS(A$64:A78)),Tasks!$I$2:$I$1001,0))),"") | F78: =IFERROR(IF(INDEX(Actions!$C$2:$C$501,MATCH(SMALL(Actions!$N$2:$N$501,ROWS(F$64:F78)),Actions!$N$2:$N$501,0))="","",INDEX(Actions!$C$2:$C$501,MATCH(SMALL(Actions!$N$2:$N$501,ROWS(F$64:F78)),Actions!$N$2:$N$501,0))),"") | G78: =IFERROR(IF(INDEX(Actions!$A$2:$A$501,MATCH(SMALL(Actions!$N$2:$N$501,ROWS(F$64:F78)),Actions!$N$2:$N$501,0))="","",INDEX(Actions!$A$2:$A$501,MATCH(SMALL(Actions!$N$2:$N$501,ROWS(F$64:F78)),Actions!$N$2:$N$501,0))),"") | H78: =IFERROR(IF(INDEX(Actions!$F$2:$F$501,MATCH(SMALL(Actions!$N$2:$N$501,ROWS(F$64:F78)),Actions!$N$2:$N$501,0))="","",INDEX(Actions!$F$2:$F$501,MATCH(SMALL(Actions!$N$2:$N$501,ROWS(F$64:F78)),Actions!$N$2:$N$501,0))),"") | I78: =IFERROR(IF(INDEX(Actions!$G$2:$G$501,MATCH(SMALL(Actions!$N$2:$N$501,ROWS(F$64:F78)),Actions!$N$2:$N$501,0))="","",INDEX(Actions!$G$2:$G$501,MATCH(SMALL(Actions!$N$2:$N$501,ROWS(F$64:F78)),Actions!$N$2:$N$501,0))),"") | J78: =IFERROR(IF(INDEX(Actions!$M$2:$M$501,MATCH(SMALL(Actions!$N$2:$N$501,ROWS(F$64:F78)),Actions!$N$2:$N$501,0))="","",INDEX(Actions!$M$2:$M$501,MATCH(SMALL(Actions!$N$2:$N$501,ROWS(F$64:F78)),Actions!$N$2:$N$501,0))),"")
A81: Top open risks (highest inherent score first)
A82: Risk | B82: Project | C82: Score | D82: Band | E82: Owner | F82: Status | G82: Due
A83: =IFERROR(IF(INDEX(Risks!$C$2:$C$501,MATCH(LARGE(Risks!$S$2:$S$501,ROWS(A$83:A83)),Risks!$S$2:$S$501,0))="","",INDEX(Risks!$C$2:$C$501,MATCH(LARGE(Risks!$S$2:$S$501,ROWS(A$83:A83)),Risks!$S$2:$S$501,0))),"") | B83: =IFERROR(IF(INDEX(Risks!$A$2:$A$501,MATCH(LARGE(Risks!$S$2:$S$501,ROWS(A$83:A83)),Risks!$S$2:$S$501,0))="","",INDEX(Risks!$A$2:$A$501,MATCH(LARGE(Risks!$S$2:$S$501,ROWS(A$83:A83)),Risks!$S$2:$S$501,0))),"") | C83: =IFERROR(IF(INDEX(Risks!$N$2:$N$501,MATCH(LARGE(Risks!$S$2:$S$501,ROWS(A$83:A83)),Risks!$S$2:$S$501,0))="","",INDEX(Risks!$N$2:$N$501,MATCH(LARGE(Risks!$S$2:$S$501,ROWS(A$83:A83)),Risks!$S$2:$S$501,0))),"") | D83: =IFERROR(IF(INDEX(Risks!$O$2:$O$501,MATCH(LARGE(Risks!$S$2:$S$501,ROWS(A$83:A83)),Risks!$S$2:$S$501,0))="","",INDEX(Risks!$O$2:$O$501,MATCH(LARGE(Risks!$S$2:$S$501,ROWS(A$83:A83)),Risks!$S$2:$S$501,0))),"") | E83: =IFERROR(IF(INDEX(Risks!$K$2:$K$501,MATCH(LARGE(Risks!$S$2:$S$501,ROWS(A$83:A83)),Risks!$S$2:$S$501,0))="","",INDEX(Risks!$K$2:$K$501,MATCH(LARGE(Risks!$S$2:$S$501,ROWS(A$83:A83)),Risks!$S$2:$S$501,0))),"") | F83: =IFERROR(IF(INDEX(Risks!$M$2:$M$501,MATCH(LARGE(Risks!$S$2:$S$501,ROWS(A$83:A83)),Risks!$S$2:$S$501,0))="","",INDEX(Risks!$M$2:$M$501,MATCH(LARGE(Risks!$S$2:$S$501,ROWS(A$83:A83)),Risks!$S$2:$S$501,0))),"") | G83: =IFERROR(IF(INDEX(Risks!$L$2:$L$501,MATCH(LARGE(Risks!$S$2:$S$501,ROWS(A$83:A83)),Risks!$S$2:$S$501,0))="","",INDEX(Risks!$L$2:$L$501,MATCH(LARGE(Risks!$S$2:$S$501,ROWS(A$83:A83)),Risks!$S$2:$S$501,0))),"")
A84: =IFERROR(IF(INDEX(Risks!$C$2:$C$501,MATCH(LARGE(Risks!$S$2:$S$501,ROWS(A$83:A84)),Risks!$S$2:$S$501,0))="","",INDEX(Risks!$C$2:$C$501,MATCH(LARGE(Risks!$S$2:$S$501,ROWS(A$83:A84)),Risks!$S$2:$S$501,0))),"") | B84: =IFERROR(IF(INDEX(Risks!$A$2:$A$501,MATCH(LARGE(Risks!$S$2:$S$501,ROWS(A$83:A84)),Risks!$S$2:$S$501,0))="","",INDEX(Risks!$A$2:$A$501,MATCH(LARGE(Risks!$S$2:$S$501,ROWS(A$83:A84)),Risks!$S$2:$S$501,0))),"") | C84: =IFERROR(IF(INDEX(Risks!$N$2:$N$501,MATCH(LARGE(Risks!$S$2:$S$501,ROWS(A$83:A84)),Risks!$S$2:$S$501,0))="","",INDEX(Risks!$N$2:$N$501,MATCH(LARGE(Risks!$S$2:$S$501,ROWS(A$83:A84)),Risks!$S$2:$S$501,0))),"") | D84: =IFERROR(IF(INDEX(Risks!$O$2:$O$501,MATCH(LARGE(Risks!$S$2:$S$501,ROWS(A$83:A84)),Risks!$S$2:$S$501,0))="","",INDEX(Risks!$O$2:$O$501,MATCH(LARGE(Risks!$S$2:$S$501,ROWS(A$83:A84)),Risks!$S$2:$S$501,0))),"") | E84: =IFERROR(IF(INDEX(Risks!$K$2:$K$501,MATCH(LARGE(Risks!$S$2:$S$501,ROWS(A$83:A84)),Risks!$S$2:$S$501,0))="","",INDEX(Risks!$K$2:$K$501,MATCH(LARGE(Risks!$S$2:$S$501,ROWS(A$83:A84)),Risks!$S$2:$S$501,0))),"") | F84: =IFERROR(IF(INDEX(Risks!$M$2:$M$501,MATCH(LARGE(Risks!$S$2:$S$501,ROWS(A$83:A84)),Risks!$S$2:$S$501,0))="","",INDEX(Risks!$M$2:$M$501,MATCH(LARGE(Risks!$S$2:$S$501,ROWS(A$83:A84)),Risks!$S$2:$S$501,0))),"") | G84: =IFERROR(IF(INDEX(Risks!$L$2:$L$501,MATCH(LARGE(Risks!$S$2:$S$501,ROWS(A$83:A84)),Risks!$S$2:$S$501,0))="","",INDEX(Risks!$L$2:$L$501,MATCH(LARGE(Risks!$S$2:$S$501,ROWS(A$83:A84)),Risks!$S$2:$S$501,0))),"")
A85: =IFERROR(IF(INDEX(Risks!$C$2:$C$501,MATCH(LARGE(Risks!$S$2:$S$501,ROWS(A$83:A85)),Risks!$S$2:$S$501,0))="","",INDEX(Risks!$C$2:$C$501,MATCH(LARGE(Risks!$S$2:$S$501,ROWS(A$83:A85)),Risks!$S$2:$S$501,0))),"") | B85: =IFERROR(IF(INDEX(Risks!$A$2:$A$501,MATCH(LARGE(Risks!$S$2:$S$501,ROWS(A$83:A85)),Risks!$S$2:$S$501,0))="","",INDEX(Risks!$A$2:$A$501,MATCH(LARGE(Risks!$S$2:$S$501,ROWS(A$83:A85)),Risks!$S$2:$S$501,0))),"") | C85: =IFERROR(IF(INDEX(Risks!$N$2:$N$501,MATCH(LARGE(Risks!$S$2:$S$501,ROWS(A$83:A85)),Risks!$S$2:$S$501,0))="","",INDEX(Risks!$N$2:$N$501,MATCH(LARGE(Risks!$S$2:$S$501,ROWS(A$83:A85)),Risks!$S$2:$S$501,0))),"") | D85: =IFERROR(IF(INDEX(Risks!$O$2:$O$501,MATCH(LARGE(Risks!$S$2:$S$501,ROWS(A$83:A85)),Risks!$S$2:$S$501,0))="","",INDEX(Risks!$O$2:$O$501,MATCH(LARGE(Risks!$S$2:$S$501,ROWS(A$83:A85)),Risks!$S$2:$S$501,0))),"") | E85: =IFERROR(IF(INDEX(Risks!$K$2:$K$501,MATCH(LARGE(Risks!$S$2:$S$501,ROWS(A$83:A85)),Risks!$S$2:$S$501,0))="","",INDEX(Risks!$K$2:$K$501,MATCH(LARGE(Risks!$S$2:$S$501,ROWS(A$83:A85)),Risks!$S$2:$S$501,0))),"") | F85: =IFERROR(IF(INDEX(Risks!$M$2:$M$501,MATCH(LARGE(Risks!$S$2:$S$501,ROWS(A$83:A85)),Risks!$S$2:$S$501,0))="","",INDEX(Risks!$M$2:$M$501,MATCH(LARGE(Risks!$S$2:$S$501,ROWS(A$83:A85)),Risks!$S$2:$S$501,0))),"") | G85: =IFERROR(IF(INDEX(Risks!$L$2:$L$501,MATCH(LARGE(Risks!$S$2:$S$501,ROWS(A$83:A85)),Risks!$S$2:$S$501,0))="","",INDEX(Risks!$L$2:$L$501,MATCH(LARGE(Risks!$S$2:$S$501,ROWS(A$83:A85)),Risks!$S$2:$S$501,0))),"")
A86: =IFERROR(IF(INDEX(Risks!$C$2:$C$501,MATCH(LARGE(Risks!$S$2:$S$501,ROWS(A$83:A86)),Risks!$S$2:$S$501,0))="","",INDEX(Risks!$C$2:$C$501,MATCH(LARGE(Risks!$S$2:$S$501,ROWS(A$83:A86)),Risks!$S$2:$S$501,0))),"") | B86: =IFERROR(IF(INDEX(Risks!$A$2:$A$501,MATCH(LARGE(Risks!$S$2:$S$501,ROWS(A$83:A86)),Risks!$S$2:$S$501,0))="","",INDEX(Risks!$A$2:$A$501,MATCH(LARGE(Risks!$S$2:$S$501,ROWS(A$83:A86)),Risks!$S$2:$S$501,0))),"") | C86: =IFERROR(IF(INDEX(Risks!$N$2:$N$501,MATCH(LARGE(Risks!$S$2:$S$501,ROWS(A$83:A86)),Risks!$S$2:$S$501,0))="","",INDEX(Risks!$N$2:$N$501,MATCH(LARGE(Risks!$S$2:$S$501,ROWS(A$83:A86)),Risks!$S$2:$S$501,0))),"") | D86: =IFERROR(IF(INDEX(Risks!$O$2:$O$501,MATCH(LARGE(Risks!$S$2:$S$501,ROWS(A$83:A86)),Risks!$S$2:$S$501,0))="","",INDEX(Risks!$O$2:$O$501,MATCH(LARGE(Risks!$S$2:$S$501,ROWS(A$83:A86)),Risks!$S$2:$S$501,0))),"") | E86: =IFERROR(IF(INDEX(Risks!$K$2:$K$501,MATCH(LARGE(Risks!$S$2:$S$501,ROWS(A$83:A86)),Risks!$S$2:$S$501,0))="","",INDEX(Risks!$K$2:$K$501,MATCH(LARGE(Risks!$S$2:$S$501,ROWS(A$83:A86)),Risks!$S$2:$S$501,0))),"") | F86: =IFERROR(IF(INDEX(Risks!$M$2:$M$501,MATCH(LARGE(Risks!$S$2:$S$501,ROWS(A$83:A86)),Risks!$S$2:$S$501,0))="","",INDEX(Risks!$M$2:$M$501,MATCH(LARGE(Risks!$S$2:$S$501,ROWS(A$83:A86)),Risks!$S$2:$S$501,0))),"") | G86: =IFERROR(IF(INDEX(Risks!$L$2:$L$501,MATCH(LARGE(Risks!$S$2:$S$501,ROWS(A$83:A86)),Risks!$S$2:$S$501,0))="","",INDEX(Risks!$L$2:$L$501,MATCH(LARGE(Risks!$S$2:$S$501,ROWS(A$83:A86)),Risks!$S$2:$S$501,0))),"")
A87: =IFERROR(IF(INDEX(Risks!$C$2:$C$501,MATCH(LARGE(Risks!$S$2:$S$501,ROWS(A$83:A87)),Risks!$S$2:$S$501,0))="","",INDEX(Risks!$C$2:$C$501,MATCH(LARGE(Risks!$S$2:$S$501,ROWS(A$83:A87)),Risks!$S$2:$S$501,0))),"") | B87: =IFERROR(IF(INDEX(Risks!$A$2:$A$501,MATCH(LARGE(Risks!$S$2:$S$501,ROWS(A$83:A87)),Risks!$S$2:$S$501,0))="","",INDEX(Risks!$A$2:$A$501,MATCH(LARGE(Risks!$S$2:$S$501,ROWS(A$83:A87)),Risks!$S$2:$S$501,0))),"") | C87: =IFERROR(IF(INDEX(Risks!$N$2:$N$501,MATCH(LARGE(Risks!$S$2:$S$501,ROWS(A$83:A87)),Risks!$S$2:$S$501,0))="","",INDEX(Risks!$N$2:$N$501,MATCH(LARGE(Risks!$S$2:$S$501,ROWS(A$83:A87)),Risks!$S$2:$S$501,0))),"") | D87: =IFERROR(IF(INDEX(Risks!$O$2:$O$501,MATCH(LARGE(Risks!$S$2:$S$501,ROWS(A$83:A87)),Risks!$S$2:$S$501,0))="","",INDEX(Risks!$O$2:$O$501,MATCH(LARGE(Risks!$S$2:$S$501,ROWS(A$83:A87)),Risks!$S$2:$S$501,0))),"") | E87: =IFERROR(IF(INDEX(Risks!$K$2:$K$501,MATCH(LARGE(Risks!$S$2:$S$501,ROWS(A$83:A87)),Risks!$S$2:$S$501,0))="","",INDEX(Risks!$K$2:$K$501,MATCH(LARGE(Risks!$S$2:$S$501,ROWS(A$83:A87)),Risks!$S$2:$S$501,0))),"") | F87: =IFERROR(IF(INDEX(Risks!$M$2:$M$501,MATCH(LARGE(Risks!$S$2:$S$501,ROWS(A$83:A87)),Risks!$S$2:$S$501,0))="","",INDEX(Risks!$M$2:$M$501,MATCH(LARGE(Risks!$S$2:$S$501,ROWS(A$83:A87)),Risks!$S$2:$S$501,0))),"") | G87: =IFERROR(IF(INDEX(Risks!$L$2:$L$501,MATCH(LARGE(Risks!$S$2:$S$501,ROWS(A$83:A87)),Risks!$S$2:$S$501,0))="","",INDEX(Risks!$L$2:$L$501,MATCH(LARGE(Risks!$S$2:$S$501,ROWS(A$83:A87)),Risks!$S$2:$S$501,0))),"")
A88: =IFERROR(IF(INDEX(Risks!$C$2:$C$501,MATCH(LARGE(Risks!$S$2:$S$501,ROWS(A$83:A88)),Risks!$S$2:$S$501,0))="","",INDEX(Risks!$C$2:$C$501,MATCH(LARGE(Risks!$S$2:$S$501,ROWS(A$83:A88)),Risks!$S$2:$S$501,0))),"") | B88: =IFERROR(IF(INDEX(Risks!$A$2:$A$501,MATCH(LARGE(Risks!$S$2:$S$501,ROWS(A$83:A88)),Risks!$S$2:$S$501,0))="","",INDEX(Risks!$A$2:$A$501,MATCH(LARGE(Risks!$S$2:$S$501,ROWS(A$83:A88)),Risks!$S$2:$S$501,0))),"") | C88: =IFERROR(IF(INDEX(Risks!$N$2:$N$501,MATCH(LARGE(Risks!$S$2:$S$501,ROWS(A$83:A88)),Risks!$S$2:$S$501,0))="","",INDEX(Risks!$N$2:$N$501,MATCH(LARGE(Risks!$S$2:$S$501,ROWS(A$83:A88)),Risks!$S$2:$S$501,0))),"") | D88: =IFERROR(IF(INDEX(Risks!$O$2:$O$501,MATCH(LARGE(Risks!$S$2:$S$501,ROWS(A$83:A88)),Risks!$S$2:$S$501,0))="","",INDEX(Risks!$O$2:$O$501,MATCH(LARGE(Risks!$S$2:$S$501,ROWS(A$83:A88)),Risks!$S$2:$S$501,0))),"") | E88: =IFERROR(IF(INDEX(Risks!$K$2:$K$501,MATCH(LARGE(Risks!$S$2:$S$501,ROWS(A$83:A88)),Risks!$S$2:$S$501,0))="","",INDEX(Risks!$K$2:$K$501,MATCH(LARGE(Risks!$S$2:$S$501,ROWS(A$83:A88)),Risks!$S$2:$S$501,0))),"") | F88: =IFERROR(IF(INDEX(Risks!$M$2:$M$501,MATCH(LARGE(Risks!$S$2:$S$501,ROWS(A$83:A88)),Risks!$S$2:$S$501,0))="","",INDEX(Risks!$M$2:$M$501,MATCH(LARGE(Risks!$S$2:$S$501,ROWS(A$83:A88)),Risks!$S$2:$S$501,0))),"") | G88: =IFERROR(IF(INDEX(Risks!$L$2:$L$501,MATCH(LARGE(Risks!$S$2:$S$501,ROWS(A$83:A88)),Risks!$S$2:$S$501,0))="","",INDEX(Risks!$L$2:$L$501,MATCH(LARGE(Risks!$S$2:$S$501,ROWS(A$83:A88)),Risks!$S$2:$S$501,0))),"")
A89: =IFERROR(IF(INDEX(Risks!$C$2:$C$501,MATCH(LARGE(Risks!$S$2:$S$501,ROWS(A$83:A89)),Risks!$S$2:$S$501,0))="","",INDEX(Risks!$C$2:$C$501,MATCH(LARGE(Risks!$S$2:$S$501,ROWS(A$83:A89)),Risks!$S$2:$S$501,0))),"") | B89: =IFERROR(IF(INDEX(Risks!$A$2:$A$501,MATCH(LARGE(Risks!$S$2:$S$501,ROWS(A$83:A89)),Risks!$S$2:$S$501,0))="","",INDEX(Risks!$A$2:$A$501,MATCH(LARGE(Risks!$S$2:$S$501,ROWS(A$83:A89)),Risks!$S$2:$S$501,0))),"") | C89: =IFERROR(IF(INDEX(Risks!$N$2:$N$501,MATCH(LARGE(Risks!$S$2:$S$501,ROWS(A$83:A89)),Risks!$S$2:$S$501,0))="","",INDEX(Risks!$N$2:$N$501,MATCH(LARGE(Risks!$S$2:$S$501,ROWS(A$83:A89)),Risks!$S$2:$S$501,0))),"") | D89: =IFERROR(IF(INDEX(Risks!$O$2:$O$501,MATCH(LARGE(Risks!$S$2:$S$501,ROWS(A$83:A89)),Risks!$S$2:$S$501,0))="","",INDEX(Risks!$O$2:$O$501,MATCH(LARGE(Risks!$S$2:$S$501,ROWS(A$83:A89)),Risks!$S$2:$S$501,0))),"") | E89: =IFERROR(IF(INDEX(Risks!$K$2:$K$501,MATCH(LARGE(Risks!$S$2:$S$501,ROWS(A$83:A89)),Risks!$S$2:$S$501,0))="","",INDEX(Risks!$K$2:$K$501,MATCH(LARGE(Risks!$S$2:$S$501,ROWS(A$83:A89)),Risks!$S$2:$S$501,0))),"") | F89: =IFERROR(IF(INDEX(Risks!$M$2:$M$501,MATCH(LARGE(Risks!$S$2:$S$501,ROWS(A$83:A89)),Risks!$S$2:$S$501,0))="","",INDEX(Risks!$M$2:$M$501,MATCH(LARGE(Risks!$S$2:$S$501,ROWS(A$83:A89)),Risks!$S$2:$S$501,0))),"") | G89: =IFERROR(IF(INDEX(Risks!$L$2:$L$501,MATCH(LARGE(Risks!$S$2:$S$501,ROWS(A$83:A89)),Risks!$S$2:$S$501,0))="","",INDEX(Risks!$L$2:$L$501,MATCH(LARGE(Risks!$S$2:$S$501,ROWS(A$83:A89)),Risks!$S$2:$S$501,0))),"")
A90: =IFERROR(IF(INDEX(Risks!$C$2:$C$501,MATCH(LARGE(Risks!$S$2:$S$501,ROWS(A$83:A90)),Risks!$S$2:$S$501,0))="","",INDEX(Risks!$C$2:$C$501,MATCH(LARGE(Risks!$S$2:$S$501,ROWS(A$83:A90)),Risks!$S$2:$S$501,0))),"") | B90: =IFERROR(IF(INDEX(Risks!$A$2:$A$501,MATCH(LARGE(Risks!$S$2:$S$501,ROWS(A$83:A90)),Risks!$S$2:$S$501,0))="","",INDEX(Risks!$A$2:$A$501,MATCH(LARGE(Risks!$S$2:$S$501,ROWS(A$83:A90)),Risks!$S$2:$S$501,0))),"") | C90: =IFERROR(IF(INDEX(Risks!$N$2:$N$501,MATCH(LARGE(Risks!$S$2:$S$501,ROWS(A$83:A90)),Risks!$S$2:$S$501,0))="","",INDEX(Risks!$N$2:$N$501,MATCH(LARGE(Risks!$S$2:$S$501,ROWS(A$83:A90)),Risks!$S$2:$S$501,0))),"") | D90: =IFERROR(IF(INDEX(Risks!$O$2:$O$501,MATCH(LARGE(Risks!$S$2:$S$501,ROWS(A$83:A90)),Risks!$S$2:$S$501,0))="","",INDEX(Risks!$O$2:$O$501,MATCH(LARGE(Risks!$S$2:$S$501,ROWS(A$83:A90)),Risks!$S$2:$S$501,0))),"") | E90: =IFERROR(IF(INDEX(Risks!$K$2:$K$501,MATCH(LARGE(Risks!$S$2:$S$501,ROWS(A$83:A90)),Risks!$S$2:$S$501,0))="","",INDEX(Risks!$K$2:$K$501,MATCH(LARGE(Risks!$S$2:$S$501,ROWS(A$83:A90)),Risks!$S$2:$S$501,0))),"") | F90: =IFERROR(IF(INDEX(Risks!$M$2:$M$501,MATCH(LARGE(Risks!$S$2:$S$501,ROWS(A$83:A90)),Risks!$S$2:$S$501,0))="","",INDEX(Risks!$M$2:$M$501,MATCH(LARGE(Risks!$S$2:$S$501,ROWS(A$83:A90)),Risks!$S$2:$S$501,0))),"") | G90: =IFERROR(IF(INDEX(Risks!$L$2:$L$501,MATCH(LARGE(Risks!$S$2:$S$501,ROWS(A$83:A90)),Risks!$S$2:$S$501,0))="","",INDEX(Risks!$L$2:$L$501,MATCH(LARGE(Risks!$S$2:$S$501,ROWS(A$83:A90)),Risks!$S$2:$S$501,0))),"")
A91: =IFERROR(IF(INDEX(Risks!$C$2:$C$501,MATCH(LARGE(Risks!$S$2:$S$501,ROWS(A$83:A91)),Risks!$S$2:$S$501,0))="","",INDEX(Risks!$C$2:$C$501,MATCH(LARGE(Risks!$S$2:$S$501,ROWS(A$83:A91)),Risks!$S$2:$S$501,0))),"") | B91: =IFERROR(IF(INDEX(Risks!$A$2:$A$501,MATCH(LARGE(Risks!$S$2:$S$501,ROWS(A$83:A91)),Risks!$S$2:$S$501,0))="","",INDEX(Risks!$A$2:$A$501,MATCH(LARGE(Risks!$S$2:$S$501,ROWS(A$83:A91)),Risks!$S$2:$S$501,0))),"") | C91: =IFERROR(IF(INDEX(Risks!$N$2:$N$501,MATCH(LARGE(Risks!$S$2:$S$501,ROWS(A$83:A91)),Risks!$S$2:$S$501,0))="","",INDEX(Risks!$N$2:$N$501,MATCH(LARGE(Risks!$S$2:$S$501,ROWS(A$83:A91)),Risks!$S$2:$S$501,0))),"") | D91: =IFERROR(IF(INDEX(Risks!$O$2:$O$501,MATCH(LARGE(Risks!$S$2:$S$501,ROWS(A$83:A91)),Risks!$S$2:$S$501,0))="","",INDEX(Risks!$O$2:$O$501,MATCH(LARGE(Risks!$S$2:$S$501,ROWS(A$83:A91)),Risks!$S$2:$S$501,0))),"") | E91: =IFERROR(IF(INDEX(Risks!$K$2:$K$501,MATCH(LARGE(Risks!$S$2:$S$501,ROWS(A$83:A91)),Risks!$S$2:$S$501,0))="","",INDEX(Risks!$K$2:$K$501,MATCH(LARGE(Risks!$S$2:$S$501,ROWS(A$83:A91)),Risks!$S$2:$S$501,0))),"") | F91: =IFERROR(IF(INDEX(Risks!$M$2:$M$501,MATCH(LARGE(Risks!$S$2:$S$501,ROWS(A$83:A91)),Risks!$S$2:$S$501,0))="","",INDEX(Risks!$M$2:$M$501,MATCH(LARGE(Risks!$S$2:$S$501,ROWS(A$83:A91)),Risks!$S$2:$S$501,0))),"") | G91: =IFERROR(IF(INDEX(Risks!$L$2:$L$501,MATCH(LARGE(Risks!$S$2:$S$501,ROWS(A$83:A91)),Risks!$S$2:$S$501,0))="","",INDEX(Risks!$L$2:$L$501,MATCH(LARGE(Risks!$S$2:$S$501,ROWS(A$83:A91)),Risks!$S$2:$S$501,0))),"")
A92: =IFERROR(IF(INDEX(Risks!$C$2:$C$501,MATCH(LARGE(Risks!$S$2:$S$501,ROWS(A$83:A92)),Risks!$S$2:$S$501,0))="","",INDEX(Risks!$C$2:$C$501,MATCH(LARGE(Risks!$S$2:$S$501,ROWS(A$83:A92)),Risks!$S$2:$S$501,0))),"") | B92: =IFERROR(IF(INDEX(Risks!$A$2:$A$501,MATCH(LARGE(Risks!$S$2:$S$501,ROWS(A$83:A92)),Risks!$S$2:$S$501,0))="","",INDEX(Risks!$A$2:$A$501,MATCH(LARGE(Risks!$S$2:$S$501,ROWS(A$83:A92)),Risks!$S$2:$S$501,0))),"") | C92: =IFERROR(IF(INDEX(Risks!$N$2:$N$501,MATCH(LARGE(Risks!$S$2:$S$501,ROWS(A$83:A92)),Risks!$S$2:$S$501,0))="","",INDEX(Risks!$N$2:$N$501,MATCH(LARGE(Risks!$S$2:$S$501,ROWS(A$83:A92)),Risks!$S$2:$S$501,0))),"") | D92: =IFERROR(IF(INDEX(Risks!$O$2:$O$501,MATCH(LARGE(Risks!$S$2:$S$501,ROWS(A$83:A92)),Risks!$S$2:$S$501,0))="","",INDEX(Risks!$O$2:$O$501,MATCH(LARGE(Risks!$S$2:$S$501,ROWS(A$83:A92)),Risks!$S$2:$S$501,0))),"") | E92: =IFERROR(IF(INDEX(Risks!$K$2:$K$501,MATCH(LARGE(Risks!$S$2:$S$501,ROWS(A$83:A92)),Risks!$S$2:$S$501,0))="","",INDEX(Risks!$K$2:$K$501,MATCH(LARGE(Risks!$S$2:$S$501,ROWS(A$83:A92)),Risks!$S$2:$S$501,0))),"") | F92: =IFERROR(IF(INDEX(Risks!$M$2:$M$501,MATCH(LARGE(Risks!$S$2:$S$501,ROWS(A$83:A92)),Risks!$S$2:$S$501,0))="","",INDEX(Risks!$M$2:$M$501,MATCH(LARGE(Risks!$S$2:$S$501,ROWS(A$83:A92)),Risks!$S$2:$S$501,0))),"") | G92: =IFERROR(IF(INDEX(Risks!$L$2:$L$501,MATCH(LARGE(Risks!$S$2:$S$501,ROWS(A$83:A92)),Risks!$S$2:$S$501,0))="","",INDEX(Risks!$L$2:$L$501,MATCH(LARGE(Risks!$S$2:$S$501,ROWS(A$83:A92)),Risks!$S$2:$S$501,0))),"")

Sheet Project Summary
A1: Project Summary
A2: Pick a project in C3. Print this sheet (or use the PDF macro) as a one-page project report.
B3: Project:
B5: Overview | E5: Health
B6: Status | C6: =IFERROR(IF(INDEX(Projects!$D$2:$D$101,MATCH($C$3,Projects!$A$2:$A$101,0))="","",INDEX(Projects!$D$2:$D$101,MATCH($C$3,Projects!$A$2:$A$101,0))),"") | E6: Overall | F6: =IFERROR(IF(INDEX(Projects!$AF$2:$AF$101,MATCH($C$3,Projects!$A$2:$A$101,0))="","",INDEX(Projects!$AF$2:$AF$101,MATCH($C$3,Projects!$A$2:$A$101,0))),"")
B7: Project Manager | C7: =IFERROR(IF(INDEX(Projects!$F$2:$F$101,MATCH($C$3,Projects!$A$2:$A$101,0))="","",INDEX(Projects!$F$2:$F$101,MATCH($C$3,Projects!$A$2:$A$101,0))),"") | E7: Schedule | F7: =IFERROR(IF(INDEX(Projects!$Z$2:$Z$101,MATCH($C$3,Projects!$A$2:$A$101,0))="","",INDEX(Projects!$Z$2:$Z$101,MATCH($C$3,Projects!$A$2:$A$101,0))),"")
B8: Project Director | C8: =IFERROR(IF(INDEX(Projects!$G$2:$G$101,MATCH($C$3,Projects!$A$2:$A$101,0))="","",INDEX(Projects!$G$2:$G$101,MATCH($C$3,Projects!$A$2:$A$101,0))),"") | E8: Budget | F8: =IFERROR(IF(INDEX(Projects!$AB$2:$AB$101,MATCH($C$3,Projects!$A$2:$A$101,0))="","",INDEX(Projects!$AB$2:$AB$101,MATCH($C$3,Projects!$A$2:$A$101,0))),"")
B9: Project Sponsor | C9: =IFERROR(IF(INDEX(Projects!$H$2:$H$101,MATCH($C$3,Projects!$A$2:$A$101,0))="","",INDEX(Projects!$H$2:$H$101,MATCH($C$3,Projects!$A$2:$A$101,0))),"") | E9: Risk | F9: =IFERROR(IF(INDEX(Projects!$AE$2:$AE$101,MATCH($C$3,Projects!$A$2:$A$101,0))="","",INDEX(Projects!$AE$2:$AE$101,MATCH($C$3,Projects!$A$2:$A$101,0))),"")
B10: Location | C10: =IFERROR(IF(INDEX(Projects!$I$2:$I$101,MATCH($C$3,Projects!$A$2:$A$101,0))="","",INDEX(Projects!$I$2:$I$101,MATCH($C$3,Projects!$A$2:$A$101,0))),"") | E10: =IFERROR(IF(INDEX(Projects!$AK$2:$AK$101,MATCH($C$3,Projects!$A$2:$A$101,0))="","",INDEX(Projects!$AK$2:$AK$101,MATCH($C$3,Projects!$A$2:$A$101,0))),"")
B11: Contractor | C11: =IFERROR(IF(INDEX(Projects!$J$2:$J$101,MATCH($C$3,Projects!$A$2:$A$101,0))="","",INDEX(Projects!$J$2:$J$101,MATCH($C$3,Projects!$A$2:$A$101,0))),"")
B13: Budget | E13: Schedule
B14: Original Budget | C14: =IFERROR(IF(INDEX(Projects!$L$2:$L$101,MATCH($C$3,Projects!$A$2:$A$101,0))="","",INDEX(Projects!$L$2:$L$101,MATCH($C$3,Projects!$A$2:$A$101,0))),"") | E14: Start Date | F14: =IFERROR(IF(INDEX(Projects!$N$2:$N$101,MATCH($C$3,Projects!$A$2:$A$101,0))="","",INDEX(Projects!$N$2:$N$101,MATCH($C$3,Projects!$A$2:$A$101,0))),"")
B15: Latest Approved Budget | C15: =IFERROR(IF(INDEX(Projects!$M$2:$M$101,MATCH($C$3,Projects!$A$2:$A$101,0))="","",INDEX(Projects!$M$2:$M$101,MATCH($C$3,Projects!$A$2:$A$101,0))),"") | E15: Target Completion | F15: =IFERROR(IF(INDEX(Projects!$O$2:$O$101,MATCH($C$3,Projects!$A$2:$A$101,0))="","",INDEX(Projects!$O$2:$O$101,MATCH($C$3,Projects!$A$2:$A$101,0))),"")
B16: Approved Variations | C16: =IFERROR(IF(INDEX(Projects!$Q$2:$Q$101,MATCH($C$3,Projects!$A$2:$A$101,0))="","",INDEX(Projects!$Q$2:$Q$101,MATCH($C$3,Projects!$A$2:$A$101,0))),"") | E16: Approved EOT days | F16: =IFERROR(IF(INDEX(Projects!$V$2:$V$101,MATCH($C$3,Projects!$A$2:$A$101,0))="","",INDEX(Projects!$V$2:$V$101,MATCH($C$3,Projects!$A$2:$A$101,0))),"")
B17: Effective Budget | C17: =IFERROR(IF(INDEX(Projects!$R$2:$R$101,MATCH($C$3,Projects!$A$2:$A$101,0))="","",INDEX(Projects!$R$2:$R$101,MATCH($C$3,Projects!$A$2:$A$101,0))),"") | E17: Revised Completion | F17: =IFERROR(IF(INDEX(Projects!$W$2:$W$101,MATCH($C$3,Projects!$A$2:$A$101,0))="","",INDEX(Projects!$W$2:$W$101,MATCH($C$3,Projects!$A$2:$A$101,0))),"")
B18: Expenditure to Date | C18: =IFERROR(IF(INDEX(Projects!$S$2:$S$101,MATCH($C$3,Projects!$A$2:$A$101,0))="","",INDEX(Projects!$S$2:$S$101,MATCH($C$3,Projects!$A$2:$A$101,0))),"") | E18: Actual Completion | F18: =IFERROR(IF(INDEX(Projects!$P$2:$P$101,MATCH($C$3,Projects!$A$2:$A$101,0))="","",INDEX(Projects!$P$2:$P$101,MATCH($C$3,Projects!$A$2:$A$101,0))),"")
B19: Forecast at Completion | C19: =IFERROR(IF(INDEX(Projects!$T$2:$T$101,MATCH($C$3,Projects!$A$2:$A$101,0))="","",INDEX(Projects!$T$2:$T$101,MATCH($C$3,Projects!$A$2:$A$101,0))),"") | E19: Timeframe elapsed | F19: =IFERROR(IF(INDEX(Projects!$Y$2:$Y$101,MATCH($C$3,Projects!$A$2:$A$101,0))="","",INDEX(Projects!$Y$2:$Y$101,MATCH($C$3,Projects!$A$2:$A$101,0))),"")
B20: Variance (budget - forecast) | C20: =IFERROR(IF(INDEX(Projects!$U$2:$U$101,MATCH($C$3,Projects!$A$2:$A$101,0))="","",INDEX(Projects!$U$2:$U$101,MATCH($C$3,Projects!$A$2:$A$101,0))),"")
B21: Forecast % of budget | C21: =IFERROR(IF(INDEX(Projects!$AA$2:$AA$101,MATCH($C$3,Projects!$A$2:$A$101,0))="","",INDEX(Projects!$AA$2:$AA$101,MATCH($C$3,Projects!$A$2:$A$101,0))),"") | E21: Open items
E22: Open tasks | F22: =IFERROR(IF(INDEX(Projects!$AG$2:$AG$101,MATCH($C$3,Projects!$A$2:$A$101,0))="","",INDEX(Projects!$AG$2:$AG$101,MATCH($C$3,Projects!$A$2:$A$101,0))),"")
E23: Open actions | F23: =IFERROR(IF(INDEX(Projects!$AH$2:$AH$101,MATCH($C$3,Projects!$A$2:$A$101,0))="","",INDEX(Projects!$AH$2:$AH$101,MATCH($C$3,Projects!$A$2:$A$101,0))),"")
E24: Open RFIs | F24: =IFERROR(IF(INDEX(Projects!$AI$2:$AI$101,MATCH($C$3,Projects!$A$2:$A$101,0))="","",INDEX(Projects!$AI$2:$AI$101,MATCH($C$3,Projects!$A$2:$A$101,0))),"")
E25: Open defects | F25: =IFERROR(IF(INDEX(Projects!$AJ$2:$AJ$101,MATCH($C$3,Projects!$A$2:$A$101,0))="","",INDEX(Projects!$AJ$2:$AJ$101,MATCH($C$3,Projects!$A$2:$A$101,0))),"")
B27: Milestones
B28: Activity | C28: WBS | D28: % Complete | E28: Original | F28: Forecast | G28: Slip (days)
B29: =IFERROR(IF(INDEX(Milestones!$C$2:$C$501,MATCH(ROWS(B$29:B29),Milestones!$K$2:$K$501,0))="","",INDEX(Milestones!$C$2:$C$501,MATCH(ROWS(B$29:B29),Milestones!$K$2:$K$501,0))),"") | C29: =IFERROR(IF(INDEX(Milestones!$B$2:$B$501,MATCH(ROWS(B$29:B29),Milestones!$K$2:$K$501,0))="","",INDEX(Milestones!$B$2:$B$501,MATCH(ROWS(B$29:B29),Milestones!$K$2:$K$501,0))),"") | D29: =IFERROR(IF(INDEX(Milestones!$D$2:$D$501,MATCH(ROWS(B$29:B29),Milestones!$K$2:$K$501,0))="","",INDEX(Milestones!$D$2:$D$501,MATCH(ROWS(B$29:B29),Milestones!$K$2:$K$501,0))),"") | E29: =IFERROR(IF(INDEX(Milestones!$F$2:$F$501,MATCH(ROWS(B$29:B29),Milestones!$K$2:$K$501,0))="","",INDEX(Milestones!$F$2:$F$501,MATCH(ROWS(B$29:B29),Milestones!$K$2:$K$501,0))),"") | F29: =IFERROR(IF(INDEX(Milestones!$G$2:$G$501,MATCH(ROWS(B$29:B29),Milestones!$K$2:$K$501,0))="","",INDEX(Milestones!$G$2:$G$501,MATCH(ROWS(B$29:B29),Milestones!$K$2:$K$501,0))),"") | G29: =IFERROR(IF(INDEX(Milestones!$J$2:$J$501,MATCH(ROWS(B$29:B29),Milestones!$K$2:$K$501,0))="","",INDEX(Milestones!$J$2:$J$501,MATCH(ROWS(B$29:B29),Milestones!$K$2:$K$501,0))),"")
B30: =IFERROR(IF(INDEX(Milestones!$C$2:$C$501,MATCH(ROWS(B$29:B30),Milestones!$K$2:$K$501,0))="","",INDEX(Milestones!$C$2:$C$501,MATCH(ROWS(B$29:B30),Milestones!$K$2:$K$501,0))),"") | C30: =IFERROR(IF(INDEX(Milestones!$B$2:$B$501,MATCH(ROWS(B$29:B30),Milestones!$K$2:$K$501,0))="","",INDEX(Milestones!$B$2:$B$501,MATCH(ROWS(B$29:B30),Milestones!$K$2:$K$501,0))),"") | D30: =IFERROR(IF(INDEX(Milestones!$D$2:$D$501,MATCH(ROWS(B$29:B30),Milestones!$K$2:$K$501,0))="","",INDEX(Milestones!$D$2:$D$501,MATCH(ROWS(B$29:B30),Milestones!$K$2:$K$501,0))),"") | E30: =IFERROR(IF(INDEX(Milestones!$F$2:$F$501,MATCH(ROWS(B$29:B30),Milestones!$K$2:$K$501,0))="","",INDEX(Milestones!$F$2:$F$501,MATCH(ROWS(B$29:B30),Milestones!$K$2:$K$501,0))),"") | F30: =IFERROR(IF(INDEX(Milestones!$G$2:$G$501,MATCH(ROWS(B$29:B30),Milestones!$K$2:$K$501,0))="","",INDEX(Milestones!$G$2:$G$501,MATCH(ROWS(B$29:B30),Milestones!$K$2:$K$501,0))),"") | G30: =IFERROR(IF(INDEX(Milestones!$J$2:$J$501,MATCH(ROWS(B$29:B30),Milestones!$K$2:$K$501,0))="","",INDEX(Milestones!$J$2:$J$501,MATCH(ROWS(B$29:B30),Milestones!$K$2:$K$501,0))),"")
B31: =IFERROR(IF(INDEX(Milestones!$C$2:$C$501,MATCH(ROWS(B$29:B31),Milestones!$K$2:$K$501,0))="","",INDEX(Milestones!$C$2:$C$501,MATCH(ROWS(B$29:B31),Milestones!$K$2:$K$501,0))),"") | C31: =IFERROR(IF(INDEX(Milestones!$B$2:$B$501,MATCH(ROWS(B$29:B31),Milestones!$K$2:$K$501,0))="","",INDEX(Milestones!$B$2:$B$501,MATCH(ROWS(B$29:B31),Milestones!$K$2:$K$501,0))),"") | D31: =IFERROR(IF(INDEX(Milestones!$D$2:$D$501,MATCH(ROWS(B$29:B31),Milestones!$K$2:$K$501,0))="","",INDEX(Milestones!$D$2:$D$501,MATCH(ROWS(B$29:B31),Milestones!$K$2:$K$501,0))),"") | E31: =IFERROR(IF(INDEX(Milestones!$F$2:$F$501,MATCH(ROWS(B$29:B31),Milestones!$K$2:$K$501,0))="","",INDEX(Milestones!$F$2:$F$501,MATCH(ROWS(B$29:B31),Milestones!$K$2:$K$501,0))),"") | F31: =IFERROR(IF(INDEX(Milestones!$G$2:$G$501,MATCH(ROWS(B$29:B31),Milestones!$K$2:$K$501,0))="","",INDEX(Milestones!$G$2:$G$501,MATCH(ROWS(B$29:B31),Milestones!$K$2:$K$501,0))),"") | G31: =IFERROR(IF(INDEX(Milestones!$J$2:$J$501,MATCH(ROWS(B$29:B31),Milestones!$K$2:$K$501,0))="","",INDEX(Milestones!$J$2:$J$501,MATCH(ROWS(B$29:B31),Milestones!$K$2:$K$501,0))),"")
B32: =IFERROR(IF(INDEX(Milestones!$C$2:$C$501,MATCH(ROWS(B$29:B32),Milestones!$K$2:$K$501,0))="","",INDEX(Milestones!$C$2:$C$501,MATCH(ROWS(B$29:B32),Milestones!$K$2:$K$501,0))),"") | C32: =IFERROR(IF(INDEX(Milestones!$B$2:$B$501,MATCH(ROWS(B$29:B32),Milestones!$K$2:$K$501,0))="","",INDEX(Milestones!$B$2:$B$501,MATCH(ROWS(B$29:B32),Milestones!$K$2:$K$501,0))),"") | D32: =IFERROR(IF(INDEX(Milestones!$D$2:$D$501,MATCH(ROWS(B$29:B32),Milestones!$K$2:$K$501,0))="","",INDEX(Milestones!$D$2:$D$501,MATCH(ROWS(B$29:B32),Milestones!$K$2:$K$501,0))),"") | E32: =IFERROR(IF(INDEX(Milestones!$F$2:$F$501,MATCH(ROWS(B$29:B32),Milestones!$K$2:$K$501,0))="","",INDEX(Milestones!$F$2:$F$501,MATCH(ROWS(B$29:B32),Milestones!$K$2:$K$501,0))),"") | F32: =IFERROR(IF(INDEX(Milestones!$G$2:$G$501,MATCH(ROWS(B$29:B32),Milestones!$K$2:$K$501,0))="","",INDEX(Milestones!$G$2:$G$501,MATCH(ROWS(B$29:B32),Milestones!$K$2:$K$501,0))),"") | G32: =IFERROR(IF(INDEX(Milestones!$J$2:$J$501,MATCH(ROWS(B$29:B32),Milestones!$K$2:$K$501,0))="","",INDEX(Milestones!$J$2:$J$501,MATCH(ROWS(B$29:B32),Milestones!$K$2:$K$501,0))),"")
B33: =IFERROR(IF(INDEX(Milestones!$C$2:$C$501,MATCH(ROWS(B$29:B33),Milestones!$K$2:$K$501,0))="","",INDEX(Milestones!$C$2:$C$501,MATCH(ROWS(B$29:B33),Milestones!$K$2:$K$501,0))),"") | C33: =IFERROR(IF(INDEX(Milestones!$B$2:$B$501,MATCH(ROWS(B$29:B33),Milestones!$K$2:$K$501,0))="","",INDEX(Milestones!$B$2:$B$501,MATCH(ROWS(B$29:B33),Milestones!$K$2:$K$501,0))),"") | D33: =IFERROR(IF(INDEX(Milestones!$D$2:$D$501,MATCH(ROWS(B$29:B33),Milestones!$K$2:$K$501,0))="","",INDEX(Milestones!$D$2:$D$501,MATCH(ROWS(B$29:B33),Milestones!$K$2:$K$501,0))),"") | E33: =IFERROR(IF(INDEX(Milestones!$F$2:$F$501,MATCH(ROWS(B$29:B33),Milestones!$K$2:$K$501,0))="","",INDEX(Milestones!$F$2:$F$501,MATCH(ROWS(B$29:B33),Milestones!$K$2:$K$501,0))),"") | F33: =IFERROR(IF(INDEX(Milestones!$G$2:$G$501,MATCH(ROWS(B$29:B33),Milestones!$K$2:$K$501,0))="","",INDEX(Milestones!$G$2:$G$501,MATCH(ROWS(B$29:B33),Milestones!$K$2:$K$501,0))),"") | G33: =IFERROR(IF(INDEX(Milestones!$J$2:$J$501,MATCH(ROWS(B$29:B33),Milestones!$K$2:$K$501,0))="","",INDEX(Milestones!$J$2:$J$501,MATCH(ROWS(B$29:B33),Milestones!$K$2:$K$501,0))),"")
B34: =IFERROR(IF(INDEX(Milestones!$C$2:$C$501,MATCH(ROWS(B$29:B34),Milestones!$K$2:$K$501,0))="","",INDEX(Milestones!$C$2:$C$501,MATCH(ROWS(B$29:B34),Milestones!$K$2:$K$501,0))),"") | C34: =IFERROR(IF(INDEX(Milestones!$B$2:$B$501,MATCH(ROWS(B$29:B34),Milestones!$K$2:$K$501,0))="","",INDEX(Milestones!$B$2:$B$501,MATCH(ROWS(B$29:B34),Milestones!$K$2:$K$501,0))),"") | D34: =IFERROR(IF(INDEX(Milestones!$D$2:$D$501,MATCH(ROWS(B$29:B34),Milestones!$K$2:$K$501,0))="","",INDEX(Milestones!$D$2:$D$501,MATCH(ROWS(B$29:B34),Milestones!$K$2:$K$501,0))),"") | E34: =IFERROR(IF(INDEX(Milestones!$F$2:$F$501,MATCH(ROWS(B$29:B34),Milestones!$K$2:$K$501,0))="","",INDEX(Milestones!$F$2:$F$501,MATCH(ROWS(B$29:B34),Milestones!$K$2:$K$501,0))),"") | F34: =IFERROR(IF(INDEX(Milestones!$G$2:$G$501,MATCH(ROWS(B$29:B34),Milestones!$K$2:$K$501,0))="","",INDEX(Milestones!$G$2:$G$501,MATCH(ROWS(B$29:B34),Milestones!$K$2:$K$501,0))),"") | G34: =IFERROR(IF(INDEX(Milestones!$J$2:$J$501,MATCH(ROWS(B$29:B34),Milestones!$K$2:$K$501,0))="","",INDEX(Milestones!$J$2:$J$501,MATCH(ROWS(B$29:B34),Milestones!$K$2:$K$501,0))),"")
B35: =IFERROR(IF(INDEX(Milestones!$C$2:$C$501,MATCH(ROWS(B$29:B35),Milestones!$K$2:$K$501,0))="","",INDEX(Milestones!$C$2:$C$501,MATCH(ROWS(B$29:B35),Milestones!$K$2:$K$501,0))),"") | C35: =IFERROR(IF(INDEX(Milestones!$B$2:$B$501,MATCH(ROWS(B$29:B35),Milestones!$K$2:$K$501,0))="","",INDEX(Milestones!$B$2:$B$501,MATCH(ROWS(B$29:B35),Milestones!$K$2:$K$501,0))),"") | D35: =IFERROR(IF(INDEX(Milestones!$D$2:$D$501,MATCH(ROWS(B$29:B35),Milestones!$K$2:$K$501,0))="","",INDEX(Milestones!$D$2:$D$501,MATCH(ROWS(B$29:B35),Milestones!$K$2:$K$501,0))),"") | E35: =IFERROR(IF(INDEX(Milestones!$F$2:$F$501,MATCH(ROWS(B$29:B35),Milestones!$K$2:$K$501,0))="","",INDEX(Milestones!$F$2:$F$501,MATCH(ROWS(B$29:B35),Milestones!$K$2:$K$501,0))),"") | F35: =IFERROR(IF(INDEX(Milestones!$G$2:$G$501,MATCH(ROWS(B$29:B35),Milestones!$K$2:$K$501,0))="","",INDEX(Milestones!$G$2:$G$501,MATCH(ROWS(B$29:B35),Milestones!$K$2:$K$501,0))),"") | G35: =IFERROR(IF(INDEX(Milestones!$J$2:$J$501,MATCH(ROWS(B$29:B35),Milestones!$K$2:$K$501,0))="","",INDEX(Milestones!$J$2:$J$501,MATCH(ROWS(B$29:B35),Milestones!$K$2:$K$501,0))),"")
B36: =IFERROR(IF(INDEX(Milestones!$C$2:$C$501,MATCH(ROWS(B$29:B36),Milestones!$K$2:$K$501,0))="","",INDEX(Milestones!$C$2:$C$501,MATCH(ROWS(B$29:B36),Milestones!$K$2:$K$501,0))),"") | C36: =IFERROR(IF(INDEX(Milestones!$B$2:$B$501,MATCH(ROWS(B$29:B36),Milestones!$K$2:$K$501,0))="","",INDEX(Milestones!$B$2:$B$501,MATCH(ROWS(B$29:B36),Milestones!$K$2:$K$501,0))),"") | D36: =IFERROR(IF(INDEX(Milestones!$D$2:$D$501,MATCH(ROWS(B$29:B36),Milestones!$K$2:$K$501,0))="","",INDEX(Milestones!$D$2:$D$501,MATCH(ROWS(B$29:B36),Milestones!$K$2:$K$501,0))),"") | E36: =IFERROR(IF(INDEX(Milestones!$F$2:$F$501,MATCH(ROWS(B$29:B36),Milestones!$K$2:$K$501,0))="","",INDEX(Milestones!$F$2:$F$501,MATCH(ROWS(B$29:B36),Milestones!$K$2:$K$501,0))),"") | F36: =IFERROR(IF(INDEX(Milestones!$G$2:$G$501,MATCH(ROWS(B$29:B36),Milestones!$K$2:$K$501,0))="","",INDEX(Milestones!$G$2:$G$501,MATCH(ROWS(B$29:B36),Milestones!$K$2:$K$501,0))),"") | G36: =IFERROR(IF(INDEX(Milestones!$J$2:$J$501,MATCH(ROWS(B$29:B36),Milestones!$K$2:$K$501,0))="","",INDEX(Milestones!$J$2:$J$501,MATCH(ROWS(B$29:B36),Milestones!$K$2:$K$501,0))),"")
B37: =IFERROR(IF(INDEX(Milestones!$C$2:$C$501,MATCH(ROWS(B$29:B37),Milestones!$K$2:$K$501,0))="","",INDEX(Milestones!$C$2:$C$501,MATCH(ROWS(B$29:B37),Milestones!$K$2:$K$501,0))),"") | C37: =IFERROR(IF(INDEX(Milestones!$B$2:$B$501,MATCH(ROWS(B$29:B37),Milestones!$K$2:$K$501,0))="","",INDEX(Milestones!$B$2:$B$501,MATCH(ROWS(B$29:B37),Milestones!$K$2:$K$501,0))),"") | D37: =IFERROR(IF(INDEX(Milestones!$D$2:$D$501,MATCH(ROWS(B$29:B37),Milestones!$K$2:$K$501,0))="","",INDEX(Milestones!$D$2:$D$501,MATCH(ROWS(B$29:B37),Milestones!$K$2:$K$501,0))),"") | E37: =IFERROR(IF(INDEX(Milestones!$F$2:$F$501,MATCH(ROWS(B$29:B37),Milestones!$K$2:$K$501,0))="","",INDEX(Milestones!$F$2:$F$501,MATCH(ROWS(B$29:B37),Milestones!$K$2:$K$501,0))),"") | F37: =IFERROR(IF(INDEX(Milestones!$G$2:$G$501,MATCH(ROWS(B$29:B37),Milestones!$K$2:$K$501,0))="","",INDEX(Milestones!$G$2:$G$501,MATCH(ROWS(B$29:B37),Milestones!$K$2:$K$501,0))),"") | G37: =IFERROR(IF(INDEX(Milestones!$J$2:$J$501,MATCH(ROWS(B$29:B37),Milestones!$K$2:$K$501,0))="","",INDEX(Milestones!$J$2:$J$501,MATCH(ROWS(B$29:B37),Milestones!$K$2:$K$501,0))),"")
B38: =IFERROR(IF(INDEX(Milestones!$C$2:$C$501,MATCH(ROWS(B$29:B38),Milestones!$K$2:$K$501,0))="","",INDEX(Milestones!$C$2:$C$501,MATCH(ROWS(B$29:B38),Milestones!$K$2:$K$501,0))),"") | C38: =IFERROR(IF(INDEX(Milestones!$B$2:$B$501,MATCH(ROWS(B$29:B38),Milestones!$K$2:$K$501,0))="","",INDEX(Milestones!$B$2:$B$501,MATCH(ROWS(B$29:B38),Milestones!$K$2:$K$501,0))),"") | D38: =IFERROR(IF(INDEX(Milestones!$D$2:$D$501,MATCH(ROWS(B$29:B38),Milestones!$K$2:$K$501,0))="","",INDEX(Milestones!$D$2:$D$501,MATCH(ROWS(B$29:B38),Milestones!$K$2:$K$501,0))),"") | E38: =IFERROR(IF(INDEX(Milestones!$F$2:$F$501,MATCH(ROWS(B$29:B38),Milestones!$K$2:$K$501,0))="","",INDEX(Milestones!$F$2:$F$501,MATCH(ROWS(B$29:B38),Milestones!$K$2:$K$501,0))),"") | F38: =IFERROR(IF(INDEX(Milestones!$G$2:$G$501,MATCH(ROWS(B$29:B38),Milestones!$K$2:$K$501,0))="","",INDEX(Milestones!$G$2:$G$501,MATCH(ROWS(B$29:B38),Milestones!$K$2:$K$501,0))),"") | G38: =IFERROR(IF(INDEX(Milestones!$J$2:$J$501,MATCH(ROWS(B$29:B38),Milestones!$K$2:$K$501,0))="","",INDEX(Milestones!$J$2:$J$501,MATCH(ROWS(B$29:B38),Milestones!$K$2:$K$501,0))),"")
B39: =IFERROR(IF(INDEX(Milestones!$C$2:$C$501,MATCH(ROWS(B$29:B39),Milestones!$K$2:$K$501,0))="","",INDEX(Milestones!$C$2:$C$501,MATCH(ROWS(B$29:B39),Milestones!$K$2:$K$501,0))),"") | C39: =IFERROR(IF(INDEX(Milestones!$B$2:$B$501,MATCH(ROWS(B$29:B39),Milestones!$K$2:$K$501,0))="","",INDEX(Milestones!$B$2:$B$501,MATCH(ROWS(B$29:B39),Milestones!$K$2:$K$501,0))),"") | D39: =IFERROR(IF(INDEX(Milestones!$D$2:$D$501,MATCH(ROWS(B$29:B39),Milestones!$K$2:$K$501,0))="","",INDEX(Milestones!$D$2:$D$501,MATCH(ROWS(B$29:B39),Milestones!$K$2:$K$501,0))),"") | E39: =IFERROR(IF(INDEX(Milestones!$F$2:$F$501,MATCH(ROWS(B$29:B39),Milestones!$K$2:$K$501,0))="","",INDEX(Milestones!$F$2:$F$501,MATCH(ROWS(B$29:B39),Milestones!$K$2:$K$501,0))),"") | F39: =IFERROR(IF(INDEX(Milestones!$G$2:$G$501,MATCH(ROWS(B$29:B39),Milestones!$K$2:$K$501,0))="","",INDEX(Milestones!$G$2:$G$501,MATCH(ROWS(B$29:B39),Milestones!$K$2:$K$501,0))),"") | G39: =IFERROR(IF(INDEX(Milestones!$J$2:$J$501,MATCH(ROWS(B$29:B39),Milestones!$K$2:$K$501,0))="","",INDEX(Milestones!$J$2:$J$501,MATCH(ROWS(B$29:B39),Milestones!$K$2:$K$501,0))),"")
B40: =IFERROR(IF(INDEX(Milestones!$C$2:$C$501,MATCH(ROWS(B$29:B40),Milestones!$K$2:$K$501,0))="","",INDEX(Milestones!$C$2:$C$501,MATCH(ROWS(B$29:B40),Milestones!$K$2:$K$501,0))),"") | C40: =IFERROR(IF(INDEX(Milestones!$B$2:$B$501,MATCH(ROWS(B$29:B40),Milestones!$K$2:$K$501,0))="","",INDEX(Milestones!$B$2:$B$501,MATCH(ROWS(B$29:B40),Milestones!$K$2:$K$501,0))),"") | D40: =IFERROR(IF(INDEX(Milestones!$D$2:$D$501,MATCH(ROWS(B$29:B40),Milestones!$K$2:$K$501,0))="","",INDEX(Milestones!$D$2:$D$501,MATCH(ROWS(B$29:B40),Milestones!$K$2:$K$501,0))),"") | E40: =IFERROR(IF(INDEX(Milestones!$F$2:$F$501,MATCH(ROWS(B$29:B40),Milestones!$K$2:$K$501,0))="","",INDEX(Milestones!$F$2:$F$501,MATCH(ROWS(B$29:B40),Milestones!$K$2:$K$501,0))),"") | F40: =IFERROR(IF(INDEX(Milestones!$G$2:$G$501,MATCH(ROWS(B$29:B40),Milestones!$K$2:$K$501,0))="","",INDEX(Milestones!$G$2:$G$501,MATCH(ROWS(B$29:B40),Milestones!$K$2:$K$501,0))),"") | G40: =IFERROR(IF(INDEX(Milestones!$J$2:$J$501,MATCH(ROWS(B$29:B40),Milestones!$K$2:$K$501,0))="","",INDEX(Milestones!$J$2:$J$501,MATCH(ROWS(B$29:B40),Milestones!$K$2:$K$501,0))),"")
B43: Top open risks
B44: Risk | C44: Band | D44: Owner | E44: Status | F44: Mitigation | G44: Due
B45: =IFERROR(IF(INDEX(Risks!$C$2:$C$501,MATCH(LARGE(Risks!$T$2:$T$501,ROWS(B$45:B45)),Risks!$T$2:$T$501,0))="","",INDEX(Risks!$C$2:$C$501,MATCH(LARGE(Risks!$T$2:$T$501,ROWS(B$45:B45)),Risks!$T$2:$T$501,0))),"") | C45: =IFERROR(IF(INDEX(Risks!$O$2:$O$501,MATCH(LARGE(Risks!$T$2:$T$501,ROWS(B$45:B45)),Risks!$T$2:$T$501,0))="","",INDEX(Risks!$O$2:$O$501,MATCH(LARGE(Risks!$T$2:$T$501,ROWS(B$45:B45)),Risks!$T$2:$T$501,0))),"") | D45: =IFERROR(IF(INDEX(Risks!$K$2:$K$501,MATCH(LARGE(Risks!$T$2:$T$501,ROWS(B$45:B45)),Risks!$T$2:$T$501,0))="","",INDEX(Risks!$K$2:$K$501,MATCH(LARGE(Risks!$T$2:$T$501,ROWS(B$45:B45)),Risks!$T$2:$T$501,0))),"") | E45: =IFERROR(IF(INDEX(Risks!$M$2:$M$501,MATCH(LARGE(Risks!$T$2:$T$501,ROWS(B$45:B45)),Risks!$T$2:$T$501,0))="","",INDEX(Risks!$M$2:$M$501,MATCH(LARGE(Risks!$T$2:$T$501,ROWS(B$45:B45)),Risks!$T$2:$T$501,0))),"") | F45: =IFERROR(IF(INDEX(Risks!$J$2:$J$501,MATCH(LARGE(Risks!$T$2:$T$501,ROWS(B$45:B45)),Risks!$T$2:$T$501,0))="","",INDEX(Risks!$J$2:$J$501,MATCH(LARGE(Risks!$T$2:$T$501,ROWS(B$45:B45)),Risks!$T$2:$T$501,0))),"") | G45: =IFERROR(IF(INDEX(Risks!$L$2:$L$501,MATCH(LARGE(Risks!$T$2:$T$501,ROWS(B$45:B45)),Risks!$T$2:$T$501,0))="","",INDEX(Risks!$L$2:$L$501,MATCH(LARGE(Risks!$T$2:$T$501,ROWS(B$45:B45)),Risks!$T$2:$T$501,0))),"")
B46: =IFERROR(IF(INDEX(Risks!$C$2:$C$501,MATCH(LARGE(Risks!$T$2:$T$501,ROWS(B$45:B46)),Risks!$T$2:$T$501,0))="","",INDEX(Risks!$C$2:$C$501,MATCH(LARGE(Risks!$T$2:$T$501,ROWS(B$45:B46)),Risks!$T$2:$T$501,0))),"") | C46: =IFERROR(IF(INDEX(Risks!$O$2:$O$501,MATCH(LARGE(Risks!$T$2:$T$501,ROWS(B$45:B46)),Risks!$T$2:$T$501,0))="","",INDEX(Risks!$O$2:$O$501,MATCH(LARGE(Risks!$T$2:$T$501,ROWS(B$45:B46)),Risks!$T$2:$T$501,0))),"") | D46: =IFERROR(IF(INDEX(Risks!$K$2:$K$501,MATCH(LARGE(Risks!$T$2:$T$501,ROWS(B$45:B46)),Risks!$T$2:$T$501,0))="","",INDEX(Risks!$K$2:$K$501,MATCH(LARGE(Risks!$T$2:$T$501,ROWS(B$45:B46)),Risks!$T$2:$T$501,0))),"") | E46: =IFERROR(IF(INDEX(Risks!$M$2:$M$501,MATCH(LARGE(Risks!$T$2:$T$501,ROWS(B$45:B46)),Risks!$T$2:$T$501,0))="","",INDEX(Risks!$M$2:$M$501,MATCH(LARGE(Risks!$T$2:$T$501,ROWS(B$45:B46)),Risks!$T$2:$T$501,0))),"") | F46: =IFERROR(IF(INDEX(Risks!$J$2:$J$501,MATCH(LARGE(Risks!$T$2:$T$501,ROWS(B$45:B46)),Risks!$T$2:$T$501,0))="","",INDEX(Risks!$J$2:$J$501,MATCH(LARGE(Risks!$T$2:$T$501,ROWS(B$45:B46)),Risks!$T$2:$T$501,0))),"") | G46: =IFERROR(IF(INDEX(Risks!$L$2:$L$501,MATCH(LARGE(Risks!$T$2:$T$501,ROWS(B$45:B46)),Risks!$T$2:$T$501,0))="","",INDEX(Risks!$L$2:$L$501,MATCH(LARGE(Risks!$T$2:$T$501,ROWS(B$45:B46)),Risks!$T$2:$T$501,0))),"")
B47: =IFERROR(IF(INDEX(Risks!$C$2:$C$501,MATCH(LARGE(Risks!$T$2:$T$501,ROWS(B$45:B47)),Risks!$T$2:$T$501,0))="","",INDEX(Risks!$C$2:$C$501,MATCH(LARGE(Risks!$T$2:$T$501,ROWS(B$45:B47)),Risks!$T$2:$T$501,0))),"") | C47: =IFERROR(IF(INDEX(Risks!$O$2:$O$501,MATCH(LARGE(Risks!$T$2:$T$501,ROWS(B$45:B47)),Risks!$T$2:$T$501,0))="","",INDEX(Risks!$O$2:$O$501,MATCH(LARGE(Risks!$T$2:$T$501,ROWS(B$45:B47)),Risks!$T$2:$T$501,0))),"") | D47: =IFERROR(IF(INDEX(Risks!$K$2:$K$501,MATCH(LARGE(Risks!$T$2:$T$501,ROWS(B$45:B47)),Risks!$T$2:$T$501,0))="","",INDEX(Risks!$K$2:$K$501,MATCH(LARGE(Risks!$T$2:$T$501,ROWS(B$45:B47)),Risks!$T$2:$T$501,0))),"") | E47: =IFERROR(IF(INDEX(Risks!$M$2:$M$501,MATCH(LARGE(Risks!$T$2:$T$501,ROWS(B$45:B47)),Risks!$T$2:$T$501,0))="","",INDEX(Risks!$M$2:$M$501,MATCH(LARGE(Risks!$T$2:$T$501,ROWS(B$45:B47)),Risks!$T$2:$T$501,0))),"") | F47: =IFERROR(IF(INDEX(Risks!$J$2:$J$501,MATCH(LARGE(Risks!$T$2:$T$501,ROWS(B$45:B47)),Risks!$T$2:$T$501,0))="","",INDEX(Risks!$J$2:$J$501,MATCH(LARGE(Risks!$T$2:$T$501,ROWS(B$45:B47)),Risks!$T$2:$T$501,0))),"") | G47: =IFERROR(IF(INDEX(Risks!$L$2:$L$501,MATCH(LARGE(Risks!$T$2:$T$501,ROWS(B$45:B47)),Risks!$T$2:$T$501,0))="","",INDEX(Risks!$L$2:$L$501,MATCH(LARGE(Risks!$T$2:$T$501,ROWS(B$45:B47)),Risks!$T$2:$T$501,0))),"")
B48: =IFERROR(IF(INDEX(Risks!$C$2:$C$501,MATCH(LARGE(Risks!$T$2:$T$501,ROWS(B$45:B48)),Risks!$T$2:$T$501,0))="","",INDEX(Risks!$C$2:$C$501,MATCH(LARGE(Risks!$T$2:$T$501,ROWS(B$45:B48)),Risks!$T$2:$T$501,0))),"") | C48: =IFERROR(IF(INDEX(Risks!$O$2:$O$501,MATCH(LARGE(Risks!$T$2:$T$501,ROWS(B$45:B48)),Risks!$T$2:$T$501,0))="","",INDEX(Risks!$O$2:$O$501,MATCH(LARGE(Risks!$T$2:$T$501,ROWS(B$45:B48)),Risks!$T$2:$T$501,0))),"") | D48: =IFERROR(IF(INDEX(Risks!$K$2:$K$501,MATCH(LARGE(Risks!$T$2:$T$501,ROWS(B$45:B48)),Risks!$T$2:$T$501,0))="","",INDEX(Risks!$K$2:$K$501,MATCH(LARGE(Risks!$T$2:$T$501,ROWS(B$45:B48)),Risks!$T$2:$T$501,0))),"") | E48: =IFERROR(IF(INDEX(Risks!$M$2:$M$501,MATCH(LARGE(Risks!$T$2:$T$501,ROWS(B$45:B48)),Risks!$T$2:$T$501,0))="","",INDEX(Risks!$M$2:$M$501,MATCH(LARGE(Risks!$T$2:$T$501,ROWS(B$45:B48)),Risks!$T$2:$T$501,0))),"") | F48: =IFERROR(IF(INDEX(Risks!$J$2:$J$501,MATCH(LARGE(Risks!$T$2:$T$501,ROWS(B$45:B48)),Risks!$T$2:$T$501,0))="","",INDEX(Risks!$J$2:$J$501,MATCH(LARGE(Risks!$T$2:$T$501,ROWS(B$45:B48)),Risks!$T$2:$T$501,0))),"") | G48: =IFERROR(IF(INDEX(Risks!$L$2:$L$501,MATCH(LARGE(Risks!$T$2:$T$501,ROWS(B$45:B48)),Risks!$T$2:$T$501,0))="","",INDEX(Risks!$L$2:$L$501,MATCH(LARGE(Risks!$T$2:$T$501,ROWS(B$45:B48)),Risks!$T$2:$T$501,0))),"")
B49: =IFERROR(IF(INDEX(Risks!$C$2:$C$501,MATCH(LARGE(Risks!$T$2:$T$501,ROWS(B$45:B49)),Risks!$T$2:$T$501,0))="","",INDEX(Risks!$C$2:$C$501,MATCH(LARGE(Risks!$T$2:$T$501,ROWS(B$45:B49)),Risks!$T$2:$T$501,0))),"") | C49: =IFERROR(IF(INDEX(Risks!$O$2:$O$501,MATCH(LARGE(Risks!$T$2:$T$501,ROWS(B$45:B49)),Risks!$T$2:$T$501,0))="","",INDEX(Risks!$O$2:$O$501,MATCH(LARGE(Risks!$T$2:$T$501,ROWS(B$45:B49)),Risks!$T$2:$T$501,0))),"") | D49: =IFERROR(IF(INDEX(Risks!$K$2:$K$501,MATCH(LARGE(Risks!$T$2:$T$501,ROWS(B$45:B49)),Risks!$T$2:$T$501,0))="","",INDEX(Risks!$K$2:$K$501,MATCH(LARGE(Risks!$T$2:$T$501,ROWS(B$45:B49)),Risks!$T$2:$T$501,0))),"") | E49: =IFERROR(IF(INDEX(Risks!$M$2:$M$501,MATCH(LARGE(Risks!$T$2:$T$501,ROWS(B$45:B49)),Risks!$T$2:$T$501,0))="","",INDEX(Risks!$M$2:$M$501,MATCH(LARGE(Risks!$T$2:$T$501,ROWS(B$45:B49)),Risks!$T$2:$T$501,0))),"") | F49: =IFERROR(IF(INDEX(Risks!$J$2:$J$501,MATCH(LARGE(Risks!$T$2:$T$501,ROWS(B$45:B49)),Risks!$T$2:$T$501,0))="","",INDEX(Risks!$J$2:$J$501,MATCH(LARGE(Risks!$T$2:$T$501,ROWS(B$45:B49)),Risks!$T$2:$T$501,0))),"") | G49: =IFERROR(IF(INDEX(Risks!$L$2:$L$501,MATCH(LARGE(Risks!$T$2:$T$501,ROWS(B$45:B49)),Risks!$T$2:$T$501,0))="","",INDEX(Risks!$L$2:$L$501,MATCH(LARGE(Risks!$T$2:$T$501,ROWS(B$45:B49)),Risks!$T$2:$T$501,0))),"")
B50: =IFERROR(IF(INDEX(Risks!$C$2:$C$501,MATCH(LARGE(Risks!$T$2:$T$501,ROWS(B$45:B50)),Risks!$T$2:$T$501,0))="","",INDEX(Risks!$C$2:$C$501,MATCH(LARGE(Risks!$T$2:$T$501,ROWS(B$45:B50)),Risks!$T$2:$T$501,0))),"") | C50: =IFERROR(IF(INDEX(Risks!$O$2:$O$501,MATCH(LARGE(Risks!$T$2:$T$501,ROWS(B$45:B50)),Risks!$T$2:$T$501,0))="","",INDEX(Risks!$O$2:$O$501,MATCH(LARGE(Risks!$T$2:$T$501,ROWS(B$45:B50)),Risks!$T$2:$T$501,0))),"") | D50: =IFERROR(IF(INDEX(Risks!$K$2:$K$501,MATCH(LARGE(Risks!$T$2:$T$501,ROWS(B$45:B50)),Risks!$T$2:$T$501,0))="","",INDEX(Risks!$K$2:$K$501,MATCH(LARGE(Risks!$T$2:$T$501,ROWS(B$45:B50)),Risks!$T$2:$T$501,0))),"") | E50: =IFERROR(IF(INDEX(Risks!$M$2:$M$501,MATCH(LARGE(Risks!$T$2:$T$501,ROWS(B$45:B50)),Risks!$T$2:$T$501,0))="","",INDEX(Risks!$M$2:$M$501,MATCH(LARGE(Risks!$T$2:$T$501,ROWS(B$45:B50)),Risks!$T$2:$T$501,0))),"") | F50: =IFERROR(IF(INDEX(Risks!$J$2:$J$501,MATCH(LARGE(Risks!$T$2:$T$501,ROWS(B$45:B50)),Risks!$T$2:$T$501,0))="","",INDEX(Risks!$J$2:$J$501,MATCH(LARGE(Risks!$T$2:$T$501,ROWS(B$45:B50)),Risks!$T$2:$T$501,0))),"") | G50: =IFERROR(IF(INDEX(Risks!$L$2:$L$501,MATCH(LARGE(Risks!$T$2:$T$501,ROWS(B$45:B50)),Risks!$T$2:$T$501,0))="","",INDEX(Risks!$L$2:$L$501,MATCH(LARGE(Risks!$T$2:$T$501,ROWS(B$45:B50)),Risks!$T$2:$T$501,0))),"")
B51: =IFERROR(IF(INDEX(Risks!$C$2:$C$501,MATCH(LARGE(Risks!$T$2:$T$501,ROWS(B$45:B51)),Risks!$T$2:$T$501,0))="","",INDEX(Risks!$C$2:$C$501,MATCH(LARGE(Risks!$T$2:$T$501,ROWS(B$45:B51)),Risks!$T$2:$T$501,0))),"") | C51: =IFERROR(IF(INDEX(Risks!$O$2:$O$501,MATCH(LARGE(Risks!$T$2:$T$501,ROWS(B$45:B51)),Risks!$T$2:$T$501,0))="","",INDEX(Risks!$O$2:$O$501,MATCH(LARGE(Risks!$T$2:$T$501,ROWS(B$45:B51)),Risks!$T$2:$T$501,0))),"") | D51: =IFERROR(IF(INDEX(Risks!$K$2:$K$501,MATCH(LARGE(Risks!$T$2:$T$501,ROWS(B$45:B51)),Risks!$T$2:$T$501,0))="","",INDEX(Risks!$K$2:$K$501,MATCH(LARGE(Risks!$T$2:$T$501,ROWS(B$45:B51)),Risks!$T$2:$T$501,0))),"") | E51: =IFERROR(IF(INDEX(Risks!$M$2:$M$501,MATCH(LARGE(Risks!$T$2:$T$501,ROWS(B$45:B51)),Risks!$T$2:$T$501,0))="","",INDEX(Risks!$M$2:$M$501,MATCH(LARGE(Risks!$T$2:$T$501,ROWS(B$45:B51)),Risks!$T$2:$T$501,0))),"") | F51: =IFERROR(IF(INDEX(Risks!$J$2:$J$501,MATCH(LARGE(Risks!$T$2:$T$501,ROWS(B$45:B51)),Risks!$T$2:$T$501,0))="","",INDEX(Risks!$J$2:$J$501,MATCH(LARGE(Risks!$T$2:$T$501,ROWS(B$45:B51)),Risks!$T$2:$T$501,0))),"") | G51: =IFERROR(IF(INDEX(Risks!$L$2:$L$501,MATCH(LARGE(Risks!$T$2:$T$501,ROWS(B$45:B51)),Risks!$T$2:$T$501,0))="","",INDEX(Risks!$L$2:$L$501,MATCH(LARGE(Risks!$T$2:$T$501,ROWS(B$45:B51)),Risks!$T$2:$T$501,0))),"")
B52: =IFERROR(IF(INDEX(Risks!$C$2:$C$501,MATCH(LARGE(Risks!$T$2:$T$501,ROWS(B$45:B52)),Risks!$T$2:$T$501,0))="","",INDEX(Risks!$C$2:$C$501,MATCH(LARGE(Risks!$T$2:$T$501,ROWS(B$45:B52)),Risks!$T$2:$T$501,0))),"") | C52: =IFERROR(IF(INDEX(Risks!$O$2:$O$501,MATCH(LARGE(Risks!$T$2:$T$501,ROWS(B$45:B52)),Risks!$T$2:$T$501,0))="","",INDEX(Risks!$O$2:$O$501,MATCH(LARGE(Risks!$T$2:$T$501,ROWS(B$45:B52)),Risks!$T$2:$T$501,0))),"") | D52: =IFERROR(IF(INDEX(Risks!$K$2:$K$501,MATCH(LARGE(Risks!$T$2:$T$501,ROWS(B$45:B52)),Risks!$T$2:$T$501,0))="","",INDEX(Risks!$K$2:$K$501,MATCH(LARGE(Risks!$T$2:$T$501,ROWS(B$45:B52)),Risks!$T$2:$T$501,0))),"") | E52: =IFERROR(IF(INDEX(Risks!$M$2:$M$501,MATCH(LARGE(Risks!$T$2:$T$501,ROWS(B$45:B52)),Risks!$T$2:$T$501,0))="","",INDEX(Risks!$M$2:$M$501,MATCH(LARGE(Risks!$T$2:$T$501,ROWS(B$45:B52)),Risks!$T$2:$T$501,0))),"") | F52: =IFERROR(IF(INDEX(Risks!$J$2:$J$501,MATCH(LARGE(Risks!$T$2:$T$501,ROWS(B$45:B52)),Risks!$T$2:$T$501,0))="","",INDEX(Risks!$J$2:$J$501,MATCH(LARGE(Risks!$T$2:$T$501,ROWS(B$45:B52)),Risks!$T$2:$T$501,0))),"") | G52: =IFERROR(IF(INDEX(Risks!$L$2:$L$501,MATCH(LARGE(Risks!$T$2:$T$501,ROWS(B$45:B52)),Risks!$T$2:$T$501,0))="","",INDEX(Risks!$L$2:$L$501,MATCH(LARGE(Risks!$T$2:$T$501,ROWS(B$45:B52)),Risks!$T$2:$T$501,0))),"")
B55: Variations
B56: Title | C56: Reference | D56: Cost Impact | E56: Time (days) | F56: Status | G56: Date Raised
B57: =IFERROR(IF(INDEX(Variations!$C$2:$C$501,MATCH(ROWS(B$57:B57),Variations!$L$2:$L$501,0))="","",INDEX(Variations!$C$2:$C$501,MATCH(ROWS(B$57:B57),Variations!$L$2:$L$501,0))),"") | C57: =IFERROR(IF(INDEX(Variations!$B$2:$B$501,MATCH(ROWS(B$57:B57),Variations!$L$2:$L$501,0))="","",INDEX(Variations!$B$2:$B$501,MATCH(ROWS(B$57:B57),Variations!$L$2:$L$501,0))),"") | D57: =IFERROR(IF(INDEX(Variations!$F$2:$F$501,MATCH(ROWS(B$57:B57),Variations!$L$2:$L$501,0))="","",INDEX(Variations!$F$2:$F$501,MATCH(ROWS(B$57:B57),Variations!$L$2:$L$501,0))),"") | E57: =IFERROR(IF(INDEX(Variations!$G$2:$G$501,MATCH(ROWS(B$57:B57),Variations!$L$2:$L$501,0))="","",INDEX(Variations!$G$2:$G$501,MATCH(ROWS(B$57:B57),Variations!$L$2:$L$501,0))),"") | F57: =IFERROR(IF(INDEX(Variations!$H$2:$H$501,MATCH(ROWS(B$57:B57),Variations!$L$2:$L$501,0))="","",INDEX(Variations!$H$2:$H$501,MATCH(ROWS(B$57:B57),Variations!$L$2:$L$501,0))),"") | G57: =IFERROR(IF(INDEX(Variations!$I$2:$I$501,MATCH(ROWS(B$57:B57),Variations!$L$2:$L$501,0))="","",INDEX(Variations!$I$2:$I$501,MATCH(ROWS(B$57:B57),Variations!$L$2:$L$501,0))),"")
B58: =IFERROR(IF(INDEX(Variations!$C$2:$C$501,MATCH(ROWS(B$57:B58),Variations!$L$2:$L$501,0))="","",INDEX(Variations!$C$2:$C$501,MATCH(ROWS(B$57:B58),Variations!$L$2:$L$501,0))),"") | C58: =IFERROR(IF(INDEX(Variations!$B$2:$B$501,MATCH(ROWS(B$57:B58),Variations!$L$2:$L$501,0))="","",INDEX(Variations!$B$2:$B$501,MATCH(ROWS(B$57:B58),Variations!$L$2:$L$501,0))),"") | D58: =IFERROR(IF(INDEX(Variations!$F$2:$F$501,MATCH(ROWS(B$57:B58),Variations!$L$2:$L$501,0))="","",INDEX(Variations!$F$2:$F$501,MATCH(ROWS(B$57:B58),Variations!$L$2:$L$501,0))),"") | E58: =IFERROR(IF(INDEX(Variations!$G$2:$G$501,MATCH(ROWS(B$57:B58),Variations!$L$2:$L$501,0))="","",INDEX(Variations!$G$2:$G$501,MATCH(ROWS(B$57:B58),Variations!$L$2:$L$501,0))),"") | F58: =IFERROR(IF(INDEX(Variations!$H$2:$H$501,MATCH(ROWS(B$57:B58),Variations!$L$2:$L$501,0))="","",INDEX(Variations!$H$2:$H$501,MATCH(ROWS(B$57:B58),Variations!$L$2:$L$501,0))),"") | G58: =IFERROR(IF(INDEX(Variations!$I$2:$I$501,MATCH(ROWS(B$57:B58),Variations!$L$2:$L$501,0))="","",INDEX(Variations!$I$2:$I$501,MATCH(ROWS(B$57:B58),Variations!$L$2:$L$501,0))),"")
B59: =IFERROR(IF(INDEX(Variations!$C$2:$C$501,MATCH(ROWS(B$57:B59),Variations!$L$2:$L$501,0))="","",INDEX(Variations!$C$2:$C$501,MATCH(ROWS(B$57:B59),Variations!$L$2:$L$501,0))),"") | C59: =IFERROR(IF(INDEX(Variations!$B$2:$B$501,MATCH(ROWS(B$57:B59),Variations!$L$2:$L$501,0))="","",INDEX(Variations!$B$2:$B$501,MATCH(ROWS(B$57:B59),Variations!$L$2:$L$501,0))),"") | D59: =IFERROR(IF(INDEX(Variations!$F$2:$F$501,MATCH(ROWS(B$57:B59),Variations!$L$2:$L$501,0))="","",INDEX(Variations!$F$2:$F$501,MATCH(ROWS(B$57:B59),Variations!$L$2:$L$501,0))),"") | E59: =IFERROR(IF(INDEX(Variations!$G$2:$G$501,MATCH(ROWS(B$57:B59),Variations!$L$2:$L$501,0))="","",INDEX(Variations!$G$2:$G$501,MATCH(ROWS(B$57:B59),Variations!$L$2:$L$501,0))),"") | F59: =IFERROR(IF(INDEX(Variations!$H$2:$H$501,MATCH(ROWS(B$57:B59),Variations!$L$2:$L$501,0))="","",INDEX(Variations!$H$2:$H$501,MATCH(ROWS(B$57:B59),Variations!$L$2:$L$501,0))),"") | G59: =IFERROR(IF(INDEX(Variations!$I$2:$I$501,MATCH(ROWS(B$57:B59),Variations!$L$2:$L$501,0))="","",INDEX(Variations!$I$2:$I$501,MATCH(ROWS(B$57:B59),Variations!$L$2:$L$501,0))),"")
B60: =IFERROR(IF(INDEX(Variations!$C$2:$C$501,MATCH(ROWS(B$57:B60),Variations!$L$2:$L$501,0))="","",INDEX(Variations!$C$2:$C$501,MATCH(ROWS(B$57:B60),Variations!$L$2:$L$501,0))),"") | C60: =IFERROR(IF(INDEX(Variations!$B$2:$B$501,MATCH(ROWS(B$57:B60),Variations!$L$2:$L$501,0))="","",INDEX(Variations!$B$2:$B$501,MATCH(ROWS(B$57:B60),Variations!$L$2:$L$501,0))),"") | D60: =IFERROR(IF(INDEX(Variations!$F$2:$F$501,MATCH(ROWS(B$57:B60),Variations!$L$2:$L$501,0))="","",INDEX(Variations!$F$2:$F$501,MATCH(ROWS(B$57:B60),Variations!$L$2:$L$501,0))),"") | E60: =IFERROR(IF(INDEX(Variations!$G$2:$G$501,MATCH(ROWS(B$57:B60),Variations!$L$2:$L$501,0))="","",INDEX(Variations!$G$2:$G$501,MATCH(ROWS(B$57:B60),Variations!$L$2:$L$501,0))),"") | F60: =IFERROR(IF(INDEX(Variations!$H$2:$H$501,MATCH(ROWS(B$57:B60),Variations!$L$2:$L$501,0))="","",INDEX(Variations!$H$2:$H$501,MATCH(ROWS(B$57:B60),Variations!$L$2:$L$501,0))),"") | G60: =IFERROR(IF(INDEX(Variations!$I$2:$I$501,MATCH(ROWS(B$57:B60),Variations!$L$2:$L$501,0))="","",INDEX(Variations!$I$2:$I$501,MATCH(ROWS(B$57:B60),Variations!$L$2:$L$501,0))),"")
B61: =IFERROR(IF(INDEX(Variations!$C$2:$C$501,MATCH(ROWS(B$57:B61),Variations!$L$2:$L$501,0))="","",INDEX(Variations!$C$2:$C$501,MATCH(ROWS(B$57:B61),Variations!$L$2:$L$501,0))),"") | C61: =IFERROR(IF(INDEX(Variations!$B$2:$B$501,MATCH(ROWS(B$57:B61),Variations!$L$2:$L$501,0))="","",INDEX(Variations!$B$2:$B$501,MATCH(ROWS(B$57:B61),Variations!$L$2:$L$501,0))),"") | D61: =IFERROR(IF(INDEX(Variations!$F$2:$F$501,MATCH(ROWS(B$57:B61),Variations!$L$2:$L$501,0))="","",INDEX(Variations!$F$2:$F$501,MATCH(ROWS(B$57:B61),Variations!$L$2:$L$501,0))),"") | E61: =IFERROR(IF(INDEX(Variations!$G$2:$G$501,MATCH(ROWS(B$57:B61),Variations!$L$2:$L$501,0))="","",INDEX(Variations!$G$2:$G$501,MATCH(ROWS(B$57:B61),Variations!$L$2:$L$501,0))),"") | F61: =IFERROR(IF(INDEX(Variations!$H$2:$H$501,MATCH(ROWS(B$57:B61),Variations!$L$2:$L$501,0))="","",INDEX(Variations!$H$2:$H$501,MATCH(ROWS(B$57:B61),Variations!$L$2:$L$501,0))),"") | G61: =IFERROR(IF(INDEX(Variations!$I$2:$I$501,MATCH(ROWS(B$57:B61),Variations!$L$2:$L$501,0))="","",INDEX(Variations!$I$2:$I$501,MATCH(ROWS(B$57:B61),Variations!$L$2:$L$501,0))),"")
B62: =IFERROR(IF(INDEX(Variations!$C$2:$C$501,MATCH(ROWS(B$57:B62),Variations!$L$2:$L$501,0))="","",INDEX(Variations!$C$2:$C$501,MATCH(ROWS(B$57:B62),Variations!$L$2:$L$501,0))),"") | C62: =IFERROR(IF(INDEX(Variations!$B$2:$B$501,MATCH(ROWS(B$57:B62),Variations!$L$2:$L$501,0))="","",INDEX(Variations!$B$2:$B$501,MATCH(ROWS(B$57:B62),Variations!$L$2:$L$501,0))),"") | D62: =IFERROR(IF(INDEX(Variations!$F$2:$F$501,MATCH(ROWS(B$57:B62),Variations!$L$2:$L$501,0))="","",INDEX(Variations!$F$2:$F$501,MATCH(ROWS(B$57:B62),Variations!$L$2:$L$501,0))),"") | E62: =IFERROR(IF(INDEX(Variations!$G$2:$G$501,MATCH(ROWS(B$57:B62),Variations!$L$2:$L$501,0))="","",INDEX(Variations!$G$2:$G$501,MATCH(ROWS(B$57:B62),Variations!$L$2:$L$501,0))),"") | F62: =IFERROR(IF(INDEX(Variations!$H$2:$H$501,MATCH(ROWS(B$57:B62),Variations!$L$2:$L$501,0))="","",INDEX(Variations!$H$2:$H$501,MATCH(ROWS(B$57:B62),Variations!$L$2:$L$501,0))),"") | G62: =IFERROR(IF(INDEX(Variations!$I$2:$I$501,MATCH(ROWS(B$57:B62),Variations!$L$2:$L$501,0))="","",INDEX(Variations!$I$2:$I$501,MATCH(ROWS(B$57:B62),Variations!$L$2:$L$501,0))),"")
B63: =IFERROR(IF(INDEX(Variations!$C$2:$C$501,MATCH(ROWS(B$57:B63),Variations!$L$2:$L$501,0))="","",INDEX(Variations!$C$2:$C$501,MATCH(ROWS(B$57:B63),Variations!$L$2:$L$501,0))),"") | C63: =IFERROR(IF(INDEX(Variations!$B$2:$B$501,MATCH(ROWS(B$57:B63),Variations!$L$2:$L$501,0))="","",INDEX(Variations!$B$2:$B$501,MATCH(ROWS(B$57:B63),Variations!$L$2:$L$501,0))),"") | D63: =IFERROR(IF(INDEX(Variations!$F$2:$F$501,MATCH(ROWS(B$57:B63),Variations!$L$2:$L$501,0))="","",INDEX(Variations!$F$2:$F$501,MATCH(ROWS(B$57:B63),Variations!$L$2:$L$501,0))),"") | E63: =IFERROR(IF(INDEX(Variations!$G$2:$G$501,MATCH(ROWS(B$57:B63),Variations!$L$2:$L$501,0))="","",INDEX(Variations!$G$2:$G$501,MATCH(ROWS(B$57:B63),Variations!$L$2:$L$501,0))),"") | F63: =IFERROR(IF(INDEX(Variations!$H$2:$H$501,MATCH(ROWS(B$57:B63),Variations!$L$2:$L$501,0))="","",INDEX(Variations!$H$2:$H$501,MATCH(ROWS(B$57:B63),Variations!$L$2:$L$501,0))),"") | G63: =IFERROR(IF(INDEX(Variations!$I$2:$I$501,MATCH(ROWS(B$57:B63),Variations!$L$2:$L$501,0))="","",INDEX(Variations!$I$2:$I$501,MATCH(ROWS(B$57:B63),Variations!$L$2:$L$501,0))),"")
B64: =IFERROR(IF(INDEX(Variations!$C$2:$C$501,MATCH(ROWS(B$57:B64),Variations!$L$2:$L$501,0))="","",INDEX(Variations!$C$2:$C$501,MATCH(ROWS(B$57:B64),Variations!$L$2:$L$501,0))),"") | C64: =IFERROR(IF(INDEX(Variations!$B$2:$B$501,MATCH(ROWS(B$57:B64),Variations!$L$2:$L$501,0))="","",INDEX(Variations!$B$2:$B$501,MATCH(ROWS(B$57:B64),Variations!$L$2:$L$501,0))),"") | D64: =IFERROR(IF(INDEX(Variations!$F$2:$F$501,MATCH(ROWS(B$57:B64),Variations!$L$2:$L$501,0))="","",INDEX(Variations!$F$2:$F$501,MATCH(ROWS(B$57:B64),Variations!$L$2:$L$501,0))),"") | E64: =IFERROR(IF(INDEX(Variations!$G$2:$G$501,MATCH(ROWS(B$57:B64),Variations!$L$2:$L$501,0))="","",INDEX(Variations!$G$2:$G$501,MATCH(ROWS(B$57:B64),Variations!$L$2:$L$501,0))),"") | F64: =IFERROR(IF(INDEX(Variations!$H$2:$H$501,MATCH(ROWS(B$57:B64),Variations!$L$2:$L$501,0))="","",INDEX(Variations!$H$2:$H$501,MATCH(ROWS(B$57:B64),Variations!$L$2:$L$501,0))),"") | G64: =IFERROR(IF(INDEX(Variations!$I$2:$I$501,MATCH(ROWS(B$57:B64),Variations!$L$2:$L$501,0))="","",INDEX(Variations!$I$2:$I$501,MATCH(ROWS(B$57:B64),Variations!$L$2:$L$501,0))),"")
B67: Open actions & decisions
B68: Title | C68: Type | D68: Owner | E68: Due | F68: Status | G68: Bucket
B69: =IFERROR(IF(INDEX(Actions!$C$2:$C$501,MATCH(ROWS(B$69:B69),Actions!$O$2:$O$501,0))="","",INDEX(Actions!$C$2:$C$501,MATCH(ROWS(B$69:B69),Actions!$O$2:$O$501,0))),"") | C69: =IFERROR(IF(INDEX(Actions!$B$2:$B$501,MATCH(ROWS(B$69:B69),Actions!$O$2:$O$501,0))="","",INDEX(Actions!$B$2:$B$501,MATCH(ROWS(B$69:B69),Actions!$O$2:$O$501,0))),"") | D69: =IFERROR(IF(INDEX(Actions!$F$2:$F$501,MATCH(ROWS(B$69:B69),Actions!$O$2:$O$501,0))="","",INDEX(Actions!$F$2:$F$501,MATCH(ROWS(B$69:B69),Actions!$O$2:$O$501,0))),"") | E69: =IFERROR(IF(INDEX(Actions!$G$2:$G$501,MATCH(ROWS(B$69:B69),Actions!$O$2:$O$501,0))="","",INDEX(Actions!$G$2:$G$501,MATCH(ROWS(B$69:B69),Actions!$O$2:$O$501,0))),"") | F69: =IFERROR(IF(INDEX(Actions!$H$2:$H$501,MATCH(ROWS(B$69:B69),Actions!$O$2:$O$501,0))="","",INDEX(Actions!$H$2:$H$501,MATCH(ROWS(B$69:B69),Actions!$O$2:$O$501,0))),"") | G69: =IFERROR(IF(INDEX(Actions!$M$2:$M$501,MATCH(ROWS(B$69:B69),Actions!$O$2:$O$501,0))="","",INDEX(Actions!$M$2:$M$501,MATCH(ROWS(B$69:B69),Actions!$O$2:$O$501,0))),"")
B70: =IFERROR(IF(INDEX(Actions!$C$2:$C$501,MATCH(ROWS(B$69:B70),Actions!$O$2:$O$501,0))="","",INDEX(Actions!$C$2:$C$501,MATCH(ROWS(B$69:B70),Actions!$O$2:$O$501,0))),"") | C70: =IFERROR(IF(INDEX(Actions!$B$2:$B$501,MATCH(ROWS(B$69:B70),Actions!$O$2:$O$501,0))="","",INDEX(Actions!$B$2:$B$501,MATCH(ROWS(B$69:B70),Actions!$O$2:$O$501,0))),"") | D70: =IFERROR(IF(INDEX(Actions!$F$2:$F$501,MATCH(ROWS(B$69:B70),Actions!$O$2:$O$501,0))="","",INDEX(Actions!$F$2:$F$501,MATCH(ROWS(B$69:B70),Actions!$O$2:$O$501,0))),"") | E70: =IFERROR(IF(INDEX(Actions!$G$2:$G$501,MATCH(ROWS(B$69:B70),Actions!$O$2:$O$501,0))="","",INDEX(Actions!$G$2:$G$501,MATCH(ROWS(B$69:B70),Actions!$O$2:$O$501,0))),"") | F70: =IFERROR(IF(INDEX(Actions!$H$2:$H$501,MATCH(ROWS(B$69:B70),Actions!$O$2:$O$501,0))="","",INDEX(Actions!$H$2:$H$501,MATCH(ROWS(B$69:B70),Actions!$O$2:$O$501,0))),"") | G70: =IFERROR(IF(INDEX(Actions!$M$2:$M$501,MATCH(ROWS(B$69:B70),Actions!$O$2:$O$501,0))="","",INDEX(Actions!$M$2:$M$501,MATCH(ROWS(B$69:B70),Actions!$O$2:$O$501,0))),"")
B71: =IFERROR(IF(INDEX(Actions!$C$2:$C$501,MATCH(ROWS(B$69:B71),Actions!$O$2:$O$501,0))="","",INDEX(Actions!$C$2:$C$501,MATCH(ROWS(B$69:B71),Actions!$O$2:$O$501,0))),"") | C71: =IFERROR(IF(INDEX(Actions!$B$2:$B$501,MATCH(ROWS(B$69:B71),Actions!$O$2:$O$501,0))="","",INDEX(Actions!$B$2:$B$501,MATCH(ROWS(B$69:B71),Actions!$O$2:$O$501,0))),"") | D71: =IFERROR(IF(INDEX(Actions!$F$2:$F$501,MATCH(ROWS(B$69:B71),Actions!$O$2:$O$501,0))="","",INDEX(Actions!$F$2:$F$501,MATCH(ROWS(B$69:B71),Actions!$O$2:$O$501,0))),"") | E71: =IFERROR(IF(INDEX(Actions!$G$2:$G$501,MATCH(ROWS(B$69:B71),Actions!$O$2:$O$501,0))="","",INDEX(Actions!$G$2:$G$501,MATCH(ROWS(B$69:B71),Actions!$O$2:$O$501,0))),"") | F71: =IFERROR(IF(INDEX(Actions!$H$2:$H$501,MATCH(ROWS(B$69:B71),Actions!$O$2:$O$501,0))="","",INDEX(Actions!$H$2:$H$501,MATCH(ROWS(B$69:B71),Actions!$O$2:$O$501,0))),"") | G71: =IFERROR(IF(INDEX(Actions!$M$2:$M$501,MATCH(ROWS(B$69:B71),Actions!$O$2:$O$501,0))="","",INDEX(Actions!$M$2:$M$501,MATCH(ROWS(B$69:B71),Actions!$O$2:$O$501,0))),"")
B72: =IFERROR(IF(INDEX(Actions!$C$2:$C$501,MATCH(ROWS(B$69:B72),Actions!$O$2:$O$501,0))="","",INDEX(Actions!$C$2:$C$501,MATCH(ROWS(B$69:B72),Actions!$O$2:$O$501,0))),"") | C72: =IFERROR(IF(INDEX(Actions!$B$2:$B$501,MATCH(ROWS(B$69:B72),Actions!$O$2:$O$501,0))="","",INDEX(Actions!$B$2:$B$501,MATCH(ROWS(B$69:B72),Actions!$O$2:$O$501,0))),"") | D72: =IFERROR(IF(INDEX(Actions!$F$2:$F$501,MATCH(ROWS(B$69:B72),Actions!$O$2:$O$501,0))="","",INDEX(Actions!$F$2:$F$501,MATCH(ROWS(B$69:B72),Actions!$O$2:$O$501,0))),"") | E72: =IFERROR(IF(INDEX(Actions!$G$2:$G$501,MATCH(ROWS(B$69:B72),Actions!$O$2:$O$501,0))="","",INDEX(Actions!$G$2:$G$501,MATCH(ROWS(B$69:B72),Actions!$O$2:$O$501,0))),"") | F72: =IFERROR(IF(INDEX(Actions!$H$2:$H$501,MATCH(ROWS(B$69:B72),Actions!$O$2:$O$501,0))="","",INDEX(Actions!$H$2:$H$501,MATCH(ROWS(B$69:B72),Actions!$O$2:$O$501,0))),"") | G72: =IFERROR(IF(INDEX(Actions!$M$2:$M$501,MATCH(ROWS(B$69:B72),Actions!$O$2:$O$501,0))="","",INDEX(Actions!$M$2:$M$501,MATCH(ROWS(B$69:B72),Actions!$O$2:$O$501,0))),"")
B73: =IFERROR(IF(INDEX(Actions!$C$2:$C$501,MATCH(ROWS(B$69:B73),Actions!$O$2:$O$501,0))="","",INDEX(Actions!$C$2:$C$501,MATCH(ROWS(B$69:B73),Actions!$O$2:$O$501,0))),"") | C73: =IFERROR(IF(INDEX(Actions!$B$2:$B$501,MATCH(ROWS(B$69:B73),Actions!$O$2:$O$501,0))="","",INDEX(Actions!$B$2:$B$501,MATCH(ROWS(B$69:B73),Actions!$O$2:$O$501,0))),"") | D73: =IFERROR(IF(INDEX(Actions!$F$2:$F$501,MATCH(ROWS(B$69:B73),Actions!$O$2:$O$501,0))="","",INDEX(Actions!$F$2:$F$501,MATCH(ROWS(B$69:B73),Actions!$O$2:$O$501,0))),"") | E73: =IFERROR(IF(INDEX(Actions!$G$2:$G$501,MATCH(ROWS(B$69:B73),Actions!$O$2:$O$501,0))="","",INDEX(Actions!$G$2:$G$501,MATCH(ROWS(B$69:B73),Actions!$O$2:$O$501,0))),"") | F73: =IFERROR(IF(INDEX(Actions!$H$2:$H$501,MATCH(ROWS(B$69:B73),Actions!$O$2:$O$501,0))="","",INDEX(Actions!$H$2:$H$501,MATCH(ROWS(B$69:B73),Actions!$O$2:$O$501,0))),"") | G73: =IFERROR(IF(INDEX(Actions!$M$2:$M$501,MATCH(ROWS(B$69:B73),Actions!$O$2:$O$501,0))="","",INDEX(Actions!$M$2:$M$501,MATCH(ROWS(B$69:B73),Actions!$O$2:$O$501,0))),"")
B74: =IFERROR(IF(INDEX(Actions!$C$2:$C$501,MATCH(ROWS(B$69:B74),Actions!$O$2:$O$501,0))="","",INDEX(Actions!$C$2:$C$501,MATCH(ROWS(B$69:B74),Actions!$O$2:$O$501,0))),"") | C74: =IFERROR(IF(INDEX(Actions!$B$2:$B$501,MATCH(ROWS(B$69:B74),Actions!$O$2:$O$501,0))="","",INDEX(Actions!$B$2:$B$501,MATCH(ROWS(B$69:B74),Actions!$O$2:$O$501,0))),"") | D74: =IFERROR(IF(INDEX(Actions!$F$2:$F$501,MATCH(ROWS(B$69:B74),Actions!$O$2:$O$501,0))="","",INDEX(Actions!$F$2:$F$501,MATCH(ROWS(B$69:B74),Actions!$O$2:$O$501,0))),"") | E74: =IFERROR(IF(INDEX(Actions!$G$2:$G$501,MATCH(ROWS(B$69:B74),Actions!$O$2:$O$501,0))="","",INDEX(Actions!$G$2:$G$501,MATCH(ROWS(B$69:B74),Actions!$O$2:$O$501,0))),"") | F74: =IFERROR(IF(INDEX(Actions!$H$2:$H$501,MATCH(ROWS(B$69:B74),Actions!$O$2:$O$501,0))="","",INDEX(Actions!$H$2:$H$501,MATCH(ROWS(B$69:B74),Actions!$O$2:$O$501,0))),"") | G74: =IFERROR(IF(INDEX(Actions!$M$2:$M$501,MATCH(ROWS(B$69:B74),Actions!$O$2:$O$501,0))="","",INDEX(Actions!$M$2:$M$501,MATCH(ROWS(B$69:B74),Actions!$O$2:$O$501,0))),"")
B75: =IFERROR(IF(INDEX(Actions!$C$2:$C$501,MATCH(ROWS(B$69:B75),Actions!$O$2:$O$501,0))="","",INDEX(Actions!$C$2:$C$501,MATCH(ROWS(B$69:B75),Actions!$O$2:$O$501,0))),"") | C75: =IFERROR(IF(INDEX(Actions!$B$2:$B$501,MATCH(ROWS(B$69:B75),Actions!$O$2:$O$501,0))="","",INDEX(Actions!$B$2:$B$501,MATCH(ROWS(B$69:B75),Actions!$O$2:$O$501,0))),"") | D75: =IFERROR(IF(INDEX(Actions!$F$2:$F$501,MATCH(ROWS(B$69:B75),Actions!$O$2:$O$501,0))="","",INDEX(Actions!$F$2:$F$501,MATCH(ROWS(B$69:B75),Actions!$O$2:$O$501,0))),"") | E75: =IFERROR(IF(INDEX(Actions!$G$2:$G$501,MATCH(ROWS(B$69:B75),Actions!$O$2:$O$501,0))="","",INDEX(Actions!$G$2:$G$501,MATCH(ROWS(B$69:B75),Actions!$O$2:$O$501,0))),"") | F75: =IFERROR(IF(INDEX(Actions!$H$2:$H$501,MATCH(ROWS(B$69:B75),Actions!$O$2:$O$501,0))="","",INDEX(Actions!$H$2:$H$501,MATCH(ROWS(B$69:B75),Actions!$O$2:$O$501,0))),"") | G75: =IFERROR(IF(INDEX(Actions!$M$2:$M$501,MATCH(ROWS(B$69:B75),Actions!$O$2:$O$501,0))="","",INDEX(Actions!$M$2:$M$501,MATCH(ROWS(B$69:B75),Actions!$O$2:$O$501,0))),"")
B76: =IFERROR(IF(INDEX(Actions!$C$2:$C$501,MATCH(ROWS(B$69:B76),Actions!$O$2:$O$501,0))="","",INDEX(Actions!$C$2:$C$501,MATCH(ROWS(B$69:B76),Actions!$O$2:$O$501,0))),"") | C76: =IFERROR(IF(INDEX(Actions!$B$2:$B$501,MATCH(ROWS(B$69:B76),Actions!$O$2:$O$501,0))="","",INDEX(Actions!$B$2:$B$501,MATCH(ROWS(B$69:B76),Actions!$O$2:$O$501,0))),"") | D76: =IFERROR(IF(INDEX(Actions!$F$2:$F$501,MATCH(ROWS(B$69:B76),Actions!$O$2:$O$501,0))="","",INDEX(Actions!$F$2:$F$501,MATCH(ROWS(B$69:B76),Actions!$O$2:$O$501,0))),"") | E76: =IFERROR(IF(INDEX(Actions!$G$2:$G$501,MATCH(ROWS(B$69:B76),Actions!$O$2:$O$501,0))="","",INDEX(Actions!$G$2:$G$501,MATCH(ROWS(B$69:B76),Actions!$O$2:$O$501,0))),"") | F76: =IFERROR(IF(INDEX(Actions!$H$2:$H$501,MATCH(ROWS(B$69:B76),Actions!$O$2:$O$501,0))="","",INDEX(Actions!$H$2:$H$501,MATCH(ROWS(B$69:B76),Actions!$O$2:$O$501,0))),"") | G76: =IFERROR(IF(INDEX(Actions!$M$2:$M$501,MATCH(ROWS(B$69:B76),Actions!$O$2:$O$501,0))="","",INDEX(Actions!$M$2:$M$501,MATCH(ROWS(B$69:B76),Actions!$O$2:$O$501,0))),"")

Sheet Gantt
A1: Gantt - milestones for the project selected on 'Project Summary'
A2: Blue = planned span (start to forecast completion); green = % complete. The red header marks the current week.
A3: Project: | B3: ='Project Summary'!C3 -> 0
A5: WBS | B5: Activity | C5: Start | D5: Finish | E5: % | G5: =IF(COUNT(C6:C30)=0,TODAY()-WEEKDAY(TODAY(),2)+1,MIN(C6:C30)-WEEKDAY(MIN(C6:C30),2)+1) -> 46300 | H5: =G5+7 -> 46307 | I5: =H5+7 -> 46314 | J5: =I5+7 -> 46321 | K5: =J5+7 -> 46328 | L5: =K5+7 -> 46335 | M5: =L5+7 -> 46342 | N5: =M5+7 -> 46349 | O5: =N5+7 -> 46356 | ... BF5: =BE5+7 -> 46657
A6: =IFERROR(IF(INDEX(Milestones!$B$2:$B$501,MATCH(ROWS(A$6:A6),Milestones!$K$2:$K$501,0))="","",INDEX(Milestones!$B$2:$B$501,MATCH(ROWS(A$6:A6),Milestones!$K$2:$K$501,0))),"") | B6: =IFERROR(IF(INDEX(Milestones!$C$2:$C$501,MATCH(ROWS(A$6:A6),Milestones!$K$2:$K$501,0))="","",INDEX(Milestones!$C$2:$C$501,MATCH(ROWS(A$6:A6),Milestones!$K$2:$K$501,0))),"") | C6: =IFERROR(IF(INDEX(Milestones!$E$2:$E$501,MATCH(ROWS(A$6:A6),Milestones!$K$2:$K$501,0))="","",INDEX(Milestones!$E$2:$E$501,MATCH(ROWS(A$6:A6),Milestones!$K$2:$K$501,0))),"") | D6: =IFERROR(IF(INDEX(Milestones!$G$2:$G$501,MATCH(ROWS(A$6:A6),Milestones!$K$2:$K$501,0))<>"",INDEX(Milestones!$G$2:$G$501,MATCH(ROWS(A$6:A6),Milestones!$K$2:$K$501,0)),INDEX(Milestones!$F$2:$F$501,MATCH(ROWS(A$6:A6),Milestones!$K$2:$K$501,0))),"") | E6: =IFERROR(IF(INDEX(Milestones!$D$2:$D$501,MATCH(ROWS(A$6:A6),Milestones!$K$2:$K$501,0))="","",INDEX(Milestones!$D$2:$D$501,MATCH(ROWS(A$6:A6),Milestones!$K$2:$K$501,0))),"")
A7: =IFERROR(IF(INDEX(Milestones!$B$2:$B$501,MATCH(ROWS(A$6:A7),Milestones!$K$2:$K$501,0))="","",INDEX(Milestones!$B$2:$B$501,MATCH(ROWS(A$6:A7),Milestones!$K$2:$K$501,0))),"") | B7: =IFERROR(IF(INDEX(Milestones!$C$2:$C$501,MATCH(ROWS(A$6:A7),Milestones!$K$2:$K$501,0))="","",INDEX(Milestones!$C$2:$C$501,MATCH(ROWS(A$6:A7),Milestones!$K$2:$K$501,0))),"") | C7: =IFERROR(IF(INDEX(Milestones!$E$2:$E$501,MATCH(ROWS(A$6:A7),Milestones!$K$2:$K$501,0))="","",INDEX(Milestones!$E$2:$E$501,MATCH(ROWS(A$6:A7),Milestones!$K$2:$K$501,0))),"") | D7: =IFERROR(IF(INDEX(Milestones!$G$2:$G$501,MATCH(ROWS(A$6:A7),Milestones!$K$2:$K$501,0))<>"",INDEX(Milestones!$G$2:$G$501,MATCH(ROWS(A$6:A7),Milestones!$K$2:$K$501,0)),INDEX(Milestones!$F$2:$F$501,MATCH(ROWS(A$6:A7),Milestones!$K$2:$K$501,0))),"") | E7: =IFERROR(IF(INDEX(Milestones!$D$2:$D$501,MATCH(ROWS(A$6:A7),Milestones!$K$2:$K$501,0))="","",INDEX(Milestones!$D$2:$D$501,MATCH(ROWS(A$6:A7),Milestones!$K$2:$K$501,0))),"")
A8: =IFERROR(IF(INDEX(Milestones!$B$2:$B$501,MATCH(ROWS(A$6:A8),Milestones!$K$2:$K$501,0))="","",INDEX(Milestones!$B$2:$B$501,MATCH(ROWS(A$6:A8),Milestones!$K$2:$K$501,0))),"") | B8: =IFERROR(IF(INDEX(Milestones!$C$2:$C$501,MATCH(ROWS(A$6:A8),Milestones!$K$2:$K$501,0))="","",INDEX(Milestones!$C$2:$C$501,MATCH(ROWS(A$6:A8),Milestones!$K$2:$K$501,0))),"") | C8: =IFERROR(IF(INDEX(Milestones!$E$2:$E$501,MATCH(ROWS(A$6:A8),Milestones!$K$2:$K$501,0))="","",INDEX(Milestones!$E$2:$E$501,MATCH(ROWS(A$6:A8),Milestones!$K$2:$K$501,0))),"") | D8: =IFERROR(IF(INDEX(Milestones!$G$2:$G$501,MATCH(ROWS(A$6:A8),Milestones!$K$2:$K$501,0))<>"",INDEX(Milestones!$G$2:$G$501,MATCH(ROWS(A$6:A8),Milestones!$K$2:$K$501,0)),INDEX(Milestones!$F$2:$F$501,MATCH(ROWS(A$6:A8),Milestones!$K$2:$K$501,0))),"") | E8: =IFERROR(IF(INDEX(Milestones!$D$2:$D$501,MATCH(ROWS(A$6:A8),Milestones!$K$2:$K$501,0))="","",INDEX(Milestones!$D$2:$D$501,MATCH(ROWS(A$6:A8),Milestones!$K$2:$K$501,0))),"")
A9: =IFERROR(IF(INDEX(Milestones!$B$2:$B$501,MATCH(ROWS(A$6:A9),Milestones!$K$2:$K$501,0))="","",INDEX(Milestones!$B$2:$B$501,MATCH(ROWS(A$6:A9),Milestones!$K$2:$K$501,0))),"") | B9: =IFERROR(IF(INDEX(Milestones!$C$2:$C$501,MATCH(ROWS(A$6:A9),Milestones!$K$2:$K$501,0))="","",INDEX(Milestones!$C$2:$C$501,MATCH(ROWS(A$6:A9),Milestones!$K$2:$K$501,0))),"") | C9: =IFERROR(IF(INDEX(Milestones!$E$2:$E$501,MATCH(ROWS(A$6:A9),Milestones!$K$2:$K$501,0))="","",INDEX(Milestones!$E$2:$E$501,MATCH(ROWS(A$6:A9),Milestones!$K$2:$K$501,0))),"") | D9: =IFERROR(IF(INDEX(Milestones!$G$2:$G$501,MATCH(ROWS(A$6:A9),Milestones!$K$2:$K$501,0))<>"",INDEX(Milestones!$G$2:$G$501,MATCH(ROWS(A$6:A9),Milestones!$K$2:$K$501,0)),INDEX(Milestones!$F$2:$F$501,MATCH(ROWS(A$6:A9),Milestones!$K$2:$K$501,0))),"") | E9: =IFERROR(IF(INDEX(Milestones!$D$2:$D$501,MATCH(ROWS(A$6:A9),Milestones!$K$2:$K$501,0))="","",INDEX(Milestones!$D$2:$D$501,MATCH(ROWS(A$6:A9),Milestones!$K$2:$K$501,0))),"")
A10: =IFERROR(IF(INDEX(Milestones!$B$2:$B$501,MATCH(ROWS(A$6:A10),Milestones!$K$2:$K$501,0))="","",INDEX(Milestones!$B$2:$B$501,MATCH(ROWS(A$6:A10),Milestones!$K$2:$K$501,0))),"") | B10: =IFERROR(IF(INDEX(Milestones!$C$2:$C$501,MATCH(ROWS(A$6:A10),Milestones!$K$2:$K$501,0))="","",INDEX(Milestones!$C$2:$C$501,MATCH(ROWS(A$6:A10),Milestones!$K$2:$K$501,0))),"") | C10: =IFERROR(IF(INDEX(Milestones!$E$2:$E$501,MATCH(ROWS(A$6:A10),Milestones!$K$2:$K$501,0))="","",INDEX(Milestones!$E$2:$E$501,MATCH(ROWS(A$6:A10),Milestones!$K$2:$K$501,0))),"") | D10: =IFERROR(IF(INDEX(Milestones!$G$2:$G$501,MATCH(ROWS(A$6:A10),Milestones!$K$2:$K$501,0))<>"",INDEX(Milestones!$G$2:$G$501,MATCH(ROWS(A$6:A10),Milestones!$K$2:$K$501,0)),INDEX(Milestones!$F$2:$F$501,MATCH(ROWS(A$6:A10),Milestones!$K$2:$K$501,0))),"") | E10: =IFERROR(IF(INDEX(Milestones!$D$2:$D$501,MATCH(ROWS(A$6:A10),Milestones!$K$2:$K$501,0))="","",INDEX(Milestones!$D$2:$D$501,MATCH(ROWS(A$6:A10),Milestones!$K$2:$K$501,0))),"")
A11: =IFERROR(IF(INDEX(Milestones!$B$2:$B$501,MATCH(ROWS(A$6:A11),Milestones!$K$2:$K$501,0))="","",INDEX(Milestones!$B$2:$B$501,MATCH(ROWS(A$6:A11),Milestones!$K$2:$K$501,0))),"") | B11: =IFERROR(IF(INDEX(Milestones!$C$2:$C$501,MATCH(ROWS(A$6:A11),Milestones!$K$2:$K$501,0))="","",INDEX(Milestones!$C$2:$C$501,MATCH(ROWS(A$6:A11),Milestones!$K$2:$K$501,0))),"") | C11: =IFERROR(IF(INDEX(Milestones!$E$2:$E$501,MATCH(ROWS(A$6:A11),Milestones!$K$2:$K$501,0))="","",INDEX(Milestones!$E$2:$E$501,MATCH(ROWS(A$6:A11),Milestones!$K$2:$K$501,0))),"") | D11: =IFERROR(IF(INDEX(Milestones!$G$2:$G$501,MATCH(ROWS(A$6:A11),Milestones!$K$2:$K$501,0))<>"",INDEX(Milestones!$G$2:$G$501,MATCH(ROWS(A$6:A11),Milestones!$K$2:$K$501,0)),INDEX(Milestones!$F$2:$F$501,MATCH(ROWS(A$6:A11),Milestones!$K$2:$K$501,0))),"") | E11: =IFERROR(IF(INDEX(Milestones!$D$2:$D$501,MATCH(ROWS(A$6:A11),Milestones!$K$2:$K$501,0))="","",INDEX(Milestones!$D$2:$D$501,MATCH(ROWS(A$6:A11),Milestones!$K$2:$K$501,0))),"")
A12: =IFERROR(IF(INDEX(Milestones!$B$2:$B$501,MATCH(ROWS(A$6:A12),Milestones!$K$2:$K$501,0))="","",INDEX(Milestones!$B$2:$B$501,MATCH(ROWS(A$6:A12),Milestones!$K$2:$K$501,0))),"") | B12: =IFERROR(IF(INDEX(Milestones!$C$2:$C$501,MATCH(ROWS(A$6:A12),Milestones!$K$2:$K$501,0))="","",INDEX(Milestones!$C$2:$C$501,MATCH(ROWS(A$6:A12),Milestones!$K$2:$K$501,0))),"") | C12: =IFERROR(IF(INDEX(Milestones!$E$2:$E$501,MATCH(ROWS(A$6:A12),Milestones!$K$2:$K$501,0))="","",INDEX(Milestones!$E$2:$E$501,MATCH(ROWS(A$6:A12),Milestones!$K$2:$K$501,0))),"") | D12: =IFERROR(IF(INDEX(Milestones!$G$2:$G$501,MATCH(ROWS(A$6:A12),Milestones!$K$2:$K$501,0))<>"",INDEX(Milestones!$G$2:$G$501,MATCH(ROWS(A$6:A12),Milestones!$K$2:$K$501,0)),INDEX(Milestones!$F$2:$F$501,MATCH(ROWS(A$6:A12),Milestones!$K$2:$K$501,0))),"") | E12: =IFERROR(IF(INDEX(Milestones!$D$2:$D$501,MATCH(ROWS(A$6:A12),Milestones!$K$2:$K$501,0))="","",INDEX(Milestones!$D$2:$D$501,MATCH(ROWS(A$6:A12),Milestones!$K$2:$K$501,0))),"")
A13: =IFERROR(IF(INDEX(Milestones!$B$2:$B$501,MATCH(ROWS(A$6:A13),Milestones!$K$2:$K$501,0))="","",INDEX(Milestones!$B$2:$B$501,MATCH(ROWS(A$6:A13),Milestones!$K$2:$K$501,0))),"") | B13: =IFERROR(IF(INDEX(Milestones!$C$2:$C$501,MATCH(ROWS(A$6:A13),Milestones!$K$2:$K$501,0))="","",INDEX(Milestones!$C$2:$C$501,MATCH(ROWS(A$6:A13),Milestones!$K$2:$K$501,0))),"") | C13: =IFERROR(IF(INDEX(Milestones!$E$2:$E$501,MATCH(ROWS(A$6:A13),Milestones!$K$2:$K$501,0))="","",INDEX(Milestones!$E$2:$E$501,MATCH(ROWS(A$6:A13),Milestones!$K$2:$K$501,0))),"") | D13: =IFERROR(IF(INDEX(Milestones!$G$2:$G$501,MATCH(ROWS(A$6:A13),Milestones!$K$2:$K$501,0))<>"",INDEX(Milestones!$G$2:$G$501,MATCH(ROWS(A$6:A13),Milestones!$K$2:$K$501,0)),INDEX(Milestones!$F$2:$F$501,MATCH(ROWS(A$6:A13),Milestones!$K$2:$K$501,0))),"") | E13: =IFERROR(IF(INDEX(Milestones!$D$2:$D$501,MATCH(ROWS(A$6:A13),Milestones!$K$2:$K$501,0))="","",INDEX(Milestones!$D$2:$D$501,MATCH(ROWS(A$6:A13),Milestones!$K$2:$K$501,0))),"")
A14: =IFERROR(IF(INDEX(Milestones!$B$2:$B$501,MATCH(ROWS(A$6:A14),Milestones!$K$2:$K$501,0))="","",INDEX(Milestones!$B$2:$B$501,MATCH(ROWS(A$6:A14),Milestones!$K$2:$K$501,0))),"") | B14: =IFERROR(IF(INDEX(Milestones!$C$2:$C$501,MATCH(ROWS(A$6:A14),Milestones!$K$2:$K$501,0))="","",INDEX(Milestones!$C$2:$C$501,MATCH(ROWS(A$6:A14),Milestones!$K$2:$K$501,0))),"") | C14: =IFERROR(IF(INDEX(Milestones!$E$2:$E$501,MATCH(ROWS(A$6:A14),Milestones!$K$2:$K$501,0))="","",INDEX(Milestones!$E$2:$E$501,MATCH(ROWS(A$6:A14),Milestones!$K$2:$K$501,0))),"") | D14: =IFERROR(IF(INDEX(Milestones!$G$2:$G$501,MATCH(ROWS(A$6:A14),Milestones!$K$2:$K$501,0))<>"",INDEX(Milestones!$G$2:$G$501,MATCH(ROWS(A$6:A14),Milestones!$K$2:$K$501,0)),INDEX(Milestones!$F$2:$F$501,MATCH(ROWS(A$6:A14),Milestones!$K$2:$K$501,0))),"") | E14: =IFERROR(IF(INDEX(Milestones!$D$2:$D$501,MATCH(ROWS(A$6:A14),Milestones!$K$2:$K$501,0))="","",INDEX(Milestones!$D$2:$D$501,MATCH(ROWS(A$6:A14),Milestones!$K$2:$K$501,0))),"")
A15: =IFERROR(IF(INDEX(Milestones!$B$2:$B$501,MATCH(ROWS(A$6:A15),Milestones!$K$2:$K$501,0))="","",INDEX(Milestones!$B$2:$B$501,MATCH(ROWS(A$6:A15),Milestones!$K$2:$K$501,0))),"") | B15: =IFERROR(IF(INDEX(Milestones!$C$2:$C$501,MATCH(ROWS(A$6:A15),Milestones!$K$2:$K$501,0))="","",INDEX(Milestones!$C$2:$C$501,MATCH(ROWS(A$6:A15),Milestones!$K$2:$K$501,0))),"") | C15: =IFERROR(IF(INDEX(Milestones!$E$2:$E$501,MATCH(ROWS(A$6:A15),Milestones!$K$2:$K$501,0))="","",INDEX(Milestones!$E$2:$E$501,MATCH(ROWS(A$6:A15),Milestones!$K$2:$K$501,0))),"") | D15: =IFERROR(IF(INDEX(Milestones!$G$2:$G$501,MATCH(ROWS(A$6:A15),Milestones!$K$2:$K$501,0))<>"",INDEX(Milestones!$G$2:$G$501,MATCH(ROWS(A$6:A15),Milestones!$K$2:$K$501,0)),INDEX(Milestones!$F$2:$F$501,MATCH(ROWS(A$6:A15),Milestones!$K$2:$K$501,0))),"") | E15: =IFERROR(IF(INDEX(Milestones!$D$2:$D$501,MATCH(ROWS(A$6:A15),Milestones!$K$2:$K$501,0))="","",INDEX(Milestones!$D$2:$D$501,MATCH(ROWS(A$6:A15),Milestones!$K$2:$K$501,0))),"")
A16: =IFERROR(IF(INDEX(Milestones!$B$2:$B$501,MATCH(ROWS(A$6:A16),Milestones!$K$2:$K$501,0))="","",INDEX(Milestones!$B$2:$B$501,MATCH(ROWS(A$6:A16),Milestones!$K$2:$K$501,0))),"") | B16: =IFERROR(IF(INDEX(Milestones!$C$2:$C$501,MATCH(ROWS(A$6:A16),Milestones!$K$2:$K$501,0))="","",INDEX(Milestones!$C$2:$C$501,MATCH(ROWS(A$6:A16),Milestones!$K$2:$K$501,0))),"") | C16: =IFERROR(IF(INDEX(Milestones!$E$2:$E$501,MATCH(ROWS(A$6:A16),Milestones!$K$2:$K$501,0))="","",INDEX(Milestones!$E$2:$E$501,MATCH(ROWS(A$6:A16),Milestones!$K$2:$K$501,0))),"") | D16: =IFERROR(IF(INDEX(Milestones!$G$2:$G$501,MATCH(ROWS(A$6:A16),Milestones!$K$2:$K$501,0))<>"",INDEX(Milestones!$G$2:$G$501,MATCH(ROWS(A$6:A16),Milestones!$K$2:$K$501,0)),INDEX(Milestones!$F$2:$F$501,MATCH(ROWS(A$6:A16),Milestones!$K$2:$K$501,0))),"") | E16: =IFERROR(IF(INDEX(Milestones!$D$2:$D$501,MATCH(ROWS(A$6:A16),Milestones!$K$2:$K$501,0))="","",INDEX(Milestones!$D$2:$D$501,MATCH(ROWS(A$6:A16),Milestones!$K$2:$K$501,0))),"")
A17: =IFERROR(IF(INDEX(Milestones!$B$2:$B$501,MATCH(ROWS(A$6:A17),Milestones!$K$2:$K$501,0))="","",INDEX(Milestones!$B$2:$B$501,MATCH(ROWS(A$6:A17),Milestones!$K$2:$K$501,0))),"") | B17: =IFERROR(IF(INDEX(Milestones!$C$2:$C$501,MATCH(ROWS(A$6:A17),Milestones!$K$2:$K$501,0))="","",INDEX(Milestones!$C$2:$C$501,MATCH(ROWS(A$6:A17),Milestones!$K$2:$K$501,0))),"") | C17: =IFERROR(IF(INDEX(Milestones!$E$2:$E$501,MATCH(ROWS(A$6:A17),Milestones!$K$2:$K$501,0))="","",INDEX(Milestones!$E$2:$E$501,MATCH(ROWS(A$6:A17),Milestones!$K$2:$K$501,0))),"") | D17: =IFERROR(IF(INDEX(Milestones!$G$2:$G$501,MATCH(ROWS(A$6:A17),Milestones!$K$2:$K$501,0))<>"",INDEX(Milestones!$G$2:$G$501,MATCH(ROWS(A$6:A17),Milestones!$K$2:$K$501,0)),INDEX(Milestones!$F$2:$F$501,MATCH(ROWS(A$6:A17),Milestones!$K$2:$K$501,0))),"") | E17: =IFERROR(IF(INDEX(Milestones!$D$2:$D$501,MATCH(ROWS(A$6:A17),Milestones!$K$2:$K$501,0))="","",INDEX(Milestones!$D$2:$D$501,MATCH(ROWS(A$6:A17),Milestones!$K$2:$K$501,0))),"")
... A30: =IFERROR(IF(INDEX(Milestones!$B$2:$B$501,MATCH(ROWS(A$6:A30),Milestones!$K$2:$K$501,0))="","",INDEX(Milestones!$B$2:$B$501,MATCH(ROWS(A$6:A30),Milestones!$K$2:$K$501,0))),"") | B30: =IFERROR(IF(INDEX(Milestones!$C$2:$C$501,MATCH(ROWS(A$6:A30),Milestones!$K$2:$K$501,0))="","",INDEX(Milestones!$C$2:$C$501,MATCH(ROWS(A$6:A30),Milestones!$K$2:$K$501,0))),"") | C30: =IFERROR(IF(INDEX(Milestones!$E$2:$E$501,MATCH(ROWS(A$6:A30),Milestones!$K$2:$K$501,0))="","",INDEX(Milestones!$E$2:$E$501,MATCH(ROWS(A$6:A30),Milestones!$K$2:$K$501,0))),"") | D30: =IFERROR(IF(INDEX(Milestones!$G$2:$G$501,MATCH(ROWS(A$6:A30),Milestones!$K$2:$K$501,0))<>"",INDEX(Milestones!$G$2:$G$501,MATCH(ROWS(A$6:A30),Milestones!$K$2:$K$501,0)),INDEX(Milestones!$F$2:$F$501,MATCH(ROWS(A$6:A30),Milestones!$K$2:$K$501,0))),"") | E30: =IFERROR(IF(INDEX(Milestones!$D$2:$D$501,MATCH(ROWS(A$6:A30),Milestones!$K$2:$K$501,0))="","",INDEX(Milestones!$D$2:$D$501,MATCH(ROWS(A$6:A30),Milestones!$K$2:$K$501,0))),"")

Sheet Charts
A1: Charts
A2: Driven by the Dashboard portfolio table and the Calc sheet.

Sheet Search
A1: Global Search
A2: Type a word in B3 and press Enter. Needs the macros (see VBA/README). Without them use Ctrl+F > Options > Within: Workbook.
A3: Search for:
A5: Sheet | B5: Row key | C5: Matching text | D5: Go to

Sheet Projects
A1: Project Name | B1: Description | C1: Asset Type | D1: Status | E1: BP Ref No | F1: Project Manager | G1: Project Director | H1: Project Sponsor | I1: Location | J1: Contractor | K1: Contract Value | L1: Original Budget | M1: Latest Approved Budget | N1: Start Date | O1: Target Completion | P1: Actual Completion | Q1: Approved Variations | R1: Effective Budget | S1: Expenditure to Date | T1: Forecast at Completion | U1: Budget Variance | V1: Approved EOT Days | W1: Revised Completion | X1: Overdue | Y1: Schedule Elapsed % | Z1: Schedule Health | AA1: Forecast % of Budget | AB1: Budget Health | AC1: Critical Risks | AD1: High Risks | AE1: Risk Health | AF1: Overall Health | AG1: Open Tasks | AH1: Open Actions | AI1: Open RFIs | AJ1: Open Defects | AK1: Health Notes
Q2: =IF(A2="","",SUMIFS(Variations!$F$2:$F$501,Variations!$A$2:$A$501,A2,Variations!$H$2:$H$501,"Approved")) | R2: =IF(A2="","",IF(M2<>"",M2,IF(L2="","",L2+Q2))) | S2: =IF(A2="","",SUMIFS('Cash Flow'!$D$2:$D$2001,'Cash Flow'!$A$2:$A$2001,A2,'Cash Flow'!$C$2:$C$2001,"Actual")) | T2: =IF(A2="","",SUMIFS('Cash Flow'!$F$2:$F$2001,'Cash Flow'!$A$2:$A$2001,A2)) | U2: =IF(A2="","",IF(R2="","",R2-T2)) | V2: =IF(A2="","",SUMIFS('EOT Claims'!$L$2:$L$501,'EOT Claims'!$A$2:$A$501,A2)) | W2: =IF(A2="","",IF(O2="","",O2+V2)) | X2: =IF(A2="","",IF(O2="","",IF(AND(NOT(OR(D2="Project Completion",D2="Defects Liability",D2="Complete",D2="Cancelled")),O2<TODAY()),"Overdue",""))) | Y2: =IF(A2="","",IF(OR(N2="",W2=""),"",IF(W2<=N2,"",(TODAY()-N2)/(W2-N2)))) | Z2: =IF(A2="","",IF(OR(Y2="",OR(D2="Project Completion",D2="Defects Liability",D2="Complete",D2="Cancelled")),"Green",IF(Y2>1.15,"Red",IF(Y2>=0.95,"Amber","Green")))) | AA2: =IF(A2="","",IF(R2="","",IF(OR(R2<=0,COUNTIFS('Cash Flow'!$A$2:$A$2001,A2)=0),"",T2/R2))) | AB2: =IF(A2="","",IF(AA2="","Green",IF(AA2>1.15,"Red",IF(AA2>=0.95,"Amber","Green")))) | AC2: =IF(A2="","",COUNTIFS(Risks!$A$2:$A$501,A2,Risks!$B$2:$B$501,"Risk",Risks!$M$2:$M$501,"<>Closed",Risks!$O$2:$O$501,"Critical")) | AD2: =IF(A2="","",COUNTIFS(Risks!$A$2:$A$501,A2,Risks!$B$2:$B$501,"Risk",Risks!$M$2:$M$501,"<>Closed",Risks!$O$2:$O$501,"High")) | AE2: =IF(A2="","",IF(AC2>0,"Red",IF(AD2>0,"Amber","Green"))) | AF2: =IF(A2="","",IF(OR(Z2="Red",AB2="Red",AE2="Red"),"Red",IF(OR(Z2="Amber",AB2="Amber",AE2="Amber"),"Amber","Green"))) | AG2: =IF(A2="","",COUNTIFS(Tasks!$A$2:$A$1001,A2,Tasks!$D$2:$D$1001,"<>Done",Tasks!$B$2:$B$1001,"<>")) | AH2: =IF(A2="","",COUNTIFS(Actions!$A$2:$A$501,A2,Actions!$H$2:$H$501,"<>Done",Actions!$C$2:$C$501,"<>")) | AI2: =IF(A2="","",COUNTIFS(RFIs!$A$2:$A$501,A2,RFIs!$G$2:$G$501,"Open")) | AJ2: =IF(A2="","",COUNTIFS(Defects!$A$2:$A$501,A2,Defects!$H$2:$H$501,"Open")) | AK2: =IF(A2="","","Schedule: "&IF(Y2="","no dates / not tracked",TEXT(Y2,"0%")&" of timeframe elapsed")&" | Budget: "&IF(AA2="","no approved budget or cash flow",TEXT(AA2,"0%")&" of budget forecast")&" | Risk: "&AC2&" critical, "&AD2&" high open")
Q3: =IF(A3="","",SUMIFS(Variations!$F$2:$F$501,Variations!$A$2:$A$501,A3,Variations!$H$2:$H$501,"Approved")) | R3: =IF(A3="","",IF(M3<>"",M3,IF(L3="","",L3+Q3))) | S3: =IF(A3="","",SUMIFS('Cash Flow'!$D$2:$D$2001,'Cash Flow'!$A$2:$A$2001,A3,'Cash Flow'!$C$2:$C$2001,"Actual")) | T3: =IF(A3="","",SUMIFS('Cash Flow'!$F$2:$F$2001,'Cash Flow'!$A$2:$A$2001,A3)) | U3: =IF(A3="","",IF(R3="","",R3-T3)) | V3: =IF(A3="","",SUMIFS('EOT Claims'!$L$2:$L$501,'EOT Claims'!$A$2:$A$501,A3)) | W3: =IF(A3="","",IF(O3="","",O3+V3)) | X3: =IF(A3="","",IF(O3="","",IF(AND(NOT(OR(D3="Project Completion",D3="Defects Liability",D3="Complete",D3="Cancelled")),O3<TODAY()),"Overdue",""))) | Y3: =IF(A3="","",IF(OR(N3="",W3=""),"",IF(W3<=N3,"",(TODAY()-N3)/(W3-N3)))) | Z3: =IF(A3="","",IF(OR(Y3="",OR(D3="Project Completion",D3="Defects Liability",D3="Complete",D3="Cancelled")),"Green",IF(Y3>1.15,"Red",IF(Y3>=0.95,"Amber","Green")))) | AA3: =IF(A3="","",IF(R3="","",IF(OR(R3<=0,COUNTIFS('Cash Flow'!$A$2:$A$2001,A3)=0),"",T3/R3))) | AB3: =IF(A3="","",IF(AA3="","Green",IF(AA3>1.15,"Red",IF(AA3>=0.95,"Amber","Green")))) | AC3: =IF(A3="","",COUNTIFS(Risks!$A$2:$A$501,A3,Risks!$B$2:$B$501,"Risk",Risks!$M$2:$M$501,"<>Closed",Risks!$O$2:$O$501,"Critical")) | AD3: =IF(A3="","",COUNTIFS(Risks!$A$2:$A$501,A3,Risks!$B$2:$B$501,"Risk",Risks!$M$2:$M$501,"<>Closed",Risks!$O$2:$O$501,"High")) | AE3: =IF(A3="","",IF(AC3>0,"Red",IF(AD3>0,"Amber","Green"))) | AF3: =IF(A3="","",IF(OR(Z3="Red",AB3="Red",AE3="Red"),"Red",IF(OR(Z3="Amber",AB3="Amber",AE3="Amber"),"Amber","Green"))) | AG3: =IF(A3="","",COUNTIFS(Tasks!$A$2:$A$1001,A3,Tasks!$D$2:$D$1001,"<>Done",Tasks!$B$2:$B$1001,"<>")) | AH3: =IF(A3="","",COUNTIFS(Actions!$A$2:$A$501,A3,Actions!$H$2:$H$501,"<>Done",Actions!$C$2:$C$501,"<>")) | AI3: =IF(A3="","",COUNTIFS(RFIs!$A$2:$A$501,A3,RFIs!$G$2:$G$501,"Open")) | AJ3: =IF(A3="","",COUNTIFS(Defects!$A$2:$A$501,A3,Defects!$H$2:$H$501,"Open")) | AK3: =IF(A3="","","Schedule: "&IF(Y3="","no dates / not tracked",TEXT(Y3,"0%")&" of timeframe elapsed")&" | Budget: "&IF(AA3="","no approved budget or cash flow",TEXT(AA3,"0%")&" of budget forecast")&" | Risk: "&AC3&" critical, "&AD3&" high open")
Q4: =IF(A4="","",SUMIFS(Variations!$F$2:$F$501,Variations!$A$2:$A$501,A4,Variations!$H$2:$H$501,"Approved")) | R4: =IF(A4="","",IF(M4<>"",M4,IF(L4="","",L4+Q4))) | S4: =IF(A4="","",SUMIFS('Cash Flow'!$D$2:$D$2001,'Cash Flow'!$A$2:$A$2001,A4,'Cash Flow'!$C$2:$C$2001,"Actual")) | T4: =IF(A4="","",SUMIFS('Cash Flow'!$F$2:$F$2001,'Cash Flow'!$A$2:$A$2001,A4)) | U4: =IF(A4="","",IF(R4="","",R4-T4)) | V4: =IF(A4="","",SUMIFS('EOT Claims'!$L$2:$L$501,'EOT Claims'!$A$2:$A$501,A4)) | W4: =IF(A4="","",IF(O4="","",O4+V4)) | X4: =IF(A4="","",IF(O4="","",IF(AND(NOT(OR(D4="Project Completion",D4="Defects Liability",D4="Complete",D4="Cancelled")),O4<TODAY()),"Overdue",""))) | Y4: =IF(A4="","",IF(OR(N4="",W4=""),"",IF(W4<=N4,"",(TODAY()-N4)/(W4-N4)))) | Z4: =IF(A4="","",IF(OR(Y4="",OR(D4="Project Completion",D4="Defects Liability",D4="Complete",D4="Cancelled")),"Green",IF(Y4>1.15,"Red",IF(Y4>=0.95,"Amber","Green")))) | AA4: =IF(A4="","",IF(R4="","",IF(OR(R4<=0,COUNTIFS('Cash Flow'!$A$2:$A$2001,A4)=0),"",T4/R4))) | AB4: =IF(A4="","",IF(AA4="","Green",IF(AA4>1.15,"Red",IF(AA4>=0.95,"Amber","Green")))) | AC4: =IF(A4="","",COUNTIFS(Risks!$A$2:$A$501,A4,Risks!$B$2:$B$501,"Risk",Risks!$M$2:$M$501,"<>Closed",Risks!$O$2:$O$501,"Critical")) | AD4: =IF(A4="","",COUNTIFS(Risks!$A$2:$A$501,A4,Risks!$B$2:$B$501,"Risk",Risks!$M$2:$M$501,"<>Closed",Risks!$O$2:$O$501,"High")) | AE4: =IF(A4="","",IF(AC4>0,"Red",IF(AD4>0,"Amber","Green"))) | AF4: =IF(A4="","",IF(OR(Z4="Red",AB4="Red",AE4="Red"),"Red",IF(OR(Z4="Amber",AB4="Amber",AE4="Amber"),"Amber","Green"))) | AG4: =IF(A4="","",COUNTIFS(Tasks!$A$2:$A$1001,A4,Tasks!$D$2:$D$1001,"<>Done",Tasks!$B$2:$B$1001,"<>")) | AH4: =IF(A4="","",COUNTIFS(Actions!$A$2:$A$501,A4,Actions!$H$2:$H$501,"<>Done",Actions!$C$2:$C$501,"<>")) | AI4: =IF(A4="","",COUNTIFS(RFIs!$A$2:$A$501,A4,RFIs!$G$2:$G$501,"Open")) | AJ4: =IF(A4="","",COUNTIFS(Defects!$A$2:$A$501,A4,Defects!$H$2:$H$501,"Open")) | AK4: =IF(A4="","","Schedule: "&IF(Y4="","no dates / not tracked",TEXT(Y4,"0%")&" of timeframe elapsed")&" | Budget: "&IF(AA4="","no approved budget or cash flow",TEXT(AA4,"0%")&" of budget forecast")&" | Risk: "&AC4&" critical, "&AD4&" high open")
Q5: =IF(A5="","",SUMIFS(Variations!$F$2:$F$501,Variations!$A$2:$A$501,A5,Variations!$H$2:$H$501,"Approved")) | R5: =IF(A5="","",IF(M5<>"",M5,IF(L5="","",L5+Q5))) | S5: =IF(A5="","",SUMIFS('Cash Flow'!$D$2:$D$2001,'Cash Flow'!$A$2:$A$2001,A5,'Cash Flow'!$C$2:$C$2001,"Actual")) | T5: =IF(A5="","",SUMIFS('Cash Flow'!$F$2:$F$2001,'Cash Flow'!$A$2:$A$2001,A5)) | U5: =IF(A5="","",IF(R5="","",R5-T5)) | V5: =IF(A5="","",SUMIFS('EOT Claims'!$L$2:$L$501,'EOT Claims'!$A$2:$A$501,A5)) | W5: =IF(A5="","",IF(O5="","",O5+V5)) | X5: =IF(A5="","",IF(O5="","",IF(AND(NOT(OR(D5="Project Completion",D5="Defects Liability",D5="Complete",D5="Cancelled")),O5<TODAY()),"Overdue",""))) | Y5: =IF(A5="","",IF(OR(N5="",W5=""),"",IF(W5<=N5,"",(TODAY()-N5)/(W5-N5)))) | Z5: =IF(A5="","",IF(OR(Y5="",OR(D5="Project Completion",D5="Defects Liability",D5="Complete",D5="Cancelled")),"Green",IF(Y5>1.15,"Red",IF(Y5>=0.95,"Amber","Green")))) | AA5: =IF(A5="","",IF(R5="","",IF(OR(R5<=0,COUNTIFS('Cash Flow'!$A$2:$A$2001,A5)=0),"",T5/R5))) | AB5: =IF(A5="","",IF(AA5="","Green",IF(AA5>1.15,"Red",IF(AA5>=0.95,"Amber","Green")))) | AC5: =IF(A5="","",COUNTIFS(Risks!$A$2:$A$501,A5,Risks!$B$2:$B$501,"Risk",Risks!$M$2:$M$501,"<>Closed",Risks!$O$2:$O$501,"Critical")) | AD5: =IF(A5="","",COUNTIFS(Risks!$A$2:$A$501,A5,Risks!$B$2:$B$501,"Risk",Risks!$M$2:$M$501,"<>Closed",Risks!$O$2:$O$501,"High")) | AE5: =IF(A5="","",IF(AC5>0,"Red",IF(AD5>0,"Amber","Green"))) | AF5: =IF(A5="","",IF(OR(Z5="Red",AB5="Red",AE5="Red"),"Red",IF(OR(Z5="Amber",AB5="Amber",AE5="Amber"),"Amber","Green"))) | AG5: =IF(A5="","",COUNTIFS(Tasks!$A$2:$A$1001,A5,Tasks!$D$2:$D$1001,"<>Done",Tasks!$B$2:$B$1001,"<>")) | AH5: =IF(A5="","",COUNTIFS(Actions!$A$2:$A$501,A5,Actions!$H$2:$H$501,"<>Done",Actions!$C$2:$C$501,"<>")) | AI5: =IF(A5="","",COUNTIFS(RFIs!$A$2:$A$501,A5,RFIs!$G$2:$G$501,"Open")) | AJ5: =IF(A5="","",COUNTIFS(Defects!$A$2:$A$501,A5,Defects!$H$2:$H$501,"Open")) | AK5: =IF(A5="","","Schedule: "&IF(Y5="","no dates / not tracked",TEXT(Y5,"0%")&" of timeframe elapsed")&" | Budget: "&IF(AA5="","no approved budget or cash flow",TEXT(AA5,"0%")&" of budget forecast")&" | Risk: "&AC5&" critical, "&AD5&" high open")
Q6: =IF(A6="","",SUMIFS(Variations!$F$2:$F$501,Variations!$A$2:$A$501,A6,Variations!$H$2:$H$501,"Approved")) | R6: =IF(A6="","",IF(M6<>"",M6,IF(L6="","",L6+Q6))) | S6: =IF(A6="","",SUMIFS('Cash Flow'!$D$2:$D$2001,'Cash Flow'!$A$2:$A$2001,A6,'Cash Flow'!$C$2:$C$2001,"Actual")) | T6: =IF(A6="","",SUMIFS('Cash Flow'!$F$2:$F$2001,'Cash Flow'!$A$2:$A$2001,A6)) | U6: =IF(A6="","",IF(R6="","",R6-T6)) | V6: =IF(A6="","",SUMIFS('EOT Claims'!$L$2:$L$501,'EOT Claims'!$A$2:$A$501,A6)) | W6: =IF(A6="","",IF(O6="","",O6+V6)) | X6: =IF(A6="","",IF(O6="","",IF(AND(NOT(OR(D6="Project Completion",D6="Defects Liability",D6="Complete",D6="Cancelled")),O6<TODAY()),"Overdue",""))) | Y6: =IF(A6="","",IF(OR(N6="",W6=""),"",IF(W6<=N6,"",(TODAY()-N6)/(W6-N6)))) | Z6: =IF(A6="","",IF(OR(Y6="",OR(D6="Project Completion",D6="Defects Liability",D6="Complete",D6="Cancelled")),"Green",IF(Y6>1.15,"Red",IF(Y6>=0.95,"Amber","Green")))) | AA6: =IF(A6="","",IF(R6="","",IF(OR(R6<=0,COUNTIFS('Cash Flow'!$A$2:$A$2001,A6)=0),"",T6/R6))) | AB6: =IF(A6="","",IF(AA6="","Green",IF(AA6>1.15,"Red",IF(AA6>=0.95,"Amber","Green")))) | AC6: =IF(A6="","",COUNTIFS(Risks!$A$2:$A$501,A6,Risks!$B$2:$B$501,"Risk",Risks!$M$2:$M$501,"<>Closed",Risks!$O$2:$O$501,"Critical")) | AD6: =IF(A6="","",COUNTIFS(Risks!$A$2:$A$501,A6,Risks!$B$2:$B$501,"Risk",Risks!$M$2:$M$501,"<>Closed",Risks!$O$2:$O$501,"High")) | AE6: =IF(A6="","",IF(AC6>0,"Red",IF(AD6>0,"Amber","Green"))) | AF6: =IF(A6="","",IF(OR(Z6="Red",AB6="Red",AE6="Red"),"Red",IF(OR(Z6="Amber",AB6="Amber",AE6="Amber"),"Amber","Green"))) | AG6: =IF(A6="","",COUNTIFS(Tasks!$A$2:$A$1001,A6,Tasks!$D$2:$D$1001,"<>Done",Tasks!$B$2:$B$1001,"<>")) | AH6: =IF(A6="","",COUNTIFS(Actions!$A$2:$A$501,A6,Actions!$H$2:$H$501,"<>Done",Actions!$C$2:$C$501,"<>")) | AI6: =IF(A6="","",COUNTIFS(RFIs!$A$2:$A$501,A6,RFIs!$G$2:$G$501,"Open")) | AJ6: =IF(A6="","",COUNTIFS(Defects!$A$2:$A$501,A6,Defects!$H$2:$H$501,"Open")) | AK6: =IF(A6="","","Schedule: "&IF(Y6="","no dates / not tracked",TEXT(Y6,"0%")&" of timeframe elapsed")&" | Budget: "&IF(AA6="","no approved budget or cash flow",TEXT(AA6,"0%")&" of budget forecast")&" | Risk: "&AC6&" critical, "&AD6&" high open")
Q7: =IF(A7="","",SUMIFS(Variations!$F$2:$F$501,Variations!$A$2:$A$501,A7,Variations!$H$2:$H$501,"Approved")) | R7: =IF(A7="","",IF(M7<>"",M7,IF(L7="","",L7+Q7))) | S7: =IF(A7="","",SUMIFS('Cash Flow'!$D$2:$D$2001,'Cash Flow'!$A$2:$A$2001,A7,'Cash Flow'!$C$2:$C$2001,"Actual")) | T7: =IF(A7="","",SUMIFS('Cash Flow'!$F$2:$F$2001,'Cash Flow'!$A$2:$A$2001,A7)) | U7: =IF(A7="","",IF(R7="","",R7-T7)) | V7: =IF(A7="","",SUMIFS('EOT Claims'!$L$2:$L$501,'EOT Claims'!$A$2:$A$501,A7)) | W7: =IF(A7="","",IF(O7="","",O7+V7)) | X7: =IF(A7="","",IF(O7="","",IF(AND(NOT(OR(D7="Project Completion",D7="Defects Liability",D7="Complete",D7="Cancelled")),O7<TODAY()),"Overdue",""))) | Y7: =IF(A7="","",IF(OR(N7="",W7=""),"",IF(W7<=N7,"",(TODAY()-N7)/(W7-N7)))) | Z7: =IF(A7="","",IF(OR(Y7="",OR(D7="Project Completion",D7="Defects Liability",D7="Complete",D7="Cancelled")),"Green",IF(Y7>1.15,"Red",IF(Y7>=0.95,"Amber","Green")))) | AA7: =IF(A7="","",IF(R7="","",IF(OR(R7<=0,COUNTIFS('Cash Flow'!$A$2:$A$2001,A7)=0),"",T7/R7))) | AB7: =IF(A7="","",IF(AA7="","Green",IF(AA7>1.15,"Red",IF(AA7>=0.95,"Amber","Green")))) | AC7: =IF(A7="","",COUNTIFS(Risks!$A$2:$A$501,A7,Risks!$B$2:$B$501,"Risk",Risks!$M$2:$M$501,"<>Closed",Risks!$O$2:$O$501,"Critical")) | AD7: =IF(A7="","",COUNTIFS(Risks!$A$2:$A$501,A7,Risks!$B$2:$B$501,"Risk",Risks!$M$2:$M$501,"<>Closed",Risks!$O$2:$O$501,"High")) | AE7: =IF(A7="","",IF(AC7>0,"Red",IF(AD7>0,"Amber","Green"))) | AF7: =IF(A7="","",IF(OR(Z7="Red",AB7="Red",AE7="Red"),"Red",IF(OR(Z7="Amber",AB7="Amber",AE7="Amber"),"Amber","Green"))) | AG7: =IF(A7="","",COUNTIFS(Tasks!$A$2:$A$1001,A7,Tasks!$D$2:$D$1001,"<>Done",Tasks!$B$2:$B$1001,"<>")) | AH7: =IF(A7="","",COUNTIFS(Actions!$A$2:$A$501,A7,Actions!$H$2:$H$501,"<>Done",Actions!$C$2:$C$501,"<>")) | AI7: =IF(A7="","",COUNTIFS(RFIs!$A$2:$A$501,A7,RFIs!$G$2:$G$501,"Open")) | AJ7: =IF(A7="","",COUNTIFS(Defects!$A$2:$A$501,A7,Defects!$H$2:$H$501,"Open")) | AK7: =IF(A7="","","Schedule: "&IF(Y7="","no dates / not tracked",TEXT(Y7,"0%")&" of timeframe elapsed")&" | Budget: "&IF(AA7="","no approved budget or cash flow",TEXT(AA7,"0%")&" of budget forecast")&" | Risk: "&AC7&" critical, "&AD7&" high open")
Q8: =IF(A8="","",SUMIFS(Variations!$F$2:$F$501,Variations!$A$2:$A$501,A8,Variations!$H$2:$H$501,"Approved")) | R8: =IF(A8="","",IF(M8<>"",M8,IF(L8="","",L8+Q8))) | S8: =IF(A8="","",SUMIFS('Cash Flow'!$D$2:$D$2001,'Cash Flow'!$A$2:$A$2001,A8,'Cash Flow'!$C$2:$C$2001,"Actual")) | T8: =IF(A8="","",SUMIFS('Cash Flow'!$F$2:$F$2001,'Cash Flow'!$A$2:$A$2001,A8)) | U8: =IF(A8="","",IF(R8="","",R8-T8)) | V8: =IF(A8="","",SUMIFS('EOT Claims'!$L$2:$L$501,'EOT Claims'!$A$2:$A$501,A8)) | W8: =IF(A8="","",IF(O8="","",O8+V8)) | X8: =IF(A8="","",IF(O8="","",IF(AND(NOT(OR(D8="Project Completion",D8="Defects Liability",D8="Complete",D8="Cancelled")),O8<TODAY()),"Overdue",""))) | Y8: =IF(A8="","",IF(OR(N8="",W8=""),"",IF(W8<=N8,"",(TODAY()-N8)/(W8-N8)))) | Z8: =IF(A8="","",IF(OR(Y8="",OR(D8="Project Completion",D8="Defects Liability",D8="Complete",D8="Cancelled")),"Green",IF(Y8>1.15,"Red",IF(Y8>=0.95,"Amber","Green")))) | AA8: =IF(A8="","",IF(R8="","",IF(OR(R8<=0,COUNTIFS('Cash Flow'!$A$2:$A$2001,A8)=0),"",T8/R8))) | AB8: =IF(A8="","",IF(AA8="","Green",IF(AA8>1.15,"Red",IF(AA8>=0.95,"Amber","Green")))) | AC8: =IF(A8="","",COUNTIFS(Risks!$A$2:$A$501,A8,Risks!$B$2:$B$501,"Risk",Risks!$M$2:$M$501,"<>Closed",Risks!$O$2:$O$501,"Critical")) | AD8: =IF(A8="","",COUNTIFS(Risks!$A$2:$A$501,A8,Risks!$B$2:$B$501,"Risk",Risks!$M$2:$M$501,"<>Closed",Risks!$O$2:$O$501,"High")) | AE8: =IF(A8="","",IF(AC8>0,"Red",IF(AD8>0,"Amber","Green"))) | AF8: =IF(A8="","",IF(OR(Z8="Red",AB8="Red",AE8="Red"),"Red",IF(OR(Z8="Amber",AB8="Amber",AE8="Amber"),"Amber","Green"))) | AG8: =IF(A8="","",COUNTIFS(Tasks!$A$2:$A$1001,A8,Tasks!$D$2:$D$1001,"<>Done",Tasks!$B$2:$B$1001,"<>")) | AH8: =IF(A8="","",COUNTIFS(Actions!$A$2:$A$501,A8,Actions!$H$2:$H$501,"<>Done",Actions!$C$2:$C$501,"<>")) | AI8: =IF(A8="","",COUNTIFS(RFIs!$A$2:$A$501,A8,RFIs!$G$2:$G$501,"Open")) | AJ8: =IF(A8="","",COUNTIFS(Defects!$A$2:$A$501,A8,Defects!$H$2:$H$501,"Open")) | AK8: =IF(A8="","","Schedule: "&IF(Y8="","no dates / not tracked",TEXT(Y8,"0%")&" of timeframe elapsed")&" | Budget: "&IF(AA8="","no approved budget or cash flow",TEXT(AA8,"0%")&" of budget forecast")&" | Risk: "&AC8&" critical, "&AD8&" high open")
Q9: =IF(A9="","",SUMIFS(Variations!$F$2:$F$501,Variations!$A$2:$A$501,A9,Variations!$H$2:$H$501,"Approved")) | R9: =IF(A9="","",IF(M9<>"",M9,IF(L9="","",L9+Q9))) | S9: =IF(A9="","",SUMIFS('Cash Flow'!$D$2:$D$2001,'Cash Flow'!$A$2:$A$2001,A9,'Cash Flow'!$C$2:$C$2001,"Actual")) | T9: =IF(A9="","",SUMIFS('Cash Flow'!$F$2:$F$2001,'Cash Flow'!$A$2:$A$2001,A9)) | U9: =IF(A9="","",IF(R9="","",R9-T9)) | V9: =IF(A9="","",SUMIFS('EOT Claims'!$L$2:$L$501,'EOT Claims'!$A$2:$A$501,A9)) | W9: =IF(A9="","",IF(O9="","",O9+V9)) | X9: =IF(A9="","",IF(O9="","",IF(AND(NOT(OR(D9="Project Completion",D9="Defects Liability",D9="Complete",D9="Cancelled")),O9<TODAY()),"Overdue",""))) | Y9: =IF(A9="","",IF(OR(N9="",W9=""),"",IF(W9<=N9,"",(TODAY()-N9)/(W9-N9)))) | Z9: =IF(A9="","",IF(OR(Y9="",OR(D9="Project Completion",D9="Defects Liability",D9="Complete",D9="Cancelled")),"Green",IF(Y9>1.15,"Red",IF(Y9>=0.95,"Amber","Green")))) | AA9: =IF(A9="","",IF(R9="","",IF(OR(R9<=0,COUNTIFS('Cash Flow'!$A$2:$A$2001,A9)=0),"",T9/R9))) | AB9: =IF(A9="","",IF(AA9="","Green",IF(AA9>1.15,"Red",IF(AA9>=0.95,"Amber","Green")))) | AC9: =IF(A9="","",COUNTIFS(Risks!$A$2:$A$501,A9,Risks!$B$2:$B$501,"Risk",Risks!$M$2:$M$501,"<>Closed",Risks!$O$2:$O$501,"Critical")) | AD9: =IF(A9="","",COUNTIFS(Risks!$A$2:$A$501,A9,Risks!$B$2:$B$501,"Risk",Risks!$M$2:$M$501,"<>Closed",Risks!$O$2:$O$501,"High")) | AE9: =IF(A9="","",IF(AC9>0,"Red",IF(AD9>0,"Amber","Green"))) | AF9: =IF(A9="","",IF(OR(Z9="Red",AB9="Red",AE9="Red"),"Red",IF(OR(Z9="Amber",AB9="Amber",AE9="Amber"),"Amber","Green"))) | AG9: =IF(A9="","",COUNTIFS(Tasks!$A$2:$A$1001,A9,Tasks!$D$2:$D$1001,"<>Done",Tasks!$B$2:$B$1001,"<>")) | AH9: =IF(A9="","",COUNTIFS(Actions!$A$2:$A$501,A9,Actions!$H$2:$H$501,"<>Done",Actions!$C$2:$C$501,"<>")) | AI9: =IF(A9="","",COUNTIFS(RFIs!$A$2:$A$501,A9,RFIs!$G$2:$G$501,"Open")) | AJ9: =IF(A9="","",COUNTIFS(Defects!$A$2:$A$501,A9,Defects!$H$2:$H$501,"Open")) | AK9: =IF(A9="","","Schedule: "&IF(Y9="","no dates / not tracked",TEXT(Y9,"0%")&" of timeframe elapsed")&" | Budget: "&IF(AA9="","no approved budget or cash flow",TEXT(AA9,"0%")&" of budget forecast")&" | Risk: "&AC9&" critical, "&AD9&" high open")
Q10: =IF(A10="","",SUMIFS(Variations!$F$2:$F$501,Variations!$A$2:$A$501,A10,Variations!$H$2:$H$501,"Approved")) | R10: =IF(A10="","",IF(M10<>"",M10,IF(L10="","",L10+Q10))) | S10: =IF(A10="","",SUMIFS('Cash Flow'!$D$2:$D$2001,'Cash Flow'!$A$2:$A$2001,A10,'Cash Flow'!$C$2:$C$2001,"Actual")) | T10: =IF(A10="","",SUMIFS('Cash Flow'!$F$2:$F$2001,'Cash Flow'!$A$2:$A$2001,A10)) | U10: =IF(A10="","",IF(R10="","",R10-T10)) | V10: =IF(A10="","",SUMIFS('EOT Claims'!$L$2:$L$501,'EOT Claims'!$A$2:$A$501,A10)) | W10: =IF(A10="","",IF(O10="","",O10+V10)) | X10: =IF(A10="","",IF(O10="","",IF(AND(NOT(OR(D10="Project Completion",D10="Defects Liability",D10="Complete",D10="Cancelled")),O10<TODAY()),"Overdue",""))) | Y10: =IF(A10="","",IF(OR(N10="",W10=""),"",IF(W10<=N10,"",(TODAY()-N10)/(W10-N10)))) | Z10: =IF(A10="","",IF(OR(Y10="",OR(D10="Project Completion",D10="Defects Liability",D10="Complete",D10="Cancelled")),"Green",IF(Y10>1.15,"Red",IF(Y10>=0.95,"Amber","Green")))) | AA10: =IF(A10="","",IF(R10="","",IF(OR(R10<=0,COUNTIFS('Cash Flow'!$A$2:$A$2001,A10)=0),"",T10/R10))) | AB10: =IF(A10="","",IF(AA10="","Green",IF(AA10>1.15,"Red",IF(AA10>=0.95,"Amber","Green")))) | AC10: =IF(A10="","",COUNTIFS(Risks!$A$2:$A$501,A10,Risks!$B$2:$B$501,"Risk",Risks!$M$2:$M$501,"<>Closed",Risks!$O$2:$O$501,"Critical")) | AD10: =IF(A10="","",COUNTIFS(Risks!$A$2:$A$501,A10,Risks!$B$2:$B$501,"Risk",Risks!$M$2:$M$501,"<>Closed",Risks!$O$2:$O$501,"High")) | AE10: =IF(A10="","",IF(AC10>0,"Red",IF(AD10>0,"Amber","Green"))) | AF10: =IF(A10="","",IF(OR(Z10="Red",AB10="Red",AE10="Red"),"Red",IF(OR(Z10="Amber",AB10="Amber",AE10="Amber"),"Amber","Green"))) | AG10: =IF(A10="","",COUNTIFS(Tasks!$A$2:$A$1001,A10,Tasks!$D$2:$D$1001,"<>Done",Tasks!$B$2:$B$1001,"<>")) | AH10: =IF(A10="","",COUNTIFS(Actions!$A$2:$A$501,A10,Actions!$H$2:$H$501,"<>Done",Actions!$C$2:$C$501,"<>")) | AI10: =IF(A10="","",COUNTIFS(RFIs!$A$2:$A$501,A10,RFIs!$G$2:$G$501,"Open")) | AJ10: =IF(A10="","",COUNTIFS(Defects!$A$2:$A$501,A10,Defects!$H$2:$H$501,"Open")) | AK10: =IF(A10="","","Schedule: "&IF(Y10="","no dates / not tracked",TEXT(Y10,"0%")&" of timeframe elapsed")&" | Budget: "&IF(AA10="","no approved budget or cash flow",TEXT(AA10,"0%")&" of budget forecast")&" | Risk: "&AC10&" critical, "&AD10&" high open")
Q11: =IF(A11="","",SUMIFS(Variations!$F$2:$F$501,Variations!$A$2:$A$501,A11,Variations!$H$2:$H$501,"Approved")) | R11: =IF(A11="","",IF(M11<>"",M11,IF(L11="","",L11+Q11))) | S11: =IF(A11="","",SUMIFS('Cash Flow'!$D$2:$D$2001,'Cash Flow'!$A$2:$A$2001,A11,'Cash Flow'!$C$2:$C$2001,"Actual")) | T11: =IF(A11="","",SUMIFS('Cash Flow'!$F$2:$F$2001,'Cash Flow'!$A$2:$A$2001,A11)) | U11: =IF(A11="","",IF(R11="","",R11-T11)) | V11: =IF(A11="","",SUMIFS('EOT Claims'!$L$2:$L$501,'EOT Claims'!$A$2:$A$501,A11)) | W11: =IF(A11="","",IF(O11="","",O11+V11)) | X11: =IF(A11="","",IF(O11="","",IF(AND(NOT(OR(D11="Project Completion",D11="Defects Liability",D11="Complete",D11="Cancelled")),O11<TODAY()),"Overdue",""))) | Y11: =IF(A11="","",IF(OR(N11="",W11=""),"",IF(W11<=N11,"",(TODAY()-N11)/(W11-N11)))) | Z11: =IF(A11="","",IF(OR(Y11="",OR(D11="Project Completion",D11="Defects Liability",D11="Complete",D11="Cancelled")),"Green",IF(Y11>1.15,"Red",IF(Y11>=0.95,"Amber","Green")))) | AA11: =IF(A11="","",IF(R11="","",IF(OR(R11<=0,COUNTIFS('Cash Flow'!$A$2:$A$2001,A11)=0),"",T11/R11))) | AB11: =IF(A11="","",IF(AA11="","Green",IF(AA11>1.15,"Red",IF(AA11>=0.95,"Amber","Green")))) | AC11: =IF(A11="","",COUNTIFS(Risks!$A$2:$A$501,A11,Risks!$B$2:$B$501,"Risk",Risks!$M$2:$M$501,"<>Closed",Risks!$O$2:$O$501,"Critical")) | AD11: =IF(A11="","",COUNTIFS(Risks!$A$2:$A$501,A11,Risks!$B$2:$B$501,"Risk",Risks!$M$2:$M$501,"<>Closed",Risks!$O$2:$O$501,"High")) | AE11: =IF(A11="","",IF(AC11>0,"Red",IF(AD11>0,"Amber","Green"))) | AF11: =IF(A11="","",IF(OR(Z11="Red",AB11="Red",AE11="Red"),"Red",IF(OR(Z11="Amber",AB11="Amber",AE11="Amber"),"Amber","Green"))) | AG11: =IF(A11="","",COUNTIFS(Tasks!$A$2:$A$1001,A11,Tasks!$D$2:$D$1001,"<>Done",Tasks!$B$2:$B$1001,"<>")) | AH11: =IF(A11="","",COUNTIFS(Actions!$A$2:$A$501,A11,Actions!$H$2:$H$501,"<>Done",Actions!$C$2:$C$501,"<>")) | AI11: =IF(A11="","",COUNTIFS(RFIs!$A$2:$A$501,A11,RFIs!$G$2:$G$501,"Open")) | AJ11: =IF(A11="","",COUNTIFS(Defects!$A$2:$A$501,A11,Defects!$H$2:$H$501,"Open")) | AK11: =IF(A11="","","Schedule: "&IF(Y11="","no dates / not tracked",TEXT(Y11,"0%")&" of timeframe elapsed")&" | Budget: "&IF(AA11="","no approved budget or cash flow",TEXT(AA11,"0%")&" of budget forecast")&" | Risk: "&AC11&" critical, "&AD11&" high open")
Q12: =IF(A12="","",SUMIFS(Variations!$F$2:$F$501,Variations!$A$2:$A$501,A12,Variations!$H$2:$H$501,"Approved")) | R12: =IF(A12="","",IF(M12<>"",M12,IF(L12="","",L12+Q12))) | S12: =IF(A12="","",SUMIFS('Cash Flow'!$D$2:$D$2001,'Cash Flow'!$A$2:$A$2001,A12,'Cash Flow'!$C$2:$C$2001,"Actual")) | T12: =IF(A12="","",SUMIFS('Cash Flow'!$F$2:$F$2001,'Cash Flow'!$A$2:$A$2001,A12)) | U12: =IF(A12="","",IF(R12="","",R12-T12)) | V12: =IF(A12="","",SUMIFS('EOT Claims'!$L$2:$L$501,'EOT Claims'!$A$2:$A$501,A12)) | W12: =IF(A12="","",IF(O12="","",O12+V12)) | X12: =IF(A12="","",IF(O12="","",IF(AND(NOT(OR(D12="Project Completion",D12="Defects Liability",D12="Complete",D12="Cancelled")),O12<TODAY()),"Overdue",""))) | Y12: =IF(A12="","",IF(OR(N12="",W12=""),"",IF(W12<=N12,"",(TODAY()-N12)/(W12-N12)))) | Z12: =IF(A12="","",IF(OR(Y12="",OR(D12="Project Completion",D12="Defects Liability",D12="Complete",D12="Cancelled")),"Green",IF(Y12>1.15,"Red",IF(Y12>=0.95,"Amber","Green")))) | AA12: =IF(A12="","",IF(R12="","",IF(OR(R12<=0,COUNTIFS('Cash Flow'!$A$2:$A$2001,A12)=0),"",T12/R12))) | AB12: =IF(A12="","",IF(AA12="","Green",IF(AA12>1.15,"Red",IF(AA12>=0.95,"Amber","Green")))) | AC12: =IF(A12="","",COUNTIFS(Risks!$A$2:$A$501,A12,Risks!$B$2:$B$501,"Risk",Risks!$M$2:$M$501,"<>Closed",Risks!$O$2:$O$501,"Critical")) | AD12: =IF(A12="","",COUNTIFS(Risks!$A$2:$A$501,A12,Risks!$B$2:$B$501,"Risk",Risks!$M$2:$M$501,"<>Closed",Risks!$O$2:$O$501,"High")) | AE12: =IF(A12="","",IF(AC12>0,"Red",IF(AD12>0,"Amber","Green"))) | AF12: =IF(A12="","",IF(OR(Z12="Red",AB12="Red",AE12="Red"),"Red",IF(OR(Z12="Amber",AB12="Amber",AE12="Amber"),"Amber","Green"))) | AG12: =IF(A12="","",COUNTIFS(Tasks!$A$2:$A$1001,A12,Tasks!$D$2:$D$1001,"<>Done",Tasks!$B$2:$B$1001,"<>")) | AH12: =IF(A12="","",COUNTIFS(Actions!$A$2:$A$501,A12,Actions!$H$2:$H$501,"<>Done",Actions!$C$2:$C$501,"<>")) | AI12: =IF(A12="","",COUNTIFS(RFIs!$A$2:$A$501,A12,RFIs!$G$2:$G$501,"Open")) | AJ12: =IF(A12="","",COUNTIFS(Defects!$A$2:$A$501,A12,Defects!$H$2:$H$501,"Open")) | AK12: =IF(A12="","","Schedule: "&IF(Y12="","no dates / not tracked",TEXT(Y12,"0%")&" of timeframe elapsed")&" | Budget: "&IF(AA12="","no approved budget or cash flow",TEXT(AA12,"0%")&" of budget forecast")&" | Risk: "&AC12&" critical, "&AD12&" high open")
Q13: =IF(A13="","",SUMIFS(Variations!$F$2:$F$501,Variations!$A$2:$A$501,A13,Variations!$H$2:$H$501,"Approved")) | R13: =IF(A13="","",IF(M13<>"",M13,IF(L13="","",L13+Q13))) | S13: =IF(A13="","",SUMIFS('Cash Flow'!$D$2:$D$2001,'Cash Flow'!$A$2:$A$2001,A13,'Cash Flow'!$C$2:$C$2001,"Actual")) | T13: =IF(A13="","",SUMIFS('Cash Flow'!$F$2:$F$2001,'Cash Flow'!$A$2:$A$2001,A13)) | U13: =IF(A13="","",IF(R13="","",R13-T13)) | V13: =IF(A13="","",SUMIFS('EOT Claims'!$L$2:$L$501,'EOT Claims'!$A$2:$A$501,A13)) | W13: =IF(A13="","",IF(O13="","",O13+V13)) | X13: =IF(A13="","",IF(O13="","",IF(AND(NOT(OR(D13="Project Completion",D13="Defects Liability",D13="Complete",D13="Cancelled")),O13<TODAY()),"Overdue",""))) | Y13: =IF(A13="","",IF(OR(N13="",W13=""),"",IF(W13<=N13,"",(TODAY()-N13)/(W13-N13)))) | Z13: =IF(A13="","",IF(OR(Y13="",OR(D13="Project Completion",D13="Defects Liability",D13="Complete",D13="Cancelled")),"Green",IF(Y13>1.15,"Red",IF(Y13>=0.95,"Amber","Green")))) | AA13: =IF(A13="","",IF(R13="","",IF(OR(R13<=0,COUNTIFS('Cash Flow'!$A$2:$A$2001,A13)=0),"",T13/R13))) | AB13: =IF(A13="","",IF(AA13="","Green",IF(AA13>1.15,"Red",IF(AA13>=0.95,"Amber","Green")))) | AC13: =IF(A13="","",COUNTIFS(Risks!$A$2:$A$501,A13,Risks!$B$2:$B$501,"Risk",Risks!$M$2:$M$501,"<>Closed",Risks!$O$2:$O$501,"Critical")) | AD13: =IF(A13="","",COUNTIFS(Risks!$A$2:$A$501,A13,Risks!$B$2:$B$501,"Risk",Risks!$M$2:$M$501,"<>Closed",Risks!$O$2:$O$501,"High")) | AE13: =IF(A13="","",IF(AC13>0,"Red",IF(AD13>0,"Amber","Green"))) | AF13: =IF(A13="","",IF(OR(Z13="Red",AB13="Red",AE13="Red"),"Red",IF(OR(Z13="Amber",AB13="Amber",AE13="Amber"),"Amber","Green"))) | AG13: =IF(A13="","",COUNTIFS(Tasks!$A$2:$A$1001,A13,Tasks!$D$2:$D$1001,"<>Done",Tasks!$B$2:$B$1001,"<>")) | AH13: =IF(A13="","",COUNTIFS(Actions!$A$2:$A$501,A13,Actions!$H$2:$H$501,"<>Done",Actions!$C$2:$C$501,"<>")) | AI13: =IF(A13="","",COUNTIFS(RFIs!$A$2:$A$501,A13,RFIs!$G$2:$G$501,"Open")) | AJ13: =IF(A13="","",COUNTIFS(Defects!$A$2:$A$501,A13,Defects!$H$2:$H$501,"Open")) | AK13: =IF(A13="","","Schedule: "&IF(Y13="","no dates / not tracked",TEXT(Y13,"0%")&" of timeframe elapsed")&" | Budget: "&IF(AA13="","no approved budget or cash flow",TEXT(AA13,"0%")&" of budget forecast")&" | Risk: "&AC13&" critical, "&AD13&" high open")
... Q101: =IF(A101="","",SUMIFS(Variations!$F$2:$F$501,Variations!$A$2:$A$501,A101,Variations!$H$2:$H$501,"Approved")) | R101: =IF(A101="","",IF(M101<>"",M101,IF(L101="","",L101+Q101))) | S101: =IF(A101="","",SUMIFS('Cash Flow'!$D$2:$D$2001,'Cash Flow'!$A$2:$A$2001,A101,'Cash Flow'!$C$2:$C$2001,"Actual")) | T101: =IF(A101="","",SUMIFS('Cash Flow'!$F$2:$F$2001,'Cash Flow'!$A$2:$A$2001,A101)) | U101: =IF(A101="","",IF(R101="","",R101-T101)) | V101: =IF(A101="","",SUMIFS('EOT Claims'!$L$2:$L$501,'EOT Claims'!$A$2:$A$501,A101)) | W101: =IF(A101="","",IF(O101="","",O101+V101)) | X101: =IF(A101="","",IF(O101="","",IF(AND(NOT(OR(D101="Project Completion",D101="Defects Liability",D101="Complete",D101="Cancelled")),O101<TODAY()),"Overdue",""))) | Y101: =IF(A101="","",IF(OR(N101="",W101=""),"",IF(W101<=N101,"",(TODAY()-N101)/(W101-N101)))) | Z101: =IF(A101="","",IF(OR(Y101="",OR(D101="Project Completion",D101="Defects Liability",D101="Complete",D101="Cancelled")),"Green",IF(Y101>1.15,"Red",IF(Y101>=0.95,"Amber","Green")))) | AA101: =IF(A101="","",IF(R101="","",IF(OR(R101<=0,COUNTIFS('Cash Flow'!$A$2:$A$2001,A101)=0),"",T101/R101))) | AB101: =IF(A101="","",IF(AA101="","Green",IF(AA101>1.15,"Red",IF(AA101>=0.95,"Amber","Green")))) | AC101: =IF(A101="","",COUNTIFS(Risks!$A$2:$A$501,A101,Risks!$B$2:$B$501,"Risk",Risks!$M$2:$M$501,"<>Closed",Risks!$O$2:$O$501,"Critical")) | AD101: =IF(A101="","",COUNTIFS(Risks!$A$2:$A$501,A101,Risks!$B$2:$B$501,"Risk",Risks!$M$2:$M$501,"<>Closed",Risks!$O$2:$O$501,"High")) | AE101: =IF(A101="","",IF(AC101>0,"Red",IF(AD101>0,"Amber","Green"))) | AF101: =IF(A101="","",IF(OR(Z101="Red",AB101="Red",AE101="Red"),"Red",IF(OR(Z101="Amber",AB101="Amber",AE101="Amber"),"Amber","Green"))) | AG101: =IF(A101="","",COUNTIFS(Tasks!$A$2:$A$1001,A101,Tasks!$D$2:$D$1001,"<>Done",Tasks!$B$2:$B$1001,"<>")) | AH101: =IF(A101="","",COUNTIFS(Actions!$A$2:$A$501,A101,Actions!$H$2:$H$501,"<>Done",Actions!$C$2:$C$501,"<>")) | AI101: =IF(A101="","",COUNTIFS(RFIs!$A$2:$A$501,A101,RFIs!$G$2:$G$501,"Open")) | AJ101: =IF(A101="","",COUNTIFS(Defects!$A$2:$A$501,A101,Defects!$H$2:$H$501,"Open")) | AK101: =IF(A101="","","Schedule: "&IF(Y101="","no dates / not tracked",TEXT(Y101,"0%")&" of timeframe elapsed")&" | Budget: "&IF(AA101="","no approved budget or cash flow",TEXT(AA101,"0%")&" of budget forecast")&" | Risk: "&AC101&" critical, "&AD101&" high open")

Sheet Tasks
A1: Project | B1: Title | C1: Description | D1: Status | E1: Due Date | F1: Recurrence | G1: Completed Date | H1: Bucket | I1: Upcoming Rank
H2: =IF(B2="","",IF(OR(D2="Done"),"Done",IF(E2="","No Due Date",IF(E2<TODAY(),"Overdue",IF(E2=TODAY(),"Due Today",IF(E2<TODAY()+7,"Due This Week","Later")))))) | I2: =IF(AND(B2<>"",D2<>"Done",E2<>""),E2+ROW()/100000,"")
H3: =IF(B3="","",IF(OR(D3="Done"),"Done",IF(E3="","No Due Date",IF(E3<TODAY(),"Overdue",IF(E3=TODAY(),"Due Today",IF(E3<TODAY()+7,"Due This Week","Later")))))) | I3: =IF(AND(B3<>"",D3<>"Done",E3<>""),E3+ROW()/100000,"")
H4: =IF(B4="","",IF(OR(D4="Done"),"Done",IF(E4="","No Due Date",IF(E4<TODAY(),"Overdue",IF(E4=TODAY(),"Due Today",IF(E4<TODAY()+7,"Due This Week","Later")))))) | I4: =IF(AND(B4<>"",D4<>"Done",E4<>""),E4+ROW()/100000,"")
H5: =IF(B5="","",IF(OR(D5="Done"),"Done",IF(E5="","No Due Date",IF(E5<TODAY(),"Overdue",IF(E5=TODAY(),"Due Today",IF(E5<TODAY()+7,"Due This Week","Later")))))) | I5: =IF(AND(B5<>"",D5<>"Done",E5<>""),E5+ROW()/100000,"")
H6: =IF(B6="","",IF(OR(D6="Done"),"Done",IF(E6="","No Due Date",IF(E6<TODAY(),"Overdue",IF(E6=TODAY(),"Due Today",IF(E6<TODAY()+7,"Due This Week","Later")))))) | I6: =IF(AND(B6<>"",D6<>"Done",E6<>""),E6+ROW()/100000,"")
H7: =IF(B7="","",IF(OR(D7="Done"),"Done",IF(E7="","No Due Date",IF(E7<TODAY(),"Overdue",IF(E7=TODAY(),"Due Today",IF(E7<TODAY()+7,"Due This Week","Later")))))) | I7: =IF(AND(B7<>"",D7<>"Done",E7<>""),E7+ROW()/100000,"")
H8: =IF(B8="","",IF(OR(D8="Done"),"Done",IF(E8="","No Due Date",IF(E8<TODAY(),"Overdue",IF(E8=TODAY(),"Due Today",IF(E8<TODAY()+7,"Due This Week","Later")))))) | I8: =IF(AND(B8<>"",D8<>"Done",E8<>""),E8+ROW()/100000,"")
H9: =IF(B9="","",IF(OR(D9="Done"),"Done",IF(E9="","No Due Date",IF(E9<TODAY(),"Overdue",IF(E9=TODAY(),"Due Today",IF(E9<TODAY()+7,"Due This Week","Later")))))) | I9: =IF(AND(B9<>"",D9<>"Done",E9<>""),E9+ROW()/100000,"")
H10: =IF(B10="","",IF(OR(D10="Done"),"Done",IF(E10="","No Due Date",IF(E10<TODAY(),"Overdue",IF(E10=TODAY(),"Due Today",IF(E10<TODAY()+7,"Due This Week","Later")))))) | I10: =IF(AND(B10<>"",D10<>"Done",E10<>""),E10+ROW()/100000,"")
H11: =IF(B11="","",IF(OR(D11="Done"),"Done",IF(E11="","No Due Date",IF(E11<TODAY(),"Overdue",IF(E11=TODAY(),"Due Today",IF(E11<TODAY()+7,"Due This Week","Later")))))) | I11: =IF(AND(B11<>"",D11<>"Done",E11<>""),E11+ROW()/100000,"")
H12: =IF(B12="","",IF(OR(D12="Done"),"Done",IF(E12="","No Due Date",IF(E12<TODAY(),"Overdue",IF(E12=TODAY(),"Due Today",IF(E12<TODAY()+7,"Due This Week","Later")))))) | I12: =IF(AND(B12<>"",D12<>"Done",E12<>""),E12+ROW()/100000,"")
H13: =IF(B13="","",IF(OR(D13="Done"),"Done",IF(E13="","No Due Date",IF(E13<TODAY(),"Overdue",IF(E13=TODAY(),"Due Today",IF(E13<TODAY()+7,"Due This Week","Later")))))) | I13: =IF(AND(B13<>"",D13<>"Done",E13<>""),E13+ROW()/100000,"")
... H1001: =IF(B1001="","",IF(OR(D1001="Done"),"Done",IF(E1001="","No Due Date",IF(E1001<TODAY(),"Overdue",IF(E1001=TODAY(),"Due Today",IF(E1001<TODAY()+7,"Due This Week","Later")))))) | I1001: =IF(AND(B1001<>"",D1001<>"Done",E1001<>""),E1001+ROW()/100000,"")

Sheet Actions
A1: Project | B1: Type | C1: Title | D1: Description | E1: Category | F1: Owner | G1: Due Date | H1: Status | I1: Date Raised | J1: Date Closed | K1: Meeting | L1: Notes | M1: Bucket | N1: Upcoming Rank | O1: Summary Seq
M2: =IF(C2="","",IF(OR(H2="Done"),"Done",IF(G2="","No Due Date",IF(G2<TODAY(),"Overdue",IF(G2=TODAY(),"Due Today",IF(G2<TODAY()+7,"Due This Week","Later")))))) | N2: =IF(AND(C2<>"",H2<>"Done",G2<>""),G2+ROW()/100000,"") | O2: =IF(AND(A2<>"",A2='Project Summary'!$C$3,H2<>"Done",C2<>""),COUNTIFS($A$2:$A2,'Project Summary'!$C$3,$H$2:$H2,"<>Done",$C$2:$C2,"<>"),"")
M3: =IF(C3="","",IF(OR(H3="Done"),"Done",IF(G3="","No Due Date",IF(G3<TODAY(),"Overdue",IF(G3=TODAY(),"Due Today",IF(G3<TODAY()+7,"Due This Week","Later")))))) | N3: =IF(AND(C3<>"",H3<>"Done",G3<>""),G3+ROW()/100000,"") | O3: =IF(AND(A3<>"",A3='Project Summary'!$C$3,H3<>"Done",C3<>""),COUNTIFS($A$2:$A3,'Project Summary'!$C$3,$H$2:$H3,"<>Done",$C$2:$C3,"<>"),"")
M4: =IF(C4="","",IF(OR(H4="Done"),"Done",IF(G4="","No Due Date",IF(G4<TODAY(),"Overdue",IF(G4=TODAY(),"Due Today",IF(G4<TODAY()+7,"Due This Week","Later")))))) | N4: =IF(AND(C4<>"",H4<>"Done",G4<>""),G4+ROW()/100000,"") | O4: =IF(AND(A4<>"",A4='Project Summary'!$C$3,H4<>"Done",C4<>""),COUNTIFS($A$2:$A4,'Project Summary'!$C$3,$H$2:$H4,"<>Done",$C$2:$C4,"<>"),"")
M5: =IF(C5="","",IF(OR(H5="Done"),"Done",IF(G5="","No Due Date",IF(G5<TODAY(),"Overdue",IF(G5=TODAY(),"Due Today",IF(G5<TODAY()+7,"Due This Week","Later")))))) | N5: =IF(AND(C5<>"",H5<>"Done",G5<>""),G5+ROW()/100000,"") | O5: =IF(AND(A5<>"",A5='Project Summary'!$C$3,H5<>"Done",C5<>""),COUNTIFS($A$2:$A5,'Project Summary'!$C$3,$H$2:$H5,"<>Done",$C$2:$C5,"<>"),"")
M6: =IF(C6="","",IF(OR(H6="Done"),"Done",IF(G6="","No Due Date",IF(G6<TODAY(),"Overdue",IF(G6=TODAY(),"Due Today",IF(G6<TODAY()+7,"Due This Week","Later")))))) | N6: =IF(AND(C6<>"",H6<>"Done",G6<>""),G6+ROW()/100000,"") | O6: =IF(AND(A6<>"",A6='Project Summary'!$C$3,H6<>"Done",C6<>""),COUNTIFS($A$2:$A6,'Project Summary'!$C$3,$H$2:$H6,"<>Done",$C$2:$C6,"<>"),"")
M7: =IF(C7="","",IF(OR(H7="Done"),"Done",IF(G7="","No Due Date",IF(G7<TODAY(),"Overdue",IF(G7=TODAY(),"Due Today",IF(G7<TODAY()+7,"Due This Week","Later")))))) | N7: =IF(AND(C7<>"",H7<>"Done",G7<>""),G7+ROW()/100000,"") | O7: =IF(AND(A7<>"",A7='Project Summary'!$C$3,H7<>"Done",C7<>""),COUNTIFS($A$2:$A7,'Project Summary'!$C$3,$H$2:$H7,"<>Done",$C$2:$C7,"<>"),"")
M8: =IF(C8="","",IF(OR(H8="Done"),"Done",IF(G8="","No Due Date",IF(G8<TODAY(),"Overdue",IF(G8=TODAY(),"Due Today",IF(G8<TODAY()+7,"Due This Week","Later")))))) | N8: =IF(AND(C8<>"",H8<>"Done",G8<>""),G8+ROW()/100000,"") | O8: =IF(AND(A8<>"",A8='Project Summary'!$C$3,H8<>"Done",C8<>""),COUNTIFS($A$2:$A8,'Project Summary'!$C$3,$H$2:$H8,"<>Done",$C$2:$C8,"<>"),"")
M9: =IF(C9="","",IF(OR(H9="Done"),"Done",IF(G9="","No Due Date",IF(G9<TODAY(),"Overdue",IF(G9=TODAY(),"Due Today",IF(G9<TODAY()+7,"Due This Week","Later")))))) | N9: =IF(AND(C9<>"",H9<>"Done",G9<>""),G9+ROW()/100000,"") | O9: =IF(AND(A9<>"",A9='Project Summary'!$C$3,H9<>"Done",C9<>""),COUNTIFS($A$2:$A9,'Project Summary'!$C$3,$H$2:$H9,"<>Done",$C$2:$C9,"<>"),"")
M10: =IF(C10="","",IF(OR(H10="Done"),"Done",IF(G10="","No Due Date",IF(G10<TODAY(),"Overdue",IF(G10=TODAY(),"Due Today",IF(G10<TODAY()+7,"Due This Week","Later")))))) | N10: =IF(AND(C10<>"",H10<>"Done",G10<>""),G10+ROW()/100000,"") | O10: =IF(AND(A10<>"",A10='Project Summary'!$C$3,H10<>"Done",C10<>""),COUNTIFS($A$2:$A10,'Project Summary'!$C$3,$H$2:$H10,"<>Done",$C$2:$C10,"<>"),"")
M11: =IF(C11="","",IF(OR(H11="Done"),"Done",IF(G11="","No Due Date",IF(G11<TODAY(),"Overdue",IF(G11=TODAY(),"Due Today",IF(G11<TODAY()+7,"Due This Week","Later")))))) | N11: =IF(AND(C11<>"",H11<>"Done",G11<>""),G11+ROW()/100000,"") | O11: =IF(AND(A11<>"",A11='Project Summary'!$C$3,H11<>"Done",C11<>""),COUNTIFS($A$2:$A11,'Project Summary'!$C$3,$H$2:$H11,"<>Done",$C$2:$C11,"<>"),"")
M12: =IF(C12="","",IF(OR(H12="Done"),"Done",IF(G12="","No Due Date",IF(G12<TODAY(),"Overdue",IF(G12=TODAY(),"Due Today",IF(G12<TODAY()+7,"Due This Week","Later")))))) | N12: =IF(AND(C12<>"",H12<>"Done",G12<>""),G12+ROW()/100000,"") | O12: =IF(AND(A12<>"",A12='Project Summary'!$C$3,H12<>"Done",C12<>""),COUNTIFS($A$2:$A12,'Project Summary'!$C$3,$H$2:$H12,"<>Done",$C$2:$C12,"<>"),"")
M13: =IF(C13="","",IF(OR(H13="Done"),"Done",IF(G13="","No Due Date",IF(G13<TODAY(),"Overdue",IF(G13=TODAY(),"Due Today",IF(G13<TODAY()+7,"Due This Week","Later")))))) | N13: =IF(AND(C13<>"",H13<>"Done",G13<>""),G13+ROW()/100000,"") | O13: =IF(AND(A13<>"",A13='Project Summary'!$C$3,H13<>"Done",C13<>""),COUNTIFS($A$2:$A13,'Project Summary'!$C$3,$H$2:$H13,"<>Done",$C$2:$C13,"<>"),"")
... M501: =IF(C501="","",IF(OR(H501="Done"),"Done",IF(G501="","No Due Date",IF(G501<TODAY(),"Overdue",IF(G501=TODAY(),"Due Today",IF(G501<TODAY()+7,"Due This Week","Later")))))) | N501: =IF(AND(C501<>"",H501<>"Done",G501<>""),G501+ROW()/100000,"") | O501: =IF(AND(A501<>"",A501='Project Summary'!$C$3,H501<>"Done",C501<>""),COUNTIFS($A$2:$A501,'Project Summary'!$C$3,$H$2:$H501,"<>Done",$C$2:$C501,"<>"),"")

Sheet Risks
A1: Project | B1: Type | C1: Title | D1: Description | E1: Category | F1: Inherent Likelihood | G1: Inherent Consequence | H1: Residual Likelihood | I1: Residual Consequence | J1: Mitigation | K1: Owner | L1: Due Date | M1: Status | N1: Inherent Score | O1: Inherent Band | P1: Residual Score | Q1: Residual Band | R1: Overdue | S1: Top Rank | T1: Summary Rank
N2: =IF(OR(C2="",F2="",G2=""),"",MATCH(F2,lst_Likelihood,0)*MATCH(G2,lst_Consequence,0)) | O2: =IF(N2="","",IF(N2>=16,"Critical",IF(N2>=10,"High",IF(N2>=5,"Medium","Low")))) | P2: =IF(OR(C2="",H2="",I2=""),"",MATCH(H2,lst_Likelihood,0)*MATCH(I2,lst_Consequence,0)) | Q2: =IF(P2="","",IF(P2>=16,"Critical",IF(P2>=10,"High",IF(P2>=5,"Medium","Low")))) | R2: =IF(AND(C2<>"",M2<>"Closed",L2<>"",L2<TODAY()),"Overdue","") | S2: =IF(AND(N2<>"",B2="Risk",M2<>"Closed"),N2+(1-ROW()/100000),"") | T2: =IF(AND(S2<>"",A2='Project Summary'!$C$3),S2,"")
N3: =IF(OR(C3="",F3="",G3=""),"",MATCH(F3,lst_Likelihood,0)*MATCH(G3,lst_Consequence,0)) | O3: =IF(N3="","",IF(N3>=16,"Critical",IF(N3>=10,"High",IF(N3>=5,"Medium","Low")))) | P3: =IF(OR(C3="",H3="",I3=""),"",MATCH(H3,lst_Likelihood,0)*MATCH(I3,lst_Consequence,0)) | Q3: =IF(P3="","",IF(P3>=16,"Critical",IF(P3>=10,"High",IF(P3>=5,"Medium","Low")))) | R3: =IF(AND(C3<>"",M3<>"Closed",L3<>"",L3<TODAY()),"Overdue","") | S3: =IF(AND(N3<>"",B3="Risk",M3<>"Closed"),N3+(1-ROW()/100000),"") | T3: =IF(AND(S3<>"",A3='Project Summary'!$C$3),S3,"")
N4: =IF(OR(C4="",F4="",G4=""),"",MATCH(F4,lst_Likelihood,0)*MATCH(G4,lst_Consequence,0)) | O4: =IF(N4="","",IF(N4>=16,"Critical",IF(N4>=10,"High",IF(N4>=5,"Medium","Low")))) | P4: =IF(OR(C4="",H4="",I4=""),"",MATCH(H4,lst_Likelihood,0)*MATCH(I4,lst_Consequence,0)) | Q4: =IF(P4="","",IF(P4>=16,"Critical",IF(P4>=10,"High",IF(P4>=5,"Medium","Low")))) | R4: =IF(AND(C4<>"",M4<>"Closed",L4<>"",L4<TODAY()),"Overdue","") | S4: =IF(AND(N4<>"",B4="Risk",M4<>"Closed"),N4+(1-ROW()/100000),"") | T4: =IF(AND(S4<>"",A4='Project Summary'!$C$3),S4,"")
N5: =IF(OR(C5="",F5="",G5=""),"",MATCH(F5,lst_Likelihood,0)*MATCH(G5,lst_Consequence,0)) | O5: =IF(N5="","",IF(N5>=16,"Critical",IF(N5>=10,"High",IF(N5>=5,"Medium","Low")))) | P5: =IF(OR(C5="",H5="",I5=""),"",MATCH(H5,lst_Likelihood,0)*MATCH(I5,lst_Consequence,0)) | Q5: =IF(P5="","",IF(P5>=16,"Critical",IF(P5>=10,"High",IF(P5>=5,"Medium","Low")))) | R5: =IF(AND(C5<>"",M5<>"Closed",L5<>"",L5<TODAY()),"Overdue","") | S5: =IF(AND(N5<>"",B5="Risk",M5<>"Closed"),N5+(1-ROW()/100000),"") | T5: =IF(AND(S5<>"",A5='Project Summary'!$C$3),S5,"")
N6: =IF(OR(C6="",F6="",G6=""),"",MATCH(F6,lst_Likelihood,0)*MATCH(G6,lst_Consequence,0)) | O6: =IF(N6="","",IF(N6>=16,"Critical",IF(N6>=10,"High",IF(N6>=5,"Medium","Low")))) | P6: =IF(OR(C6="",H6="",I6=""),"",MATCH(H6,lst_Likelihood,0)*MATCH(I6,lst_Consequence,0)) | Q6: =IF(P6="","",IF(P6>=16,"Critical",IF(P6>=10,"High",IF(P6>=5,"Medium","Low")))) | R6: =IF(AND(C6<>"",M6<>"Closed",L6<>"",L6<TODAY()),"Overdue","") | S6: =IF(AND(N6<>"",B6="Risk",M6<>"Closed"),N6+(1-ROW()/100000),"") | T6: =IF(AND(S6<>"",A6='Project Summary'!$C$3),S6,"")
N7: =IF(OR(C7="",F7="",G7=""),"",MATCH(F7,lst_Likelihood,0)*MATCH(G7,lst_Consequence,0)) | O7: =IF(N7="","",IF(N7>=16,"Critical",IF(N7>=10,"High",IF(N7>=5,"Medium","Low")))) | P7: =IF(OR(C7="",H7="",I7=""),"",MATCH(H7,lst_Likelihood,0)*MATCH(I7,lst_Consequence,0)) | Q7: =IF(P7="","",IF(P7>=16,"Critical",IF(P7>=10,"High",IF(P7>=5,"Medium","Low")))) | R7: =IF(AND(C7<>"",M7<>"Closed",L7<>"",L7<TODAY()),"Overdue","") | S7: =IF(AND(N7<>"",B7="Risk",M7<>"Closed"),N7+(1-ROW()/100000),"") | T7: =IF(AND(S7<>"",A7='Project Summary'!$C$3),S7,"")
N8: =IF(OR(C8="",F8="",G8=""),"",MATCH(F8,lst_Likelihood,0)*MATCH(G8,lst_Consequence,0)) | O8: =IF(N8="","",IF(N8>=16,"Critical",IF(N8>=10,"High",IF(N8>=5,"Medium","Low")))) | P8: =IF(OR(C8="",H8="",I8=""),"",MATCH(H8,lst_Likelihood,0)*MATCH(I8,lst_Consequence,0)) | Q8: =IF(P8="","",IF(P8>=16,"Critical",IF(P8>=10,"High",IF(P8>=5,"Medium","Low")))) | R8: =IF(AND(C8<>"",M8<>"Closed",L8<>"",L8<TODAY()),"Overdue","") | S8: =IF(AND(N8<>"",B8="Risk",M8<>"Closed"),N8+(1-ROW()/100000),"") | T8: =IF(AND(S8<>"",A8='Project Summary'!$C$3),S8,"")
N9: =IF(OR(C9="",F9="",G9=""),"",MATCH(F9,lst_Likelihood,0)*MATCH(G9,lst_Consequence,0)) | O9: =IF(N9="","",IF(N9>=16,"Critical",IF(N9>=10,"High",IF(N9>=5,"Medium","Low")))) | P9: =IF(OR(C9="",H9="",I9=""),"",MATCH(H9,lst_Likelihood,0)*MATCH(I9,lst_Consequence,0)) | Q9: =IF(P9="","",IF(P9>=16,"Critical",IF(P9>=10,"High",IF(P9>=5,"Medium","Low")))) | R9: =IF(AND(C9<>"",M9<>"Closed",L9<>"",L9<TODAY()),"Overdue","") | S9: =IF(AND(N9<>"",B9="Risk",M9<>"Closed"),N9+(1-ROW()/100000),"") | T9: =IF(AND(S9<>"",A9='Project Summary'!$C$3),S9,"")
N10: =IF(OR(C10="",F10="",G10=""),"",MATCH(F10,lst_Likelihood,0)*MATCH(G10,lst_Consequence,0)) | O10: =IF(N10="","",IF(N10>=16,"Critical",IF(N10>=10,"High",IF(N10>=5,"Medium","Low")))) | P10: =IF(OR(C10="",H10="",I10=""),"",MATCH(H10,lst_Likelihood,0)*MATCH(I10,lst_Consequence,0)) | Q10: =IF(P10="","",IF(P10>=16,"Critical",IF(P10>=10,"High",IF(P10>=5,"Medium","Low")))) | R10: =IF(AND(C10<>"",M10<>"Closed",L10<>"",L10<TODAY()),"Overdue","") | S10: =IF(AND(N10<>"",B10="Risk",M10<>"Closed"),N10+(1-ROW()/100000),"") | T10: =IF(AND(S10<>"",A10='Project Summary'!$C$3),S10,"")
N11: =IF(OR(C11="",F11="",G11=""),"",MATCH(F11,lst_Likelihood,0)*MATCH(G11,lst_Consequence,0)) | O11: =IF(N11="","",IF(N11>=16,"Critical",IF(N11>=10,"High",IF(N11>=5,"Medium","Low")))) | P11: =IF(OR(C11="",H11="",I11=""),"",MATCH(H11,lst_Likelihood,0)*MATCH(I11,lst_Consequence,0)) | Q11: =IF(P11="","",IF(P11>=16,"Critical",IF(P11>=10,"High",IF(P11>=5,"Medium","Low")))) | R11: =IF(AND(C11<>"",M11<>"Closed",L11<>"",L11<TODAY()),"Overdue","") | S11: =IF(AND(N11<>"",B11="Risk",M11<>"Closed"),N11+(1-ROW()/100000),"") | T11: =IF(AND(S11<>"",A11='Project Summary'!$C$3),S11,"")
N12: =IF(OR(C12="",F12="",G12=""),"",MATCH(F12,lst_Likelihood,0)*MATCH(G12,lst_Consequence,0)) | O12: =IF(N12="","",IF(N12>=16,"Critical",IF(N12>=10,"High",IF(N12>=5,"Medium","Low")))) | P12: =IF(OR(C12="",H12="",I12=""),"",MATCH(H12,lst_Likelihood,0)*MATCH(I12,lst_Consequence,0)) | Q12: =IF(P12="","",IF(P12>=16,"Critical",IF(P12>=10,"High",IF(P12>=5,"Medium","Low")))) | R12: =IF(AND(C12<>"",M12<>"Closed",L12<>"",L12<TODAY()),"Overdue","") | S12: =IF(AND(N12<>"",B12="Risk",M12<>"Closed"),N12+(1-ROW()/100000),"") | T12: =IF(AND(S12<>"",A12='Project Summary'!$C$3),S12,"")
N13: =IF(OR(C13="",F13="",G13=""),"",MATCH(F13,lst_Likelihood,0)*MATCH(G13,lst_Consequence,0)) | O13: =IF(N13="","",IF(N13>=16,"Critical",IF(N13>=10,"High",IF(N13>=5,"Medium","Low")))) | P13: =IF(OR(C13="",H13="",I13=""),"",MATCH(H13,lst_Likelihood,0)*MATCH(I13,lst_Consequence,0)) | Q13: =IF(P13="","",IF(P13>=16,"Critical",IF(P13>=10,"High",IF(P13>=5,"Medium","Low")))) | R13: =IF(AND(C13<>"",M13<>"Closed",L13<>"",L13<TODAY()),"Overdue","") | S13: =IF(AND(N13<>"",B13="Risk",M13<>"Closed"),N13+(1-ROW()/100000),"") | T13: =IF(AND(S13<>"",A13='Project Summary'!$C$3),S13,"")
... N501: =IF(OR(C501="",F501="",G501=""),"",MATCH(F501,lst_Likelihood,0)*MATCH(G501,lst_Consequence,0)) | O501: =IF(N501="","",IF(N501>=16,"Critical",IF(N501>=10,"High",IF(N501>=5,"Medium","Low")))) | P501: =IF(OR(C501="",H501="",I501=""),"",MATCH(H501,lst_Likelihood,0)*MATCH(I501,lst_Consequence,0)) | Q501: =IF(P501="","",IF(P501>=16,"Critical",IF(P501>=10,"High",IF(P501>=5,"Medium","Low")))) | R501: =IF(AND(C501<>"",M501<>"Closed",L501<>"",L501<TODAY()),"Overdue","") | S501: =IF(AND(N501<>"",B501="Risk",M501<>"Closed"),N501+(1-ROW()/100000),"") | T501: =IF(AND(S501<>"",A501='Project Summary'!$C$3),S501,"")

Sheet RFIs
A1: Project | B1: RFI Number | C1: Subject | D1: Question | E1: Response | F1: Raised To | G1: Status | H1: Date Raised | I1: Date Required | J1: Date Answered | K1: Notes | L1: Flag
L2: =IF(OR(B2="",G2<>"Open",I2=""),"",IF(I2<TODAY(),"Overdue",IF(I2<=TODAY()+7,"Due Soon","")))
L3: =IF(OR(B3="",G3<>"Open",I3=""),"",IF(I3<TODAY(),"Overdue",IF(I3<=TODAY()+7,"Due Soon","")))
L4: =IF(OR(B4="",G4<>"Open",I4=""),"",IF(I4<TODAY(),"Overdue",IF(I4<=TODAY()+7,"Due Soon","")))
L5: =IF(OR(B5="",G5<>"Open",I5=""),"",IF(I5<TODAY(),"Overdue",IF(I5<=TODAY()+7,"Due Soon","")))
L6: =IF(OR(B6="",G6<>"Open",I6=""),"",IF(I6<TODAY(),"Overdue",IF(I6<=TODAY()+7,"Due Soon","")))
L7: =IF(OR(B7="",G7<>"Open",I7=""),"",IF(I7<TODAY(),"Overdue",IF(I7<=TODAY()+7,"Due Soon","")))
L8: =IF(OR(B8="",G8<>"Open",I8=""),"",IF(I8<TODAY(),"Overdue",IF(I8<=TODAY()+7,"Due Soon","")))
L9: =IF(OR(B9="",G9<>"Open",I9=""),"",IF(I9<TODAY(),"Overdue",IF(I9<=TODAY()+7,"Due Soon","")))
L10: =IF(OR(B10="",G10<>"Open",I10=""),"",IF(I10<TODAY(),"Overdue",IF(I10<=TODAY()+7,"Due Soon","")))
L11: =IF(OR(B11="",G11<>"Open",I11=""),"",IF(I11<TODAY(),"Overdue",IF(I11<=TODAY()+7,"Due Soon","")))
L12: =IF(OR(B12="",G12<>"Open",I12=""),"",IF(I12<TODAY(),"Overdue",IF(I12<=TODAY()+7,"Due Soon","")))
L13: =IF(OR(B13="",G13<>"Open",I13=""),"",IF(I13<TODAY(),"Overdue",IF(I13<=TODAY()+7,"Due Soon","")))
... L501: =IF(OR(B501="",G501<>"Open",I501=""),"",IF(I501<TODAY(),"Overdue",IF(I501<=TODAY()+7,"Due Soon","")))

Sheet Defects
A1: Project | B1: Title | C1: Description | D1: Location | E1: Category | F1: Assigned To | G1: Due Date | H1: Status | I1: Date Raised | J1: Date Closed | K1: Retention Held | L1: Notes | M1: Flag
M2: =IF(OR(B2="",H2<>"Open",G2=""),"",IF(G2<TODAY(),"Overdue",""))
M3: =IF(OR(B3="",H3<>"Open",G3=""),"",IF(G3<TODAY(),"Overdue",""))
M4: =IF(OR(B4="",H4<>"Open",G4=""),"",IF(G4<TODAY(),"Overdue",""))
M5: =IF(OR(B5="",H5<>"Open",G5=""),"",IF(G5<TODAY(),"Overdue",""))
M6: =IF(OR(B6="",H6<>"Open",G6=""),"",IF(G6<TODAY(),"Overdue",""))
M7: =IF(OR(B7="",H7<>"Open",G7=""),"",IF(G7<TODAY(),"Overdue",""))
M8: =IF(OR(B8="",H8<>"Open",G8=""),"",IF(G8<TODAY(),"Overdue",""))
M9: =IF(OR(B9="",H9<>"Open",G9=""),"",IF(G9<TODAY(),"Overdue",""))
M10: =IF(OR(B10="",H10<>"Open",G10=""),"",IF(G10<TODAY(),"Overdue",""))
M11: =IF(OR(B11="",H11<>"Open",G11=""),"",IF(G11<TODAY(),"Overdue",""))
M12: =IF(OR(B12="",H12<>"Open",G12=""),"",IF(G12<TODAY(),"Overdue",""))
M13: =IF(OR(B13="",H13<>"Open",G13=""),"",IF(G13<TODAY(),"Overdue",""))
... M501: =IF(OR(B501="",H501<>"Open",G501=""),"",IF(G501<TODAY(),"Overdue",""))

Sheet Variations
A1: Project | B1: Reference | C1: Title | D1: Description | E1: Category | F1: Cost Impact | G1: Time Impact Days | H1: Status | I1: Date Raised | J1: Date Decided | K1: Notes | L1: Summary Seq
L2: =IF(AND(A2<>"",A2='Project Summary'!$C$3,C2<>""),COUNTIFS($A$2:$A2,'Project Summary'!$C$3,$C$2:$C2,"<>"),"")
L3: =IF(AND(A3<>"",A3='Project Summary'!$C$3,C3<>""),COUNTIFS($A$2:$A3,'Project Summary'!$C$3,$C$2:$C3,"<>"),"")
L4: =IF(AND(A4<>"",A4='Project Summary'!$C$3,C4<>""),COUNTIFS($A$2:$A4,'Project Summary'!$C$3,$C$2:$C4,"<>"),"")
L5: =IF(AND(A5<>"",A5='Project Summary'!$C$3,C5<>""),COUNTIFS($A$2:$A5,'Project Summary'!$C$3,$C$2:$C5,"<>"),"")
L6: =IF(AND(A6<>"",A6='Project Summary'!$C$3,C6<>""),COUNTIFS($A$2:$A6,'Project Summary'!$C$3,$C$2:$C6,"<>"),"")
L7: =IF(AND(A7<>"",A7='Project Summary'!$C$3,C7<>""),COUNTIFS($A$2:$A7,'Project Summary'!$C$3,$C$2:$C7,"<>"),"")
L8: =IF(AND(A8<>"",A8='Project Summary'!$C$3,C8<>""),COUNTIFS($A$2:$A8,'Project Summary'!$C$3,$C$2:$C8,"<>"),"")
L9: =IF(AND(A9<>"",A9='Project Summary'!$C$3,C9<>""),COUNTIFS($A$2:$A9,'Project Summary'!$C$3,$C$2:$C9,"<>"),"")
L10: =IF(AND(A10<>"",A10='Project Summary'!$C$3,C10<>""),COUNTIFS($A$2:$A10,'Project Summary'!$C$3,$C$2:$C10,"<>"),"")
L11: =IF(AND(A11<>"",A11='Project Summary'!$C$3,C11<>""),COUNTIFS($A$2:$A11,'Project Summary'!$C$3,$C$2:$C11,"<>"),"")
L12: =IF(AND(A12<>"",A12='Project Summary'!$C$3,C12<>""),COUNTIFS($A$2:$A12,'Project Summary'!$C$3,$C$2:$C12,"<>"),"")
L13: =IF(AND(A13<>"",A13='Project Summary'!$C$3,C13<>""),COUNTIFS($A$2:$A13,'Project Summary'!$C$3,$C$2:$C13,"<>"),"")
... L501: =IF(AND(A501<>"",A501='Project Summary'!$C$3,C501<>""),COUNTIFS($A$2:$A501,'Project Summary'!$C$3,$C$2:$C501,"<>"),"")

Sheet EOT Claims
A1: Project | B1: Reference | C1: Title | D1: Cause | E1: Description | F1: Days Claimed | G1: Days Granted | H1: Status | I1: Date Submitted | J1: Date Decided | K1: Notes | L1: Days Counted
L2: =IF(OR(C2="",H2<>"Approved"),0,IF(G2<>"",G2,N(F2))) -> 0
L3: =IF(OR(C3="",H3<>"Approved"),0,IF(G3<>"",G3,N(F3))) -> 0
L4: =IF(OR(C4="",H4<>"Approved"),0,IF(G4<>"",G4,N(F4))) -> 0
L5: =IF(OR(C5="",H5<>"Approved"),0,IF(G5<>"",G5,N(F5))) -> 0
L6: =IF(OR(C6="",H6<>"Approved"),0,IF(G6<>"",G6,N(F6))) -> 0
L7: =IF(OR(C7="",H7<>"Approved"),0,IF(G7<>"",G7,N(F7))) -> 0
L8: =IF(OR(C8="",H8<>"Approved"),0,IF(G8<>"",G8,N(F8))) -> 0
L9: =IF(OR(C9="",H9<>"Approved"),0,IF(G9<>"",G9,N(F9))) -> 0
L10: =IF(OR(C10="",H10<>"Approved"),0,IF(G10<>"",G10,N(F10))) -> 0
L11: =IF(OR(C11="",H11<>"Approved"),0,IF(G11<>"",G11,N(F11))) -> 0
L12: =IF(OR(C12="",H12<>"Approved"),0,IF(G12<>"",G12,N(F12))) -> 0
L13: =IF(OR(C13="",H13<>"Approved"),0,IF(G13<>"",G13,N(F13))) -> 0
... L501: =IF(OR(C501="",H501<>"Approved"),0,IF(G501<>"",G501,N(F501))) -> 0

Sheet Cash Flow
A1: Project | B1: Month | C1: Type | D1: Amount | E1: Month Key | F1: Counted Amount
E2: =IF(OR(A2="",B2=""),"",DATE(YEAR(B2),MONTH(B2),1)) | F2: =IF(OR(E2="",D2=""),0,IF(C2="Actual",D2,IF(COUNTIFS($A$2:$A$2001,A2,$E$2:$E$2001,E2,$C$2:$C$2001,"Actual")>0,0,D2))) -> 0
E3: =IF(OR(A3="",B3=""),"",DATE(YEAR(B3),MONTH(B3),1)) | F3: =IF(OR(E3="",D3=""),0,IF(C3="Actual",D3,IF(COUNTIFS($A$2:$A$2001,A3,$E$2:$E$2001,E3,$C$2:$C$2001,"Actual")>0,0,D3))) -> 0
E4: =IF(OR(A4="",B4=""),"",DATE(YEAR(B4),MONTH(B4),1)) | F4: =IF(OR(E4="",D4=""),0,IF(C4="Actual",D4,IF(COUNTIFS($A$2:$A$2001,A4,$E$2:$E$2001,E4,$C$2:$C$2001,"Actual")>0,0,D4))) -> 0
E5: =IF(OR(A5="",B5=""),"",DATE(YEAR(B5),MONTH(B5),1)) | F5: =IF(OR(E5="",D5=""),0,IF(C5="Actual",D5,IF(COUNTIFS($A$2:$A$2001,A5,$E$2:$E$2001,E5,$C$2:$C$2001,"Actual")>0,0,D5))) -> 0
E6: =IF(OR(A6="",B6=""),"",DATE(YEAR(B6),MONTH(B6),1)) | F6: =IF(OR(E6="",D6=""),0,IF(C6="Actual",D6,IF(COUNTIFS($A$2:$A$2001,A6,$E$2:$E$2001,E6,$C$2:$C$2001,"Actual")>0,0,D6))) -> 0
E7: =IF(OR(A7="",B7=""),"",DATE(YEAR(B7),MONTH(B7),1)) | F7: =IF(OR(E7="",D7=""),0,IF(C7="Actual",D7,IF(COUNTIFS($A$2:$A$2001,A7,$E$2:$E$2001,E7,$C$2:$C$2001,"Actual")>0,0,D7))) -> 0
E8: =IF(OR(A8="",B8=""),"",DATE(YEAR(B8),MONTH(B8),1)) | F8: =IF(OR(E8="",D8=""),0,IF(C8="Actual",D8,IF(COUNTIFS($A$2:$A$2001,A8,$E$2:$E$2001,E8,$C$2:$C$2001,"Actual")>0,0,D8))) -> 0
E9: =IF(OR(A9="",B9=""),"",DATE(YEAR(B9),MONTH(B9),1)) | F9: =IF(OR(E9="",D9=""),0,IF(C9="Actual",D9,IF(COUNTIFS($A$2:$A$2001,A9,$E$2:$E$2001,E9,$C$2:$C$2001,"Actual")>0,0,D9))) -> 0
E10: =IF(OR(A10="",B10=""),"",DATE(YEAR(B10),MONTH(B10),1)) | F10: =IF(OR(E10="",D10=""),0,IF(C10="Actual",D10,IF(COUNTIFS($A$2:$A$2001,A10,$E$2:$E$2001,E10,$C$2:$C$2001,"Actual")>0,0,D10))) -> 0
E11: =IF(OR(A11="",B11=""),"",DATE(YEAR(B11),MONTH(B11),1)) | F11: =IF(OR(E11="",D11=""),0,IF(C11="Actual",D11,IF(COUNTIFS($A$2:$A$2001,A11,$E$2:$E$2001,E11,$C$2:$C$2001,"Actual")>0,0,D11))) -> 0
E12: =IF(OR(A12="",B12=""),"",DATE(YEAR(B12),MONTH(B12),1)) | F12: =IF(OR(E12="",D12=""),0,IF(C12="Actual",D12,IF(COUNTIFS($A$2:$A$2001,A12,$E$2:$E$2001,E12,$C$2:$C$2001,"Actual")>0,0,D12))) -> 0
E13: =IF(OR(A13="",B13=""),"",DATE(YEAR(B13),MONTH(B13),1)) | F13: =IF(OR(E13="",D13=""),0,IF(C13="Actual",D13,IF(COUNTIFS($A$2:$A$2001,A13,$E$2:$E$2001,E13,$C$2:$C$2001,"Actual")>0,0,D13))) -> 0
... E2001: =IF(OR(A2001="",B2001=""),"",DATE(YEAR(B2001),MONTH(B2001),1)) | F2001: =IF(OR(E2001="",D2001=""),0,IF(C2001="Actual",D2001,IF(COUNTIFS($A$2:$A$2001,A2001,$E$2:$E$2001,E2001,$C$2:$C$2001,"Actual")>0,0,D2001))) -> 0

Sheet Milestones
A1: Project | B1: WBS Item | C1: Task / Activity | D1: % Complete | E1: Start Date | F1: Original Completion | G1: Forecast Completion | H1: Actual Completion | I1: Notes | J1: Slip (days) | K1: Summary Seq
J2: =IF(OR(C2="",F2="",G2=""),"",G2-F2) | K2: =IF(AND(A2<>"",A2='Project Summary'!$C$3,C2<>""),COUNTIFS($A$2:$A2,'Project Summary'!$C$3,$C$2:$C2,"<>"),"")
J3: =IF(OR(C3="",F3="",G3=""),"",G3-F3) | K3: =IF(AND(A3<>"",A3='Project Summary'!$C$3,C3<>""),COUNTIFS($A$2:$A3,'Project Summary'!$C$3,$C$2:$C3,"<>"),"")
J4: =IF(OR(C4="",F4="",G4=""),"",G4-F4) | K4: =IF(AND(A4<>"",A4='Project Summary'!$C$3,C4<>""),COUNTIFS($A$2:$A4,'Project Summary'!$C$3,$C$2:$C4,"<>"),"")
J5: =IF(OR(C5="",F5="",G5=""),"",G5-F5) | K5: =IF(AND(A5<>"",A5='Project Summary'!$C$3,C5<>""),COUNTIFS($A$2:$A5,'Project Summary'!$C$3,$C$2:$C5,"<>"),"")
J6: =IF(OR(C6="",F6="",G6=""),"",G6-F6) | K6: =IF(AND(A6<>"",A6='Project Summary'!$C$3,C6<>""),COUNTIFS($A$2:$A6,'Project Summary'!$C$3,$C$2:$C6,"<>"),"")
J7: =IF(OR(C7="",F7="",G7=""),"",G7-F7) | K7: =IF(AND(A7<>"",A7='Project Summary'!$C$3,C7<>""),COUNTIFS($A$2:$A7,'Project Summary'!$C$3,$C$2:$C7,"<>"),"")
J8: =IF(OR(C8="",F8="",G8=""),"",G8-F8) | K8: =IF(AND(A8<>"",A8='Project Summary'!$C$3,C8<>""),COUNTIFS($A$2:$A8,'Project Summary'!$C$3,$C$2:$C8,"<>"),"")
J9: =IF(OR(C9="",F9="",G9=""),"",G9-F9) | K9: =IF(AND(A9<>"",A9='Project Summary'!$C$3,C9<>""),COUNTIFS($A$2:$A9,'Project Summary'!$C$3,$C$2:$C9,"<>"),"")
J10: =IF(OR(C10="",F10="",G10=""),"",G10-F10) | K10: =IF(AND(A10<>"",A10='Project Summary'!$C$3,C10<>""),COUNTIFS($A$2:$A10,'Project Summary'!$C$3,$C$2:$C10,"<>"),"")
J11: =IF(OR(C11="",F11="",G11=""),"",G11-F11) | K11: =IF(AND(A11<>"",A11='Project Summary'!$C$3,C11<>""),COUNTIFS($A$2:$A11,'Project Summary'!$C$3,$C$2:$C11,"<>"),"")
J12: =IF(OR(C12="",F12="",G12=""),"",G12-F12) | K12: =IF(AND(A12<>"",A12='Project Summary'!$C$3,C12<>""),COUNTIFS($A$2:$A12,'Project Summary'!$C$3,$C$2:$C12,"<>"),"")
J13: =IF(OR(C13="",F13="",G13=""),"",G13-F13) | K13: =IF(AND(A13<>"",A13='Project Summary'!$C$3,C13<>""),COUNTIFS($A$2:$A13,'Project Summary'!$C$3,$C$2:$C13,"<>"),"")
... J501: =IF(OR(C501="",F501="",G501=""),"",G501-F501) | K501: =IF(AND(A501<>"",A501='Project Summary'!$C$3,C501<>""),COUNTIFS($A$2:$A501,'Project Summary'!$C$3,$C$2:$C501,"<>"),"")

Sheet Payment Claims
A1: Project | B1: Contract | C1: Claim Number | D1: Period Ending | E1: Claimed Amount | F1: Certified Amount | G1: Status | H1: Date Submitted | I1: Date Certified | J1: Date Paid | K1: Notes

Sheet Contracts
A1: Project | B1: Party Type | C1: Party Name | D1: Discipline / Scope | E1: Contract Number | F1: Contract Form | G1: Contract Value | H1: Contingency | I1: PO Value | J1: Provisional Items | K1: Retention % | L1: DLP Months | M1: Execution Date | N1: Start Date | O1: Completion Date | P1: Status | Q1: Notes | R1: Claimed to Date | S1: Remaining
R2: =IF(C2="","",SUMIFS('Payment Claims'!$E$2:$E$501,'Payment Claims'!$A$2:$A$501,A2,'Payment Claims'!$B$2:$B$501,C2,'Payment Claims'!$G$2:$G$501,"<>Disputed")) | S2: =IF(OR(C2="",G2=""),"",G2-R2)
R3: =IF(C3="","",SUMIFS('Payment Claims'!$E$2:$E$501,'Payment Claims'!$A$2:$A$501,A3,'Payment Claims'!$B$2:$B$501,C3,'Payment Claims'!$G$2:$G$501,"<>Disputed")) | S3: =IF(OR(C3="",G3=""),"",G3-R3)
R4: =IF(C4="","",SUMIFS('Payment Claims'!$E$2:$E$501,'Payment Claims'!$A$2:$A$501,A4,'Payment Claims'!$B$2:$B$501,C4,'Payment Claims'!$G$2:$G$501,"<>Disputed")) | S4: =IF(OR(C4="",G4=""),"",G4-R4)
R5: =IF(C5="","",SUMIFS('Payment Claims'!$E$2:$E$501,'Payment Claims'!$A$2:$A$501,A5,'Payment Claims'!$B$2:$B$501,C5,'Payment Claims'!$G$2:$G$501,"<>Disputed")) | S5: =IF(OR(C5="",G5=""),"",G5-R5)
R6: =IF(C6="","",SUMIFS('Payment Claims'!$E$2:$E$501,'Payment Claims'!$A$2:$A$501,A6,'Payment Claims'!$B$2:$B$501,C6,'Payment Claims'!$G$2:$G$501,"<>Disputed")) | S6: =IF(OR(C6="",G6=""),"",G6-R6)
R7: =IF(C7="","",SUMIFS('Payment Claims'!$E$2:$E$501,'Payment Claims'!$A$2:$A$501,A7,'Payment Claims'!$B$2:$B$501,C7,'Payment Claims'!$G$2:$G$501,"<>Disputed")) | S7: =IF(OR(C7="",G7=""),"",G7-R7)
R8: =IF(C8="","",SUMIFS('Payment Claims'!$E$2:$E$501,'Payment Claims'!$A$2:$A$501,A8,'Payment Claims'!$B$2:$B$501,C8,'Payment Claims'!$G$2:$G$501,"<>Disputed")) | S8: =IF(OR(C8="",G8=""),"",G8-R8)
R9: =IF(C9="","",SUMIFS('Payment Claims'!$E$2:$E$501,'Payment Claims'!$A$2:$A$501,A9,'Payment Claims'!$B$2:$B$501,C9,'Payment Claims'!$G$2:$G$501,"<>Disputed")) | S9: =IF(OR(C9="",G9=""),"",G9-R9)
